{"pokemons": {"Sylveon": {"win": 73, "lost": 28, "players": {"Xante": {"win": 0, "lost": 1, "battle_sets": {"Hyper Voice_Calm Mind_XSpeed": {"win": 0, "lost": 1}}}, "ShreyNHK": {"win": 1, "lost": 0, "battle_sets": {"Hyper Voice_Calm Mind_EjectButton": {"win": 1, "lost": 0}}}, "RJG\u30fbRuvis": {"win": 5, "lost": 1, "battle_sets": {"Hyper Voice_Calm Mind_XSpeed": {"win": 4, "lost": 1}, "Hyper Voice_Draining Kiss_XSpeed": {"win": 1, "lost": 0}}}, "KlausVIII": {"win": 7, "lost": 1, "battle_sets": {"Hyper Voice_Calm Mind_XSpeed": {"win": 7, "lost": 1}}}, "Wulf?": {"win": 3, "lost": 0, "battle_sets": {"Hyper Voice_Calm Mind_XSpeed": {"win": 3, "lost": 0}}}, "nayeon": {"win": 1, "lost": 0, "battle_sets": {"Hyper Voice_Calm Mind_XSpeed": {"win": 1, "lost": 0}}}, "Jjacky": {"win": 2, "lost": 1, "battle_sets": {"Hyper Voice_Calm Mind_XSpeed": {"win": 2, "lost": 1}}}, "5i\u30fbInferno": {"win": 1, "lost": 1, "battle_sets": {"Hyper Voice_Calm Mind_EjectButton": {"win": 1, "lost": 1}}}, "AkumaCx": {"win": 1, "lost": 1, "battle_sets": {"Hyper Voice_Calm Mind_XSpeed": {"win": 1, "lost": 1}}}, "dordori": {"win": 1, "lost": 0, "battle_sets": {"Hyper Voice_Calm Mind_XSpeed": {"win": 1, "lost": 0}}}, "ttvSixsies": {"win": 0, "lost": 1, "battle_sets": {"Hyper Voice_Calm Mind_XSpeed": {"win": 0, "lost": 1}}}, "BB\u30fbSkyfire": {"win": 29, "lost": 8, "battle_sets": {"Hyper Voice_Calm Mind_XSpeed": {"win": 29, "lost": 8}}}, "\u5b9f\u306f\u30d4\u30af\u30bd\u30eb": {"win": 1, "lost": 0, "battle_sets": {"Hyper Voice_Calm Mind_XSpeed": {"win": 1, "lost": 0}}}, "ADESu23\u30fbTTV": {"win": 2, "lost": 0, "battle_sets": {"Hyper Voice_Calm Mind_XSpeed": {"win": 2, "lost": 0}}}, "Jaypa\u30c4": {"win": 3, "lost": 0, "battle_sets": {"Hyper Voice_Calm Mind_XSpeed": {"win": 3, "lost": 0}}}, "\u663c\u5bdd\u3072\u307f": {"win": 15, "lost": 13, "battle_sets": {"Hyper Voice_Calm Mind_EjectButton": {"win": 15, "lost": 13}}}, "\u6953\u5c02\u304b\u3073\u304d\u3089": {"win": 1, "lost": 0, "battle_sets": {"Hyper Voice_Calm Mind_XSpeed": {"win": 1, "lost": 0}}}}, "battle_sets": {"Hyper Voice_Calm Mind_XSpeed": {"win": 55, "lost": 14}, "Hyper Voice_Calm Mind_EjectButton": {"win": 17, "lost": 14}, "Hyper Voice_Draining Kiss_XSpeed": {"win": 1, "lost": 0}}}, "Slowbro": {"win": 25, "lost": 8, "players": {"Xante": {"win": 2, "lost": 1, "battle_sets": {"__XSpeed": {"win": 2, "lost": 1}}}, "PotatoUwU": {"win": 10, "lost": 3, "battle_sets": {"__XSpeed": {"win": 10, "lost": 3}}}, "ttvGhatlue": {"win": 2, "lost": 0, "battle_sets": {"__XSpeed": {"win": 2, "lost": 0}}}, "5i\u30fbInferno": {"win": 1, "lost": 0, "battle_sets": {"__Potion": {"win": 1, "lost": 0}}}, "AkumaCx": {"win": 1, "lost": 1, "battle_sets": {"__Potion": {"win": 1, "lost": 1}}}, "BB\u30fbOsIrIs": {"win": 0, "lost": 1, "battle_sets": {"__Potion": {"win": 0, "lost": 1}}}, "ttvSixsies": {"win": 4, "lost": 0, "battle_sets": {"__XSpeed": {"win": 4, "lost": 0}}}, "STMN\u30fbFroy": {"win": 2, "lost": 0, "battle_sets": {"__Potion": {"win": 2, "lost": 0}}}, "Jaypa\u30c4": {"win": 2, "lost": 2, "battle_sets": {"__Potion": {"win": 2, "lost": 2}}}, "\u6953\u5c02\u304b\u3073\u304d\u3089": {"win": 1, "lost": 0, "battle_sets": {"__Potion": {"win": 1, "lost": 0}}}}, "battle_sets": {"__XSpeed": {"win": 18, "lost": 4}, "__Potion": {"win": 7, "lost": 4}}}, "Lucario": {"win": 231, "lost": 100, "players": {"Xante": {"win": 4, "lost": 0, "battle_sets": {"Power-Up Punch_Close Combat_XSpeed": {"win": 4, "lost": 0}}}, "KlausVIII": {"win": 8, "lost": 4, "battle_sets": {"Power-Up Punch_Close Combat_XSpeed": {"win": 4, "lost": 4}, "Extreme Speed_Bone Rush_XSpeed": {"win": 4, "lost": 0}}}, "Wablet?": {"win": 27, "lost": 2, "battle_sets": {"Extreme Speed_Bone Rush_Purify": {"win": 27, "lost": 2}}}, "Wulf?": {"win": 0, "lost": 2, "battle_sets": {"Extreme Speed_Bone Rush_Purify": {"win": 0, "lost": 2}}}, "Metallic\u30c4": {"win": 1, "lost": 1, "battle_sets": {"Extreme Speed_Bone Rush_Purify": {"win": 1, "lost": 1}}}, "\u9811\u5f35\u308d\u3046ww": {"win": 1, "lost": 1, "battle_sets": {"Extreme Speed_Bone Rush_Purify": {"win": 1, "lost": 1}}}, "R0juu": {"win": 3, "lost": 2, "battle_sets": {"Power-Up Punch_Close Combat_XAttack": {"win": 3, "lost": 2}}}, "ttvGhatlue": {"win": 0, "lost": 1, "battle_sets": {"Power-Up Punch_Close Combat_XSpeed": {"win": 0, "lost": 1}}}, "ENT\u30fbScepTer": {"win": 2, "lost": 2, "battle_sets": {"Extreme Speed_Bone Rush_Purify": {"win": 2, "lost": 2}}}, "OMO\u30e1Phoenix": {"win": 1, "lost": 0, "battle_sets": {"Power-Up Punch_Close Combat_EjectButton": {"win": 1, "lost": 0}}}, "5i\u30fbInferno": {"win": 0, "lost": 1, "battle_sets": {"Power-Up Punch_Close Combat_XSpeed": {"win": 0, "lost": 1}}}, "Kenoken": {"win": 10, "lost": 4, "battle_sets": {"Extreme Speed_Bone Rush_XSpeed": {"win": 6, "lost": 2}, "Power-Up Punch_Close Combat_XSpeed": {"win": 2, "lost": 1}, "Extreme Speed_Close Combat_XSpeed": {"win": 1, "lost": 0}, "Extreme Speed_Bone Rush_XAttack": {"win": 0, "lost": 1}, "Extreme Speed_Close Combat_XAttack": {"win": 1, "lost": 0}}}, "MW\u30fbAngel\u30b7": {"win": 1, "lost": 1, "battle_sets": {"Power-Up Punch_Close Combat_XAttack": {"win": 1, "lost": 1}}}, "KyluK?": {"win": 14, "lost": 5, "battle_sets": {"Extreme Speed_Bone Rush_Purify": {"win": 13, "lost": 4}, "Power-Up Punch_Close Combat_Purify": {"win": 1, "lost": 0}, "Power-Up Punch_Bone Rush_Purify": {"win": 0, "lost": 1}}}, "dordori": {"win": 3, "lost": 2, "battle_sets": {"Extreme Speed_Bone Rush_Purify": {"win": 3, "lost": 2}}}, "AramisCe": {"win": 12, "lost": 6, "battle_sets": {"Extreme Speed_Bone Rush_XSpeed": {"win": 10, "lost": 5}, "Extreme Speed_Close Combat_XSpeed": {"win": 1, "lost": 0}, "Power-Up Punch_Close Combat_XSpeed": {"win": 1, "lost": 1}}}, "\ub108\ub3c4\ub0b4\uaebc": {"win": 8, "lost": 6, "battle_sets": {"Extreme Speed_Bone Rush_Purify": {"win": 8, "lost": 6}}}, "STMN\u30fbTexas": {"win": 0, "lost": 1, "battle_sets": {"Power-Up Punch_Close Combat_XAttack": {"win": 0, "lost": 1}}}, "ttvSixsies": {"win": 2, "lost": 2, "battle_sets": {"Power-Up Punch_Close Combat_XSpeed": {"win": 0, "lost": 1}, "Power-Up Punch_Bone Rush_XSpeed": {"win": 2, "lost": 1}}}, "Aurimakii": {"win": 14, "lost": 6, "battle_sets": {"Extreme Speed_Bone Rush_XSpeed": {"win": 9, "lost": 4}, "Extreme Speed_Close Combat_XSpeed": {"win": 4, "lost": 2}, "Power-Up Punch_Close Combat_XSpeed": {"win": 1, "lost": 0}}}, "STMN\u30fbFroy": {"win": 1, "lost": 2, "battle_sets": {"Extreme Speed_Bone Rush_XAttack": {"win": 1, "lost": 2}}}, "\u3042_\u3052": {"win": 0, "lost": 2, "battle_sets": {"Extreme Speed_Bone Rush_Purify": {"win": 0, "lost": 2}}}, "BB\u30fbSkyfire": {"win": 2, "lost": 0, "battle_sets": {"Power-Up Punch_Close Combat_XSpeed": {"win": 1, "lost": 0}, "Extreme Speed_Bone Rush_XSpeed": {"win": 1, "lost": 0}}}, "OMO\u30e1Nafylno": {"win": 9, "lost": 3, "battle_sets": {"Extreme Speed_Bone Rush_Purify": {"win": 9, "lost": 3}}}, "S\u012bmp": {"win": 8, "lost": 0, "battle_sets": {"Extreme Speed_Bone Rush_XAttack": {"win": 4, "lost": 0}, "Power-Up Punch_Close Combat_XAttack": {"win": 4, "lost": 0}}}, "Espoir\u0421\u0432\u0451\u0442": {"win": 30, "lost": 14, "battle_sets": {"Extreme Speed_Bone Rush_Purify": {"win": 30, "lost": 13}, "Power-Up Punch_Close Combat_XSpeed": {"win": 0, "lost": 1}}}, "Trafyyy": {"win": 1, "lost": 0, "battle_sets": {"Power-Up Punch_Bone Rush_EjectButton": {"win": 1, "lost": 0}}}, "\u304b\u3073\u304d\u3089\u5c02\u6953": {"win": 25, "lost": 8, "battle_sets": {"Extreme Speed_Bone Rush_Purify": {"win": 25, "lost": 8}}}, "GyZ": {"win": 1, "lost": 0, "battle_sets": {"Extreme Speed_Close Combat_XSpeed": {"win": 1, "lost": 0}}}, "TILTED\u00d7Y\u00fbta": {"win": 2, "lost": 1, "battle_sets": {"Power-Up Punch_Close Combat_XSpeed": {"win": 2, "lost": 1}}}, "\u30fbJohn\u30fb": {"win": 1, "lost": 0, "battle_sets": {"Extreme Speed_Bone Rush_Purify": {"win": 1, "lost": 0}}}, "T2_Mame": {"win": 0, "lost": 1, "battle_sets": {"Extreme Speed_Bone Rush_Purify": {"win": 0, "lost": 1}}}, "Evilgenius2": {"win": 5, "lost": 0, "battle_sets": {"Extreme Speed_Bone Rush_Purify": {"win": 5, "lost": 0}}}, "\u5b9f\u306f\u30d4\u30af\u30bd\u30eb": {"win": 13, "lost": 7, "battle_sets": {"Extreme Speed_Bone Rush_Purify": {"win": 9, "lost": 7}, "Power-Up Punch_Close Combat_XAttack": {"win": 4, "lost": 0}}}, "\ud6c8\ud3ec\ub3c4": {"win": 1, "lost": 1, "battle_sets": {"Extreme Speed_Bone Rush_Purify": {"win": 1, "lost": 1}}}, "\u79cb\u6d25\u831c": {"win": 9, "lost": 3, "battle_sets": {"Extreme Speed_Bone Rush_Purify": {"win": 9, "lost": 3}}}, "Jaypa\u30c4": {"win": 0, "lost": 1, "battle_sets": {"Extreme Speed_Bone Rush_XSpeed": {"win": 0, "lost": 1}}}, "Cr\u00f3ng": {"win": 0, "lost": 1, "battle_sets": {"Extreme Speed_Bone Rush_Purify": {"win": 0, "lost": 1}}}, "RENAMED": {"win": 2, "lost": 3, "battle_sets": {"Extreme Speed_Bone Rush_Purify": {"win": 2, "lost": 3}}}, "Overseert": {"win": 8, "lost": 4, "battle_sets": {"Extreme Speed_Bone Rush_XSpeed": {"win": 8, "lost": 4}}}, "ryanxoxo": {"win": 2, "lost": 0, "battle_sets": {"Extreme Speed_Bone Rush_XSpeed": {"win": 2, "lost": 0}}}}, "battle_sets": {"Power-Up Punch_Close Combat_XSpeed": {"win": 15, "lost": 11}, "Extreme Speed_Bone Rush_XSpeed": {"win": 40, "lost": 16}, "Extreme Speed_Bone Rush_Purify": {"win": 146, "lost": 62}, "Power-Up Punch_Close Combat_XAttack": {"win": 12, "lost": 4}, "Power-Up Punch_Close Combat_EjectButton": {"win": 1, "lost": 0}, "Extreme Speed_Close Combat_XSpeed": {"win": 7, "lost": 2}, "Extreme Speed_Bone Rush_XAttack": {"win": 5, "lost": 3}, "Extreme Speed_Close Combat_XAttack": {"win": 1, "lost": 0}, "Power-Up Punch_Close Combat_Purify": {"win": 1, "lost": 0}, "Power-Up Punch_Bone Rush_Purify": {"win": 0, "lost": 1}, "Power-Up Punch_Bone Rush_XSpeed": {"win": 2, "lost": 1}, "Power-Up Punch_Bone Rush_EjectButton": {"win": 1, "lost": 0}}}, "Machamp": {"win": 72, "lost": 28, "players": {"Xante": {"win": 1, "lost": 0, "battle_sets": {"Cross Chop_Dynamic Punch_EjectButton": {"win": 1, "lost": 0}}}, "ShreyNHK": {"win": 0, "lost": 1, "battle_sets": {"Close Combat_Dynamic Punch_EjectButton": {"win": 0, "lost": 1}}}, "RJG\u30fbRuvis": {"win": 4, "lost": 3, "battle_sets": {"Close Combat_Dynamic Punch_EjectButton": {"win": 4, "lost": 3}}}, "KlausVIII": {"win": 3, "lost": 1, "battle_sets": {"Cross Chop_Dynamic Punch_EjectButton": {"win": 3, "lost": 1}}}, "Metallic\u30c4": {"win": 1, "lost": 0, "battle_sets": {"Close Combat_Dynamic Punch_EjectButton": {"win": 1, "lost": 0}}}, "R0juu": {"win": 13, "lost": 9, "battle_sets": {"Close Combat_Dynamic Punch_EjectButton": {"win": 5, "lost": 5}, "Close Combat_Dynamic Punch_XAttack": {"win": 8, "lost": 4}}}, "caligola999": {"win": 3, "lost": 0, "battle_sets": {"Cross Chop_Dynamic Punch_EjectButton": {"win": 3, "lost": 0}}}, "5i\u30fbInferno": {"win": 5, "lost": 2, "battle_sets": {"Cross Chop_Dynamic Punch_EjectButton": {"win": 5, "lost": 2}}}, "Kenoken": {"win": 2, "lost": 0, "battle_sets": {"Close Combat_Dynamic Punch_EjectButton": {"win": 1, "lost": 0}, "Cross Chop_Dynamic Punch_EjectButton": {"win": 1, "lost": 0}}}, "dordori": {"win": 0, "lost": 1, "battle_sets": {"Close Combat_Dynamic Punch_EjectButton": {"win": 0, "lost": 1}}}, "STMN\u30fbTexas": {"win": 2, "lost": 0, "battle_sets": {"Cross Chop_Dynamic Punch_EjectButton": {"win": 1, "lost": 0}, "Close Combat_Dynamic Punch_EjectButton": {"win": 1, "lost": 0}}}, "99\u30e0\u4efb\u4e49\u4f1f": {"win": 2, "lost": 0, "battle_sets": {"Cross Chop_Dynamic Punch_XAttack": {"win": 2, "lost": 0}}}, "99\u30e0Sensei": {"win": 0, "lost": 1, "battle_sets": {"Cross Chop_Dynamic Punch_XAttack": {"win": 0, "lost": 1}}}, "TtvPikaGod22": {"win": 4, "lost": 0, "battle_sets": {"Close Combat_Dynamic Punch_EjectButton": {"win": 4, "lost": 0}}}, "DanielMil": {"win": 7, "lost": 1, "battle_sets": {"Cross Chop_Dynamic Punch_XSpeed": {"win": 3, "lost": 1}, "Close Combat_Dynamic Punch_XSpeed": {"win": 1, "lost": 0}, "Cross Chop_Dynamic Punch_EjectButton": {"win": 2, "lost": 0}, "Close Combat_Dynamic Punch_EjectButton": {"win": 1, "lost": 0}}}, "BB\u30fbSkyfire": {"win": 0, "lost": 1, "battle_sets": {"Close Combat_Dynamic Punch_EjectButton": {"win": 0, "lost": 1}}}, "S\u012bmp": {"win": 2, "lost": 2, "battle_sets": {"Cross Chop_Dynamic Punch_XAttack": {"win": 2, "lost": 2}}}, "Espoir\u0421\u0432\u0451\u0442": {"win": 1, "lost": 0, "battle_sets": {"Cross Chop_Dynamic Punch_EjectButton": {"win": 1, "lost": 0}}}, "GyZ": {"win": 3, "lost": 1, "battle_sets": {"Cross Chop_Dynamic Punch_EjectButton": {"win": 3, "lost": 1}}}, "EMPxSorA\u53f3": {"win": 1, "lost": 0, "battle_sets": {"Close Combat_Dynamic Punch_EjectButton": {"win": 1, "lost": 0}}}, "TILTED\u00d7Y\u00fbta": {"win": 1, "lost": 0, "battle_sets": {"Cross Chop_Dynamic Punch_EjectButton": {"win": 1, "lost": 0}}}, "\u30fbJohn\u30fb": {"win": 1, "lost": 0, "battle_sets": {"Cross Chop_Dynamic Punch_EjectButton": {"win": 1, "lost": 0}}}, "\u5b9f\u306f\u30d4\u30af\u30bd\u30eb": {"win": 1, "lost": 0, "battle_sets": {"Cross Chop_Dynamic Punch_EjectButton": {"win": 1, "lost": 0}}}, "Pikachichu": {"win": 15, "lost": 3, "battle_sets": {"Cross Chop_Dynamic Punch_EjectButton": {"win": 15, "lost": 3}}}, "Jaypa\u30c4": {"win": 0, "lost": 1, "battle_sets": {"Cross Chop_Dynamic Punch_EjectButton": {"win": 0, "lost": 1}}}, "Overseert": {"win": 0, "lost": 1, "battle_sets": {"Cross Chop_Dynamic Punch_EjectButton": {"win": 0, "lost": 1}}}}, "battle_sets": {"Cross Chop_Dynamic Punch_EjectButton": {"win": 38, "lost": 9}, "Close Combat_Dynamic Punch_EjectButton": {"win": 18, "lost": 11}, "Close Combat_Dynamic Punch_XAttack": {"win": 8, "lost": 4}, "Cross Chop_Dynamic Punch_XAttack": {"win": 4, "lost": 3}, "Cross Chop_Dynamic Punch_XSpeed": {"win": 3, "lost": 1}, "Close Combat_Dynamic Punch_XSpeed": {"win": 1, "lost": 0}}}, "Trevenant": {"win": 37, "lost": 14, "players": {"Xante": {"win": 0, "lost": 1, "battle_sets": {"Curse_Horn Leech_Potion": {"win": 0, "lost": 1}}}, "ttvGhatlue": {"win": 1, "lost": 0, "battle_sets": {"Curse_Horn Leech_Tail": {"win": 1, "lost": 0}}}, "ENT\u30fbScepTer": {"win": 2, "lost": 0, "battle_sets": {"Curse_Horn Leech_Potion": {"win": 2, "lost": 0}}}, "99\u30e0Sensei": {"win": 4, "lost": 0, "battle_sets": {"Curse_Horn Leech_Potion": {"win": 4, "lost": 0}}}, "TtvPikaGod22": {"win": 1, "lost": 2, "battle_sets": {"Curse_Horn Leech_Potion": {"win": 1, "lost": 2}}}, "STMN\u30fbFroy": {"win": 18, "lost": 2, "battle_sets": {"Curse_Horn Leech_Potion": {"win": 18, "lost": 2}}}, "EMPxSorA\u53f3": {"win": 1, "lost": 1, "battle_sets": {"Curse_Horn Leech_Potion": {"win": 1, "lost": 1}}}, "\u663c\u5bdd\u3072\u307f": {"win": 2, "lost": 1, "battle_sets": {"Curse_Horn Leech_Potion": {"win": 2, "lost": 1}}}, "McToffin": {"win": 8, "lost": 7, "battle_sets": {"Curse_Horn Leech_EjectButton": {"win": 8, "lost": 7}}}}, "battle_sets": {"Curse_Horn Leech_Potion": {"win": 28, "lost": 7}, "Curse_Horn Leech_Tail": {"win": 1, "lost": 0}, "Curse_Horn Leech_EjectButton": {"win": 8, "lost": 7}}}, "Aegislash": {"win": 4, "lost": 6, "players": {"Xante": {"win": 0, "lost": 1, "battle_sets": {"Sacred Sword_Wide Guard_Purify": {"win": 0, "lost": 1}}}, "RJG\u30fbRuvis": {"win": 0, "lost": 1, "battle_sets": {"Sacred Sword_Wide Guard_Potion": {"win": 0, "lost": 1}}}, "ttvGhatlue": {"win": 0, "lost": 1, "battle_sets": {"Shadow Claw_Wide Guard_Purify": {"win": 0, "lost": 1}}}, "KyluK?": {"win": 1, "lost": 0, "battle_sets": {"Sacred Sword_Wide Guard_Purify": {"win": 1, "lost": 0}}}, "AramisCe": {"win": 0, "lost": 1, "battle_sets": {"Shadow Claw_Wide Guard_EjectButton": {"win": 0, "lost": 1}}}, "OMO\u30e1Nafylno": {"win": 0, "lost": 1, "battle_sets": {"Sacred Sword_Wide Guard_EjectButton": {"win": 0, "lost": 1}}}, "S\u012bmp": {"win": 0, "lost": 1, "battle_sets": {"Sacred Sword_Wide Guard_XAttack": {"win": 0, "lost": 1}}}, "Overseert": {"win": 3, "lost": 0, "battle_sets": {"Sacred Sword_Wide Guard_XSpeed": {"win": 3, "lost": 0}}}}, "battle_sets": {"Sacred Sword_Wide Guard_Purify": {"win": 1, "lost": 1}, "Sacred Sword_Wide Guard_Potion": {"win": 0, "lost": 1}, "Shadow Claw_Wide Guard_Purify": {"win": 0, "lost": 1}, "Shadow Claw_Wide Guard_EjectButton": {"win": 0, "lost": 1}, "Sacred Sword_Wide Guard_EjectButton": {"win": 0, "lost": 1}, "Sacred Sword_Wide Guard_XAttack": {"win": 0, "lost": 1}, "Sacred Sword_Wide Guard_XSpeed": {"win": 3, "lost": 0}}}, "Delphox": {"win": 22, "lost": 11, "players": {"Xante": {"win": 1, "lost": 0, "battle_sets": {"Mystical Fire_Fire Spin_EjectButton": {"win": 1, "lost": 0}}}, "ShreyNHK": {"win": 1, "lost": 0, "battle_sets": {"Mystical Fire_Fire Spin_EjectButton": {"win": 1, "lost": 0}}}, "RJG\u30fbRuvis": {"win": 0, "lost": 1, "battle_sets": {"Mystical Fire_Flame Charge_EjectButton": {"win": 0, "lost": 1}}}, "TE\u30fb999": {"win": 3, "lost": 3, "battle_sets": {"Mystical Fire_Fire Spin_XSpeed": {"win": 3, "lost": 3}}}, "CeS\u68a6Inf\u00ed": {"win": 2, "lost": 0, "battle_sets": {"Mystical Fire_Fire Spin_XSpeed": {"win": 2, "lost": 0}}}, "99\u30e0\u4efb\u4e49\u4f1f": {"win": 2, "lost": 0, "battle_sets": {"Mystical Fire_Flame Charge_EjectButton": {"win": 2, "lost": 0}}}, "CeS\u68a6KiD": {"win": 3, "lost": 1, "battle_sets": {"Mystical Fire_Fire Spin_XSpeed": {"win": 3, "lost": 1}}}, "\u6b7batited04": {"win": 0, "lost": 1, "battle_sets": {"Mystical Fire_Fire Spin_EjectButton": {"win": 0, "lost": 1}}}, "\u3042_\u3052": {"win": 1, "lost": 1, "battle_sets": {"Mystical Fire_Fire Spin_EjectButton": {"win": 1, "lost": 1}}}, "Trafyyy": {"win": 2, "lost": 0, "battle_sets": {"Mystical Fire_Fire Spin_EjectButton": {"win": 1, "lost": 0}, "Fire Blast_Fire Spin_EjectButton": {"win": 1, "lost": 0}}}, "GyZ": {"win": 4, "lost": 2, "battle_sets": {"Mystical Fire_Fire Spin_XSpeed": {"win": 4, "lost": 2}}}, "ADESu23\u30fbTTV": {"win": 1, "lost": 0, "battle_sets": {"Mystical Fire_Flame Charge_EjectButton": {"win": 1, "lost": 0}}}, "ryanxoxo": {"win": 2, "lost": 2, "battle_sets": {"Mystical Fire_Fire Spin_EjectButton": {"win": 2, "lost": 2}}}}, "battle_sets": {"Mystical Fire_Fire Spin_EjectButton": {"win": 6, "lost": 4}, "Mystical Fire_Flame Charge_EjectButton": {"win": 3, "lost": 1}, "Mystical Fire_Fire Spin_XSpeed": {"win": 12, "lost": 6}, "Fire Blast_Fire Spin_EjectButton": {"win": 1, "lost": 0}}}, "Zeraora": {"win": 58, "lost": 29, "players": {"Xante": {"win": 1, "lost": 1, "battle_sets": {"Volt Switch_Discharge_Potion": {"win": 1, "lost": 0}, "Volt Switch_Discharge_XAttack": {"win": 0, "lost": 1}}}, "ShreyNHK": {"win": 1, "lost": 0, "battle_sets": {"Volt Switch_Discharge_XAttack": {"win": 1, "lost": 0}}}, "Wulf?": {"win": 1, "lost": 0, "battle_sets": {"Volt Switch_Discharge_XAttack": {"win": 1, "lost": 0}}}, "Metallic\u30c4": {"win": 4, "lost": 0, "battle_sets": {"Spark_Discharge_XAttack": {"win": 4, "lost": 0}}}, "AFR\u30fbMiva": {"win": 1, "lost": 0, "battle_sets": {"Volt Switch_Discharge_XAttack": {"win": 1, "lost": 0}}}, "ENT\u30fbScepTer": {"win": 1, "lost": 1, "battle_sets": {"Volt Switch_Discharge_XAttack": {"win": 1, "lost": 1}}}, "OMO\u30e1Phoenix": {"win": 0, "lost": 1, "battle_sets": {"Volt Switch_Discharge_XAttack": {"win": 0, "lost": 1}}}, "MW\u30fbAngel\u30b7": {"win": 14, "lost": 3, "battle_sets": {"Volt Switch_Discharge_XAttack": {"win": 14, "lost": 3}}}, "KyluK?": {"win": 1, "lost": 1, "battle_sets": {"Volt Switch_Discharge_XAttack": {"win": 1, "lost": 1}}}, "AkumaCx": {"win": 1, "lost": 1, "battle_sets": {"Volt Switch_Discharge_XAttack": {"win": 1, "lost": 1}}}, "dordori": {"win": 8, "lost": 3, "battle_sets": {"Volt Switch_Discharge_XAttack": {"win": 8, "lost": 3}}}, "Aurimakii": {"win": 2, "lost": 1, "battle_sets": {"Volt Switch_Discharge_XAttack": {"win": 2, "lost": 1}}}, "CeS\u68a6KiD": {"win": 7, "lost": 1, "battle_sets": {"Volt Switch_Discharge_XAttack": {"win": 7, "lost": 1}}}, "MugiwarcTTV": {"win": 1, "lost": 2, "battle_sets": {"Spark_Discharge_XAttack": {"win": 1, "lost": 1}, "Volt Switch_Discharge_XAttack": {"win": 0, "lost": 1}}}, "BB\u30fbSkyfire": {"win": 0, "lost": 2, "battle_sets": {"Volt Switch_Discharge_Purify": {"win": 0, "lost": 2}}}, "S\u012bmp": {"win": 5, "lost": 1, "battle_sets": {"Volt Switch_Discharge_XAttack": {"win": 5, "lost": 1}}}, "EMPxSorA\u53f3": {"win": 1, "lost": 0, "battle_sets": {"Volt Switch_Discharge_EjectButton": {"win": 1, "lost": 0}}}, "\u30fbJohn\u30fb": {"win": 2, "lost": 2, "battle_sets": {"Volt Switch_Discharge_Purify": {"win": 2, "lost": 1}, "Volt Switch_Discharge_XAttack": {"win": 0, "lost": 1}}}, "S4L-": {"win": 5, "lost": 6, "battle_sets": {"Volt Switch_Discharge_XAttack": {"win": 5, "lost": 6}}}, "\ud6c8\ud3ec\ub3c4": {"win": 1, "lost": 1, "battle_sets": {"Volt Switch_Discharge_XAttack": {"win": 1, "lost": 1}}}, "Jaypa\u30c4": {"win": 0, "lost": 1, "battle_sets": {"Volt Switch_Discharge_EjectButton": {"win": 0, "lost": 1}}}, "Cr\u00f3ng": {"win": 1, "lost": 0, "battle_sets": {"Volt Switch_Discharge_Purify": {"win": 1, "lost": 0}}}, "\u6953\u5c02\u304b\u3073\u304d\u3089": {"win": 0, "lost": 1, "battle_sets": {"Volt Switch_Discharge_Purify": {"win": 0, "lost": 1}}}}, "battle_sets": {"Volt Switch_Discharge_Potion": {"win": 1, "lost": 0}, "Volt Switch_Discharge_XAttack": {"win": 48, "lost": 23}, "Spark_Discharge_XAttack": {"win": 5, "lost": 1}, "Volt Switch_Discharge_Purify": {"win": 3, "lost": 4}, "Volt Switch_Discharge_EjectButton": {"win": 1, "lost": 1}}}, "Glaceon": {"win": 173, "lost": 83, "players": {"Xante": {"win": 11, "lost": 4, "battle_sets": {"_Ice Shard_EjectButton": {"win": 3, "lost": 2}, "_Ice Shard_XSpeed": {"win": 8, "lost": 2}}}, "PotatoUwU": {"win": 0, "lost": 1, "battle_sets": {"_Ice Shard_XSpeed": {"win": 0, "lost": 1}}}, "ShreyNHK": {"win": 18, "lost": 6, "battle_sets": {"_Ice Shard_XSpeed": {"win": 18, "lost": 5}, "__XSpeed": {"win": 0, "lost": 1}}}, "Wulf?": {"win": 0, "lost": 1, "battle_sets": {"_Ice Shard_XSpeed": {"win": 0, "lost": 1}}}, "Metallic\u30c4": {"win": 7, "lost": 1, "battle_sets": {"_Ice Shard_XSpeed": {"win": 7, "lost": 1}}}, "ttvGhatlue": {"win": 1, "lost": 0, "battle_sets": {"_Ice Shard_XSpeed": {"win": 1, "lost": 0}}}, "ENT\u30fbScepTer": {"win": 6, "lost": 3, "battle_sets": {"_Ice Shard_XSpeed": {"win": 3, "lost": 2}, "__XSpeed": {"win": 2, "lost": 1}, "_Ice Shard_Purify": {"win": 1, "lost": 0}}}, "caligola999": {"win": 4, "lost": 4, "battle_sets": {"_Ice Shard_EjectButton": {"win": 4, "lost": 4}}}, "OMO\u30e1Phoenix": {"win": 17, "lost": 4, "battle_sets": {"_Ice Shard_XSpeed": {"win": 17, "lost": 4}}}, "5i\u30fbInferno": {"win": 1, "lost": 1, "battle_sets": {"_Ice Shard_EjectButton": {"win": 1, "lost": 1}}}, "MW\u30fbAngel\u30b7": {"win": 2, "lost": 3, "battle_sets": {"_Ice Shard_XSpeed": {"win": 2, "lost": 3}}}, "AkumaCx": {"win": 2, "lost": 1, "battle_sets": {"_Ice Shard_XSpeed": {"win": 1, "lost": 0}, "_Ice Shard_XAttack": {"win": 1, "lost": 1}}}, "AramisCe": {"win": 1, "lost": 0, "battle_sets": {"_Ice Shard_XSpeed": {"win": 1, "lost": 0}}}, "IsWillTV\u30c4": {"win": 1, "lost": 1, "battle_sets": {"_Ice Shard_XSpeed": {"win": 1, "lost": 1}}}, "STMN\u30fbKira": {"win": 2, "lost": 1, "battle_sets": {"_Ice Shard_EjectButton": {"win": 2, "lost": 1}}}, "Tybseol": {"win": 29, "lost": 10, "battle_sets": {"_Ice Shard_EjectButton": {"win": 29, "lost": 10}}}, "99\u30e0\u4efb\u4e49\u4f1f": {"win": 17, "lost": 13, "battle_sets": {"_Ice Shard_XSpeed": {"win": 16, "lost": 13}, "Icy Wind__XSpeed": {"win": 1, "lost": 0}}}, "Aurimakii": {"win": 1, "lost": 2, "battle_sets": {"Icy Wind_Ice Shard_XSpeed": {"win": 0, "lost": 1}, "__XSpeed": {"win": 0, "lost": 1}, "_Ice Shard_XSpeed": {"win": 1, "lost": 0}}}, "CeS\u68a6KiD": {"win": 1, "lost": 0, "battle_sets": {"_Ice Shard_Purify": {"win": 1, "lost": 0}}}, "STMN\u30fbFroy": {"win": 7, "lost": 6, "battle_sets": {"_Ice Shard_XSpeed": {"win": 7, "lost": 6}}}, "MugiwarcTTV": {"win": 1, "lost": 0, "battle_sets": {"_Ice Shard_XSpeed": {"win": 1, "lost": 0}}}, "DanielMil": {"win": 1, "lost": 0, "battle_sets": {"_Ice Shard_XSpeed": {"win": 1, "lost": 0}}}, "\u3042_\u3052": {"win": 2, "lost": 1, "battle_sets": {"_Ice Shard_EjectButton": {"win": 2, "lost": 1}}}, "BB\u30fbSkyfire": {"win": 1, "lost": 0, "battle_sets": {"_Ice Shard_EjectButton": {"win": 1, "lost": 0}}}, "OMO\u30e1Nafylno": {"win": 0, "lost": 2, "battle_sets": {"Icy Wind_Ice Shard_XSpeed": {"win": 0, "lost": 1}, "_Ice Shard_XSpeed": {"win": 0, "lost": 1}}}, "S\u012bmp": {"win": 0, "lost": 1, "battle_sets": {"_Ice Shard_XSpeed": {"win": 0, "lost": 1}}}, "Espoir\u0421\u0432\u0451\u0442": {"win": 0, "lost": 1, "battle_sets": {"_Ice Shard_XAttack": {"win": 0, "lost": 1}}}, "Evilgenius2": {"win": 0, "lost": 1, "battle_sets": {"_Ice Shard_XSpeed": {"win": 0, "lost": 1}}}, "ADESu23\u30fbTTV": {"win": 3, "lost": 0, "battle_sets": {"_Ice Shard_XSpeed": {"win": 2, "lost": 0}, "Icy Wind__XSpeed": {"win": 1, "lost": 0}}}, "Cr\u00f3ng": {"win": 7, "lost": 4, "battle_sets": {"_Ice Shard_XSpeed": {"win": 7, "lost": 4}}}, "\u663c\u5bdd\u3072\u307f": {"win": 17, "lost": 2, "battle_sets": {"_Ice Shard_EjectButton": {"win": 17, "lost": 2}}}, "ryanxoxo": {"win": 11, "lost": 9, "battle_sets": {"_Ice Shard_XSpeed": {"win": 3, "lost": 5}, "_Ice Shard_EjectButton": {"win": 8, "lost": 4}}}, "\u6953\u5c02\u304b\u3073\u304d\u3089": {"win": 2, "lost": 0, "battle_sets": {"_Ice Shard_XAttack": {"win": 2, "lost": 0}}}}, "battle_sets": {"_Ice Shard_EjectButton": {"win": 67, "lost": 25}, "_Ice Shard_XSpeed": {"win": 97, "lost": 51}, "__XSpeed": {"win": 2, "lost": 3}, "_Ice Shard_Purify": {"win": 2, "lost": 0}, "_Ice Shard_XAttack": {"win": 3, "lost": 2}, "Icy Wind__XSpeed": {"win": 2, "lost": 0}, "Icy Wind_Ice Shard_XSpeed": {"win": 0, "lost": 2}}}, "Venusaur": {"win": 12, "lost": 7, "players": {"Xante": {"win": 1, "lost": 1, "battle_sets": {"Giga Drain_Petal Dance_Purify": {"win": 1, "lost": 1}}}, "RJG\u30fbRuvis": {"win": 1, "lost": 1, "battle_sets": {"Giga Drain_Petal Dance_Purify": {"win": 1, "lost": 1}}}, "AFR\u30fbMiva": {"win": 2, "lost": 1, "battle_sets": {"Giga Drain_Petal Dance_Purify": {"win": 2, "lost": 1}}}, "AramisCe": {"win": 0, "lost": 1, "battle_sets": {"Giga Drain_Petal Dance_XSpeed": {"win": 0, "lost": 1}}}, "Espoir\u0421\u0432\u0451\u0442": {"win": 0, "lost": 1, "battle_sets": {"Sludge Bomb_Solar Beam_EjectButton": {"win": 0, "lost": 1}}}, "Trafyyy": {"win": 1, "lost": 0, "battle_sets": {"Sludge Bomb_Solar Beam_EjectButton": {"win": 1, "lost": 0}}}, "S4L-": {"win": 1, "lost": 0, "battle_sets": {"Giga Drain_Petal Dance_Purify": {"win": 1, "lost": 0}}}, "T2_Mame": {"win": 1, "lost": 1, "battle_sets": {"Giga Drain_Petal Dance_Purify": {"win": 1, "lost": 1}}}, "\u5b9f\u306f\u30d4\u30af\u30bd\u30eb": {"win": 1, "lost": 0, "battle_sets": {"Giga Drain_Petal Dance_Purify": {"win": 1, "lost": 0}}}, "ttv_mMALIKx": {"win": 2, "lost": 0, "battle_sets": {"Giga Drain_Petal Dance_Purify": {"win": 2, "lost": 0}}}, "Pikachichu": {"win": 1, "lost": 0, "battle_sets": {"Giga Drain_Petal Dance_Purify": {"win": 1, "lost": 0}}}, "Jaypa\u30c4": {"win": 1, "lost": 1, "battle_sets": {"Giga Drain_Petal Dance_Purify": {"win": 1, "lost": 1}}}}, "battle_sets": {"Giga Drain_Petal Dance_Purify": {"win": 11, "lost": 5}, "Giga Drain_Petal Dance_XSpeed": {"win": 0, "lost": 1}, "Sludge Bomb_Solar Beam_EjectButton": {"win": 1, "lost": 1}}}, "Alolan Ninetales": {"win": 2, "lost": 2, "players": {"Xante": {"win": 1, "lost": 0, "battle_sets": {"Dazzling Gleam_Aurora Veil_XAttack": {"win": 1, "lost": 0}}}, "CeS\u68a6Inf\u00ed": {"win": 0, "lost": 1, "battle_sets": {"Dazzling Gleam_Aurora Veil_EjectButton": {"win": 0, "lost": 1}}}, "OMO\u30e1Nafylno": {"win": 0, "lost": 1, "battle_sets": {"Dazzling Gleam_Aurora Veil_EjectButton": {"win": 0, "lost": 1}}}, "\u5b9f\u306f\u30d4\u30af\u30bd\u30eb": {"win": 1, "lost": 0, "battle_sets": {"Dazzling Gleam_Aurora Veil_EjectButton": {"win": 1, "lost": 0}}}}, "battle_sets": {"Dazzling Gleam_Aurora Veil_XAttack": {"win": 1, "lost": 0}, "Dazzling Gleam_Aurora Veil_EjectButton": {"win": 1, "lost": 2}}}, "Tsareena": {"win": 164, "lost": 41, "players": {"Xante": {"win": 4, "lost": 0, "battle_sets": {"Stomp_Trop Kick_XSpeed": {"win": 2, "lost": 0}, "Stomp_Grassy Glide_XSpeed": {"win": 2, "lost": 0}}}, "iamJPN": {"win": 15, "lost": 0, "battle_sets": {"Stomp_Trop Kick_XAttack": {"win": 15, "lost": 0}}}, "Metallic\u30c4": {"win": 6, "lost": 1, "battle_sets": {"Stomp_Grassy Glide_Purify": {"win": 6, "lost": 1}}}, "\u9811\u5f35\u308d\u3046ww": {"win": 5, "lost": 2, "battle_sets": {"Stomp_Trop Kick_XSpeed": {"win": 5, "lost": 2}}}, "nayeon": {"win": 22, "lost": 5, "battle_sets": {"Stomp_Trop Kick_Purify": {"win": 22, "lost": 5}}}, "AMaddog": {"win": 1, "lost": 0, "battle_sets": {"Stomp_Trop Kick_XAttack": {"win": 1, "lost": 0}}}, "5i\u30fbInferno": {"win": 1, "lost": 0, "battle_sets": {"Stomp_Grassy Glide_Purify": {"win": 1, "lost": 0}}}, "Kenoken": {"win": 11, "lost": 1, "battle_sets": {"Stomp_Grassy Glide_XSpeed": {"win": 11, "lost": 1}}}, "AkumaCx": {"win": 1, "lost": 0, "battle_sets": {"Stomp_Grassy Glide_XSpeed": {"win": 1, "lost": 0}}}, "dordori": {"win": 2, "lost": 0, "battle_sets": {"Stomp_Trop Kick_XAttack": {"win": 2, "lost": 0}}}, "AramisCe": {"win": 6, "lost": 1, "battle_sets": {"Stomp_Grassy Glide_XSpeed": {"win": 4, "lost": 1}, "Triple Axel_Grassy Glide_XSpeed": {"win": 2, "lost": 0}}}, "TE\u30fbFreaK": {"win": 1, "lost": 0, "battle_sets": {"Stomp_Grassy Glide_XSpeed": {"win": 1, "lost": 0}}}, "\ub108\ub3c4\ub0b4\uaebc": {"win": 6, "lost": 1, "battle_sets": {"Stomp_Trop Kick_XAttack": {"win": 6, "lost": 1}}}, "STMN\u30fbTexas": {"win": 16, "lost": 3, "battle_sets": {"Stomp_Trop Kick_Potion": {"win": 16, "lost": 3}}}, "99\u30e0\u4efb\u4e49\u4f1f": {"win": 3, "lost": 1, "battle_sets": {"Stomp_Trop Kick_Purify": {"win": 3, "lost": 1}}}, "DanielMil": {"win": 2, "lost": 0, "battle_sets": {"Stomp_Grassy Glide_XSpeed": {"win": 2, "lost": 0}}}, "BB\u30fbSkyfire": {"win": 1, "lost": 0, "battle_sets": {"Stomp_Grassy Glide_XSpeed": {"win": 1, "lost": 0}}}, "OMO\u30e1Nafylno": {"win": 1, "lost": 0, "battle_sets": {"Stomp_Grassy Glide_XAttack": {"win": 1, "lost": 0}}}, "S\u012bmp": {"win": 1, "lost": 0, "battle_sets": {"Stomp_Grassy Glide_XSpeed": {"win": 1, "lost": 0}}}, "Toloman": {"win": 1, "lost": 1, "battle_sets": {"Stomp_Grassy Glide_Purify": {"win": 1, "lost": 1}}}, "Espoir\u0421\u0432\u0451\u0442": {"win": 0, "lost": 1, "battle_sets": {"Stomp_Grassy Glide_XAttack": {"win": 0, "lost": 1}}}, "Trafyyy": {"win": 1, "lost": 0, "battle_sets": {"Stomp_Trop Kick_Purify": {"win": 1, "lost": 0}}}, "EMPxSorA\u53f3": {"win": 1, "lost": 0, "battle_sets": {"Stomp_Trop Kick_EjectButton": {"win": 1, "lost": 0}}}, "\u30fbJohn\u30fb": {"win": 3, "lost": 0, "battle_sets": {"Stomp_Grassy Glide_Purify": {"win": 3, "lost": 0}}}, "T2_Mame": {"win": 3, "lost": 1, "battle_sets": {"Stomp_Trop Kick_Purify": {"win": 3, "lost": 1}}}, "\u5b9f\u306f\u30d4\u30af\u30bd\u30eb": {"win": 0, "lost": 2, "battle_sets": {"Stomp_Trop Kick_XAttack": {"win": 0, "lost": 2}}}, "\u79cb\u6d25\u831c": {"win": 8, "lost": 1, "battle_sets": {"Stomp_Trop Kick_XAttack": {"win": 8, "lost": 1}}}, "\u3042\u305a\u3079\u308b\u3068": {"win": 8, "lost": 3, "battle_sets": {"Stomp_Trop Kick_XAttack": {"win": 8, "lost": 3}}}, "Cr\u00f3ng": {"win": 4, "lost": 5, "battle_sets": {"Stomp_Trop Kick_XSpeed": {"win": 4, "lost": 5}}}, "RENAMED": {"win": 6, "lost": 2, "battle_sets": {"Stomp_Trop Kick_XSpeed": {"win": 6, "lost": 2}}}, "jatinjwin": {"win": 17, "lost": 8, "battle_sets": {"Stomp_Trop Kick_XAttack": {"win": 2, "lost": 1}, "Stomp_Trop Kick_EjectButton": {"win": 1, "lost": 0}, "Stomp_Trop Kick_XSpeed": {"win": 13, "lost": 7}, "Stomp_Trop Kick_Purify": {"win": 1, "lost": 0}}}, "Overseert": {"win": 1, "lost": 1, "battle_sets": {"Stomp_Grassy Glide_XSpeed": {"win": 1, "lost": 1}}}, "\u62b1\u3048\u843d\u3061\u8b66\u5bdf": {"win": 1, "lost": 1, "battle_sets": {"Stomp_Trop Kick_XAttack": {"win": 1, "lost": 1}}}, "\u6953\u5c02\u304b\u3073\u304d\u3089": {"win": 5, "lost": 0, "battle_sets": {"Stomp_Trop Kick_Purify": {"win": 5, "lost": 0}}}}, "battle_sets": {"Stomp_Trop Kick_XSpeed": {"win": 30, "lost": 16}, "Stomp_Grassy Glide_XSpeed": {"win": 24, "lost": 3}, "Stomp_Trop Kick_XAttack": {"win": 43, "lost": 9}, "Stomp_Grassy Glide_Purify": {"win": 11, "lost": 2}, "Stomp_Trop Kick_Purify": {"win": 35, "lost": 7}, "Triple Axel_Grassy Glide_XSpeed": {"win": 2, "lost": 0}, "Stomp_Trop Kick_Potion": {"win": 16, "lost": 3}, "Stomp_Grassy Glide_XAttack": {"win": 1, "lost": 1}, "Stomp_Trop Kick_EjectButton": {"win": 2, "lost": 0}}}, "Blissey": {"win": 140, "lost": 48, "players": {"PotatoUwU": {"win": 6, "lost": 4, "battle_sets": {"Egg Bomb_Soft-Boiled_XSpeed": {"win": 6, "lost": 4}}}, "XIS\u30fbMazo": {"win": 2, "lost": 0, "battle_sets": {"Egg Bomb_Soft-Boiled_XSpeed": {"win": 2, "lost": 0}}}, "RJG\u30fbRuvis": {"win": 0, "lost": 1, "battle_sets": {"Egg Bomb_Soft-Boiled_XSpeed": {"win": 0, "lost": 1}}}, "Wablet?": {"win": 0, "lost": 1, "battle_sets": {"Egg Bomb_Soft-Boiled_XSpeed": {"win": 0, "lost": 1}}}, "Wulf?": {"win": 7, "lost": 0, "battle_sets": {"Egg Bomb_Soft-Boiled_XSpeed": {"win": 5, "lost": 0}, "Egg Bomb_Safeguard_XSpeed": {"win": 2, "lost": 0}}}, "Metallic\u30c4": {"win": 1, "lost": 0, "battle_sets": {"Egg Bomb_Safeguard_XSpeed": {"win": 1, "lost": 0}}}, "AFR\u30fbMiva": {"win": 2, "lost": 0, "battle_sets": {"Helping Hand_Safeguard_XSpeed": {"win": 1, "lost": 0}, "Egg Bomb_Safeguard_XSpeed": {"win": 1, "lost": 0}}}, "ttvGhatlue": {"win": 1, "lost": 0, "battle_sets": {"Egg Bomb_Soft-Boiled_XSpeed": {"win": 1, "lost": 0}}}, "nayeon": {"win": 2, "lost": 0, "battle_sets": {"Egg Bomb_Soft-Boiled_XSpeed": {"win": 2, "lost": 0}}}, "\ud37c\ubc0d": {"win": 25, "lost": 5, "battle_sets": {"Helping Hand_Safeguard_XSpeed": {"win": 25, "lost": 5}}}, "OMO\u30e1Phoenix": {"win": 2, "lost": 2, "battle_sets": {"Egg Bomb_Soft-Boiled_XSpeed": {"win": 2, "lost": 2}}}, "5i\u30fbInferno": {"win": 3, "lost": 0, "battle_sets": {"Egg Bomb_Soft-Boiled_XSpeed": {"win": 3, "lost": 0}}}, "BTW_Deku,": {"win": 19, "lost": 8, "battle_sets": {"Egg Bomb_Soft-Boiled_Potion": {"win": 19, "lost": 8}}}, "KyluK?": {"win": 4, "lost": 1, "battle_sets": {"Egg Bomb_Safeguard_XSpeed": {"win": 1, "lost": 0}, "Egg Bomb_Soft-Boiled_XSpeed": {"win": 3, "lost": 0}, "Egg Bomb_Soft-Boiled_Tail": {"win": 0, "lost": 1}}}, "AkumaCx": {"win": 15, "lost": 7, "battle_sets": {"Egg Bomb_Soft-Boiled_XSpeed": {"win": 15, "lost": 7}}}, "Ghost?\u3164": {"win": 6, "lost": 0, "battle_sets": {"Egg Bomb_Soft-Boiled_XSpeed": {"win": 6, "lost": 0}}}, "TE\u30fb999": {"win": 12, "lost": 5, "battle_sets": {"Egg Bomb_Safeguard_XSpeed": {"win": 8, "lost": 3}, "Egg Bomb_Soft-Boiled_XSpeed": {"win": 3, "lost": 1}, "Helping Hand_Safeguard_XSpeed": {"win": 1, "lost": 1}}}, "STMN\u30fbKira": {"win": 1, "lost": 0, "battle_sets": {"Helping Hand_Safeguard_XSpeed": {"win": 1, "lost": 0}}}, "BB\u30fbSkyfire": {"win": 2, "lost": 2, "battle_sets": {"Egg Bomb_Soft-Boiled_XSpeed": {"win": 2, "lost": 2}}}, "S\u012bmp": {"win": 1, "lost": 2, "battle_sets": {"Egg Bomb_Soft-Boiled_XSpeed": {"win": 1, "lost": 2}}}, "Trafyyy": {"win": 1, "lost": 0, "battle_sets": {"Egg Bomb_Soft-Boiled_XSpeed": {"win": 1, "lost": 0}}}, "GyZ": {"win": 0, "lost": 1, "battle_sets": {"Egg Bomb_Soft-Boiled_XSpeed": {"win": 0, "lost": 1}}}, "\u5b9f\u306f\u30d4\u30af\u30bd\u30eb": {"win": 3, "lost": 1, "battle_sets": {"Helping Hand_Safeguard_EjectButton": {"win": 1, "lost": 0}, "Egg Bomb_Soft-Boiled_EjectButton": {"win": 2, "lost": 1}}}, "\ud6c8\ud3ec\ub3c4": {"win": 7, "lost": 1, "battle_sets": {"Egg Bomb_Safeguard_XSpeed": {"win": 6, "lost": 1}, "Helping Hand_Safeguard_XSpeed": {"win": 1, "lost": 0}}}, "Cr\u00f3ng": {"win": 1, "lost": 1, "battle_sets": {"Helping Hand_Safeguard_XSpeed": {"win": 1, "lost": 1}}}, "j\u0139": {"win": 13, "lost": 5, "battle_sets": {"Egg Bomb_Soft-Boiled_XSpeed": {"win": 13, "lost": 5}}}, "Overseert": {"win": 4, "lost": 1, "battle_sets": {"Egg Bomb_Soft-Boiled_XSpeed": {"win": 2, "lost": 0}, "Egg Bomb_Safeguard_XSpeed": {"win": 1, "lost": 1}, "Helping Hand_Safeguard_XSpeed": {"win": 1, "lost": 0}}}}, "battle_sets": {"Egg Bomb_Soft-Boiled_XSpeed": {"win": 67, "lost": 26}, "Egg Bomb_Safeguard_XSpeed": {"win": 20, "lost": 5}, "Helping Hand_Safeguard_XSpeed": {"win": 31, "lost": 7}, "Egg Bomb_Soft-Boiled_Potion": {"win": 19, "lost": 8}, "Egg Bomb_Soft-Boiled_Tail": {"win": 0, "lost": 1}, "Helping Hand_Safeguard_EjectButton": {"win": 1, "lost": 0}, "Egg Bomb_Soft-Boiled_EjectButton": {"win": 2, "lost": 1}}}, "Hoopa": {"win": 113, "lost": 27, "players": {"PotatoUwU": {"win": 3, "lost": 0, "battle_sets": {"Hyperspace Fury_Psybeam_XSpeed": {"win": 2, "lost": 0}, "Phantom Force_Hyperspace Hole_XSpeed": {"win": 1, "lost": 0}}}, "RJG\u30fbRuvis": {"win": 5, "lost": 2, "battle_sets": {"Phantom Force_Hyperspace Hole_XSpeed": {"win": 2, "lost": 2}, "Hyperspace Fury_Psybeam_XSpeed": {"win": 2, "lost": 0}, "Shadow Ball_Hyperspace Hole_XSpeed": {"win": 1, "lost": 0}}}, "AFR\u30fbMiva": {"win": 1, "lost": 0, "battle_sets": {"Phantom Force_Hyperspace Hole_XSpeed": {"win": 1, "lost": 0}}}, "Ghost?\u3164": {"win": 24, "lost": 8, "battle_sets": {"Phantom Force_Hyperspace Hole_XSpeed": {"win": 21, "lost": 8}, "Hyperspace Fury_Psybeam_XSpeed": {"win": 3, "lost": 0}}}, "iamJAP": {"win": 15, "lost": 0, "battle_sets": {"Phantom Force_Hyperspace Hole_EjectButton": {"win": 10, "lost": 0}, "Hyperspace Fury_Psybeam_EjectButton": {"win": 5, "lost": 0}}}, "BB\u30fbOsIrIs": {"win": 25, "lost": 9, "battle_sets": {"Shadow Ball_Hyperspace Hole_XSpeed": {"win": 21, "lost": 8}, "Hyperspace Fury_Psybeam_XSpeed": {"win": 4, "lost": 1}}}, "Toloman": {"win": 14, "lost": 2, "battle_sets": {"Phantom Force_Hyperspace Hole_EjectButton": {"win": 10, "lost": 1}, "Hyperspace Fury_Psybeam_EjectButton": {"win": 4, "lost": 1}}}, "Trafyyy": {"win": 1, "lost": 0, "battle_sets": {"Hyperspace Fury_Psybeam_XAttack": {"win": 1, "lost": 0}}}, "GyZ": {"win": 6, "lost": 2, "battle_sets": {"Phantom Force_Hyperspace Hole_XSpeed": {"win": 6, "lost": 2}}}, "TILTED\u00d7Y\u00fbta": {"win": 2, "lost": 0, "battle_sets": {"Hyperspace Fury_Psybeam_XSpeed": {"win": 1, "lost": 0}, "Shadow Ball_Hyperspace Hole_XSpeed": {"win": 1, "lost": 0}}}, "\uc774\ud14c": {"win": 7, "lost": 1, "battle_sets": {"Shadow Ball_Hyperspace Hole_XSpeed": {"win": 3, "lost": 1}, "Hyperspace Fury_Psybeam_XSpeed": {"win": 2, "lost": 0}, "Phantom Force_Hyperspace Hole_XSpeed": {"win": 2, "lost": 0}}}, "\u5b9f\u306f\u30d4\u30af\u30bd\u30eb": {"win": 0, "lost": 1, "battle_sets": {"Phantom Force_Hyperspace Hole_EjectButton": {"win": 0, "lost": 1}}}, "ADESu23\u30fbTTV": {"win": 1, "lost": 0, "battle_sets": {"Phantom Force_Hyperspace Hole_XSpeed": {"win": 1, "lost": 0}}}, "Cr\u00f3ng": {"win": 3, "lost": 0, "battle_sets": {"Shadow Ball_Hyperspace Hole_XAttack": {"win": 1, "lost": 0}, "Shadow Ball_Hyperspace Hole_EjectButton": {"win": 2, "lost": 0}}}, "j\u0139": {"win": 5, "lost": 0, "battle_sets": {"Phantom Force_Hyperspace Hole_EjectButton": {"win": 4, "lost": 0}, "Hyperspace Fury_Psybeam_EjectButton": {"win": 1, "lost": 0}}}, "jatinjwin": {"win": 1, "lost": 2, "battle_sets": {"Phantom Force_Hyperspace Hole_Potion": {"win": 1, "lost": 2}}}}, "battle_sets": {"Hyperspace Fury_Psybeam_XSpeed": {"win": 14, "lost": 1}, "Phantom Force_Hyperspace Hole_XSpeed": {"win": 34, "lost": 12}, "Shadow Ball_Hyperspace Hole_XSpeed": {"win": 26, "lost": 9}, "Phantom Force_Hyperspace Hole_EjectButton": {"win": 24, "lost": 2}, "Hyperspace Fury_Psybeam_EjectButton": {"win": 10, "lost": 1}, "Hyperspace Fury_Psybeam_XAttack": {"win": 1, "lost": 0}, "Shadow Ball_Hyperspace Hole_XAttack": {"win": 1, "lost": 0}, "Shadow Ball_Hyperspace Hole_EjectButton": {"win": 2, "lost": 0}, "Phantom Force_Hyperspace Hole_Potion": {"win": 1, "lost": 2}}}, "Garchomp": {"win": 50, "lost": 24, "players": {"PotatoUwU": {"win": 6, "lost": 1, "battle_sets": {"Dragon Rush_Dragon Claw_EjectButton": {"win": 6, "lost": 1}}}, "ttvGhatlue": {"win": 0, "lost": 1, "battle_sets": {"Dragon Rush_Dragon Claw_EjectButton": {"win": 0, "lost": 1}}}, "STMN\u30fbTexas": {"win": 1, "lost": 0, "battle_sets": {"Dragon Rush_Dragon Claw_EjectButton": {"win": 1, "lost": 0}}}, "TtvPikaGod22": {"win": 24, "lost": 8, "battle_sets": {"Dragon Rush_Dragon Claw_EjectButton": {"win": 24, "lost": 7}, "Dig_Dragon Claw_EjectButton": {"win": 0, "lost": 1}}}, "ttvNintendil": {"win": 17, "lost": 12, "battle_sets": {"Dragon Rush_Dragon Claw_EjectButton": {"win": 17, "lost": 12}}}, "RENAMED": {"win": 2, "lost": 2, "battle_sets": {"Dragon Rush_Dragon Claw_EjectButton": {"win": 2, "lost": 2}}}}, "battle_sets": {"Dragon Rush_Dragon Claw_EjectButton": {"win": 50, "lost": 23}, "Dig_Dragon Claw_EjectButton": {"win": 0, "lost": 1}}}, "Wigglytuff": {"win": 18, "lost": 2, "players": {"PotatoUwU": {"win": 0, "lost": 1, "battle_sets": {"Dazzling Gleam_Sing_XSpeed": {"win": 0, "lost": 1}}}, "TE\u30fb999": {"win": 1, "lost": 0, "battle_sets": {"Dazzling Gleam_Sing_XSpeed": {"win": 1, "lost": 0}}}, "TE\u30fbFreaK": {"win": 1, "lost": 0, "battle_sets": {"Dazzling Gleam_Sing_XSpeed": {"win": 1, "lost": 0}}}, "Parasite": {"win": 10, "lost": 0, "battle_sets": {"Dazzling Gleam_Rollout_EjectButton": {"win": 10, "lost": 0}}}, "EMPxSorA\u53f3": {"win": 5, "lost": 1, "battle_sets": {"Double Slap_Sing_EjectButton": {"win": 1, "lost": 0}, "Dazzling Gleam_Sing_EjectButton": {"win": 4, "lost": 1}}}, "\u6953\u5c02\u304b\u3073\u304d\u3089": {"win": 1, "lost": 0, "battle_sets": {"Dazzling Gleam_Sing_XSpeed": {"win": 1, "lost": 0}}}}, "battle_sets": {"Dazzling Gleam_Sing_XSpeed": {"win": 3, "lost": 1}, "Dazzling Gleam_Rollout_EjectButton": {"win": 10, "lost": 0}, "Double Slap_Sing_EjectButton": {"win": 1, "lost": 0}, "Dazzling Gleam_Sing_EjectButton": {"win": 4, "lost": 1}}}, "Cramorant": {"win": 90, "lost": 29, "players": {"XIS\u30fbMazo": {"win": 23, "lost": 2, "battle_sets": {"Dive_Air Slash_EjectButton": {"win": 22, "lost": 2}, "Surf_Hurricane_EjectButton": {"win": 1, "lost": 0}}}, "Wulf?": {"win": 1, "lost": 0, "battle_sets": {"Dive_Air Slash_EjectButton": {"win": 1, "lost": 0}}}, "Suix\u3164": {"win": 15, "lost": 0, "battle_sets": {"Dive_Air Slash_EjectButton": {"win": 15, "lost": 0}}}, "Metallic\u30c4": {"win": 1, "lost": 0, "battle_sets": {"Surf_Hurricane_EjectButton": {"win": 1, "lost": 0}}}, "AFR\u30fbMiva": {"win": 0, "lost": 1, "battle_sets": {"Dive_Air Slash_EjectButton": {"win": 0, "lost": 1}}}, "ttvGhatlue": {"win": 1, "lost": 0, "battle_sets": {"Dive_Air Slash_EjectButton": {"win": 1, "lost": 0}}}, "OMO\u30e1Phoenix": {"win": 1, "lost": 1, "battle_sets": {"Surf_Hurricane_EjectButton": {"win": 1, "lost": 1}}}, "MW\u30fbAngel\u30b7": {"win": 3, "lost": 3, "battle_sets": {"Dive_Air Slash_EjectButton": {"win": 2, "lost": 3}, "Surf_Air Slash_EjectButton": {"win": 1, "lost": 0}}}, "KyluK?": {"win": 0, "lost": 2, "battle_sets": {"Dive_Air Slash_EjectButton": {"win": 0, "lost": 2}}}, "STMN\u30fbKira": {"win": 5, "lost": 0, "battle_sets": {"Dive_Air Slash_EjectButton": {"win": 5, "lost": 0}}}, "ttvSixsies": {"win": 1, "lost": 1, "battle_sets": {"Dive_Air Slash_EjectButton": {"win": 1, "lost": 1}}}, "STMN\u30fbFroy": {"win": 0, "lost": 1, "battle_sets": {"Dive_Air Slash_Potion": {"win": 0, "lost": 1}}}, "MugiwarcTTV": {"win": 0, "lost": 1, "battle_sets": {"Dive_Air Slash_Potion": {"win": 0, "lost": 1}}}, "\u3042_\u3052": {"win": 3, "lost": 0, "battle_sets": {"Surf_Air Slash_EjectButton": {"win": 3, "lost": 0}}}, "OMO\u30e1Nafylno": {"win": 6, "lost": 1, "battle_sets": {"Dive_Air Slash_EjectButton": {"win": 6, "lost": 1}}}, "S\u012bmp": {"win": 2, "lost": 1, "battle_sets": {"Dive_Air Slash_EjectButton": {"win": 2, "lost": 1}}}, "TILTED\u00d7Y\u00fbta": {"win": 1, "lost": 0, "battle_sets": {"Dive_Air Slash_EjectButton": {"win": 1, "lost": 0}}}, "\u30fbJohn\u30fb": {"win": 3, "lost": 2, "battle_sets": {"Dive_Air Slash_EjectButton": {"win": 2, "lost": 2}, "Surf_Hurricane_EjectButton": {"win": 1, "lost": 0}}}, "ADESu23\u30fbTTV": {"win": 1, "lost": 1, "battle_sets": {"Dive_Air Slash_Purify": {"win": 1, "lost": 1}}}, "Jaypa\u30c4": {"win": 5, "lost": 2, "battle_sets": {"Dive_Air Slash_EjectButton": {"win": 5, "lost": 2}}}, "Overseert": {"win": 4, "lost": 2, "battle_sets": {"Dive_Air Slash_EjectButton": {"win": 4, "lost": 2}}}, "\u6953\u5c02\u304b\u3073\u304d\u3089": {"win": 3, "lost": 1, "battle_sets": {"Dive_Air Slash_EjectButton": {"win": 3, "lost": 1}}}, "SirWaddleChu": {"win": 11, "lost": 7, "battle_sets": {"Dive_Air Slash_EjectButton": {"win": 11, "lost": 7}}}}, "battle_sets": {"Dive_Air Slash_EjectButton": {"win": 81, "lost": 25}, "Surf_Hurricane_EjectButton": {"win": 4, "lost": 1}, "Surf_Air Slash_EjectButton": {"win": 4, "lost": 0}, "Dive_Air Slash_Potion": {"win": 0, "lost": 2}, "Dive_Air Slash_Purify": {"win": 1, "lost": 1}}}, "Decidueye": {"win": 24, "lost": 9, "players": {"XIS\u30fbMazo": {"win": 0, "lost": 1, "battle_sets": {"Spirit Shackle_Leaf Storm_EjectButton": {"win": 0, "lost": 1}}}, "RJG\u30fbRuvis": {"win": 1, "lost": 0, "battle_sets": {"Spirit Shackle_Shadow Sneak_XSpeed": {"win": 1, "lost": 0}}}, "Metallic\u30c4": {"win": 1, "lost": 0, "battle_sets": {"Spirit Shackle_Shadow Sneak_XSpeed": {"win": 1, "lost": 0}}}, "OMO\u30e1Phoenix": {"win": 2, "lost": 1, "battle_sets": {"Spirit Shackle_Shadow Sneak_XSpeed": {"win": 2, "lost": 1}}}, "5i\u30fbKeep": {"win": 1, "lost": 1, "battle_sets": {"Razor Leaf_Shadow Sneak_EjectButton": {"win": 1, "lost": 1}}}, "Trafyyy": {"win": 1, "lost": 0, "battle_sets": {"Razor Leaf_Shadow Sneak_XSpeed": {"win": 1, "lost": 0}}}, "MUn": {"win": 18, "lost": 5, "battle_sets": {"Spirit Shackle_Shadow Sneak_EjectButton": {"win": 17, "lost": 4}, "Razor Leaf_Shadow Sneak_EjectButton": {"win": 1, "lost": 1}}}, "ADESu23\u30fbTTV": {"win": 0, "lost": 1, "battle_sets": {"Spirit Shackle_Shadow Sneak_XSpeed": {"win": 0, "lost": 1}}}}, "battle_sets": {"Spirit Shackle_Leaf Storm_EjectButton": {"win": 0, "lost": 1}, "Spirit Shackle_Shadow Sneak_XSpeed": {"win": 4, "lost": 2}, "Razor Leaf_Shadow Sneak_EjectButton": {"win": 2, "lost": 2}, "Razor Leaf_Shadow Sneak_XSpeed": {"win": 1, "lost": 0}, "Spirit Shackle_Shadow Sneak_EjectButton": {"win": 17, "lost": 4}}}, "Dragonite": {"win": 155, "lost": 35, "players": {"ShreyNHK": {"win": 3, "lost": 1, "battle_sets": {"Dragon Dance_Hyper Beam_Purify": {"win": 3, "lost": 1}}}, "RJG\u30fbRuvis": {"win": 0, "lost": 1, "battle_sets": {"Dragon Dance_Hyper Beam_Purify": {"win": 0, "lost": 1}}}, "\u82a5\u5ddd\u3042\u304d": {"win": 15, "lost": 0, "battle_sets": {"Dragon Dance_Hyper Beam_EjectButton": {"win": 15, "lost": 0}}}, "Metallic\u30c4": {"win": 1, "lost": 0, "battle_sets": {"Dragon Dance_Hyper Beam_Purify": {"win": 1, "lost": 0}}}, "\u9811\u5f35\u308d\u3046ww": {"win": 18, "lost": 3, "battle_sets": {"Dragon Dance_Hyper Beam_EjectButton": {"win": 18, "lost": 3}}}, "R0juu": {"win": 9, "lost": 3, "battle_sets": {"Dragon Dance_Hyper Beam_XAttack": {"win": 9, "lost": 3}}}, "ttvGhatlue": {"win": 1, "lost": 0, "battle_sets": {"Dragon Dance_Hyper Beam_XAttack": {"win": 1, "lost": 0}}}, "ENT\u30fbScepTer": {"win": 1, "lost": 0, "battle_sets": {"Dragon Dance_Hyper Beam_Purify": {"win": 1, "lost": 0}}}, "caligola999": {"win": 1, "lost": 0, "battle_sets": {"Dragon Dance_Hyper Beam_XAttack": {"win": 1, "lost": 0}}}, "AMaddog": {"win": 20, "lost": 5, "battle_sets": {"Dragon Dance_Hyper Beam_Purify": {"win": 20, "lost": 5}}}, "TE\u30fb999": {"win": 4, "lost": 2, "battle_sets": {"Dragon Dance_Hyper Beam_Purify": {"win": 4, "lost": 2}}}, "dordori": {"win": 2, "lost": 0, "battle_sets": {"Dragon Dance_Hyper Beam_EjectButton": {"win": 2, "lost": 0}}}, "\u7adc\u821e\u3071\u3089\u3066\u3083": {"win": 5, "lost": 3, "battle_sets": {"Dragon Dance_Hyper Beam_Ganrao": {"win": 3, "lost": 0}, "Dragon Dance_Hyper Beam_EjectButton": {"win": 2, "lost": 3}}}, "\u3042_\u3052": {"win": 1, "lost": 0, "battle_sets": {"Dragon Dance_Hyper Beam_EjectButton": {"win": 1, "lost": 0}}}, "Trafyyy": {"win": 6, "lost": 0, "battle_sets": {"Dragon Dance_Hyper Beam_Purify": {"win": 4, "lost": 0}, "Dragon Dance_Hyper Beam_Gear": {"win": 2, "lost": 0}}}, "TILTED\u00d7Y\u00fbta": {"win": 1, "lost": 0, "battle_sets": {"Dragon Dance_Hyper Beam_XAttack": {"win": 1, "lost": 0}}}, "S4L-": {"win": 8, "lost": 2, "battle_sets": {"Dragon Dance_Hyper Beam_EjectButton": {"win": 6, "lost": 2}, "Dragon Dance_Hyper Beam_Purify": {"win": 2, "lost": 0}}}, "\u96a0\u5c45\u3057\u307e\u3057\u305f": {"win": 16, "lost": 3, "battle_sets": {"Dragon Dance_Hyper Beam_EjectButton": {"win": 16, "lost": 3}}}, "Evilgenius2": {"win": 4, "lost": 2, "battle_sets": {"Dragon Dance_Hyper Beam_Purify": {"win": 4, "lost": 2}}}, "ADESu23\u30fbTTV": {"win": 2, "lost": 0, "battle_sets": {"Dragon Dance_Hyper Beam_XAttack": {"win": 2, "lost": 0}}}, "ttv_mMALIKx": {"win": 2, "lost": 0, "battle_sets": {"Dragon Dance_Hyper Beam_Purify": {"win": 2, "lost": 0}}}, "Jaypa\u30c4": {"win": 2, "lost": 2, "battle_sets": {"Dragon Dance_Hyper Beam_XAttack": {"win": 2, "lost": 2}}}, "Cr\u00f3ng": {"win": 7, "lost": 3, "battle_sets": {"Dragon Dance_Hyper Beam_Purify": {"win": 7, "lost": 3}}}, "RENAMED": {"win": 10, "lost": 3, "battle_sets": {"Dragon Dance_Hyper Beam_Purify": {"win": 10, "lost": 3}}}, "Overseert": {"win": 3, "lost": 2, "battle_sets": {"Dragon Dance_Hyper Beam_Purify": {"win": 2, "lost": 1}, "Dragon Dance_Hyper Beam_XAttack": {"win": 1, "lost": 1}}}, "\u62b1\u3048\u843d\u3061\u8b66\u5bdf": {"win": 13, "lost": 0, "battle_sets": {"Dragon Dance_Hyper Beam_XAttack": {"win": 13, "lost": 0}}}}, "battle_sets": {"Dragon Dance_Hyper Beam_Purify": {"win": 60, "lost": 18}, "Dragon Dance_Hyper Beam_EjectButton": {"win": 60, "lost": 11}, "Dragon Dance_Hyper Beam_XAttack": {"win": 30, "lost": 6}, "Dragon Dance_Hyper Beam_Ganrao": {"win": 3, "lost": 0}, "Dragon Dance_Hyper Beam_Gear": {"win": 2, "lost": 0}}}, "Pikachu": {"win": 18, "lost": 5, "players": {"ShreyNHK": {"win": 1, "lost": 0, "battle_sets": {"Thunder_Thunderbolt_XSpeed": {"win": 1, "lost": 0}}}, "RJG\u30fbRuvis": {"win": 1, "lost": 0, "battle_sets": {"Thunder_Volt Tackle_XSpeed": {"win": 1, "lost": 0}}}, "AFR\u30fbMiva": {"win": 1, "lost": 0, "battle_sets": {"Electro Ball_Volt Tackle_XSpeed": {"win": 1, "lost": 0}}}, "OMO\u30e1Phoenix": {"win": 1, "lost": 0, "battle_sets": {"Thunder_Thunderbolt_EjectButton": {"win": 1, "lost": 0}}}, "TE\u30fb999": {"win": 0, "lost": 1, "battle_sets": {"Thunder_Thunderbolt_EjectButton": {"win": 0, "lost": 1}}}, "CeS\u68a6Inf\u00ed": {"win": 1, "lost": 0, "battle_sets": {"Thunder_Thunderbolt_XSpeed": {"win": 1, "lost": 0}}}, "OMO\u30e1Nafylno": {"win": 9, "lost": 1, "battle_sets": {"Thunder_Thunderbolt_XSpeed": {"win": 9, "lost": 1}}}, "Trafyyy": {"win": 1, "lost": 1, "battle_sets": {"Electro Ball_Volt Tackle_EjectButton": {"win": 1, "lost": 1}}}, "\u30fbJohn\u30fb": {"win": 2, "lost": 0, "battle_sets": {"Electro Ball_Volt Tackle_EjectButton": {"win": 2, "lost": 0}}}, "ttvNintendil": {"win": 1, "lost": 1, "battle_sets": {"Thunder_Thunderbolt_EjectButton": {"win": 1, "lost": 0}, "Electro Ball_Volt Tackle_EjectButton": {"win": 0, "lost": 1}}}, "Jaypa\u30c4": {"win": 0, "lost": 1, "battle_sets": {"Electro Ball_Thunderbolt_EjectButton": {"win": 0, "lost": 1}}}}, "battle_sets": {"Thunder_Thunderbolt_XSpeed": {"win": 11, "lost": 1}, "Thunder_Volt Tackle_XSpeed": {"win": 1, "lost": 0}, "Electro Ball_Volt Tackle_XSpeed": {"win": 1, "lost": 0}, "Thunder_Thunderbolt_EjectButton": {"win": 2, "lost": 1}, "Electro Ball_Volt Tackle_EjectButton": {"win": 3, "lost": 2}, "Electro Ball_Thunderbolt_EjectButton": {"win": 0, "lost": 1}}}, "Gardevoir": {"win": 14, "lost": 3, "players": {"ShreyNHK": {"win": 1, "lost": 0, "battle_sets": {"Moonblast_Future Sight_XSpeed": {"win": 1, "lost": 0}}}, "blushUwU": {"win": 11, "lost": 3, "battle_sets": {"Moonblast_Future Sight_EjectButton": {"win": 11, "lost": 3}}}, "TILTED\u00d7Y\u00fbta": {"win": 1, "lost": 0, "battle_sets": {"Psychic_Future Sight_EjectButton": {"win": 1, "lost": 0}}}, "ryanxoxo": {"win": 1, "lost": 0, "battle_sets": {"Moonblast_Future Sight_EjectButton": {"win": 1, "lost": 0}}}}, "battle_sets": {"Moonblast_Future Sight_XSpeed": {"win": 1, "lost": 0}, "Moonblast_Future Sight_EjectButton": {"win": 12, "lost": 3}, "Psychic_Future Sight_EjectButton": {"win": 1, "lost": 0}}}, "Greninja": {"win": 87, "lost": 40, "players": {"ShreyNHK": {"win": 2, "lost": 0, "battle_sets": {"Surf_Smokescreen_XAttack": {"win": 2, "lost": 0}}}, "Metallic\u30c4": {"win": 2, "lost": 2, "battle_sets": {"Surf_Smokescreen_Purify": {"win": 2, "lost": 2}}}, "\u9811\u5f35\u308d\u3046ww": {"win": 2, "lost": 0, "battle_sets": {"Water Shuriken_Double Team_EjectButton": {"win": 1, "lost": 0}, "Surf_Smokescreen_EjectButton": {"win": 1, "lost": 0}}}, "ttvGhatlue": {"win": 1, "lost": 0, "battle_sets": {"Surf_Smokescreen_EjectButton": {"win": 1, "lost": 0}}}, "ENT\u30fbScepTer": {"win": 0, "lost": 1, "battle_sets": {"Surf_Smokescreen_XAttack": {"win": 0, "lost": 1}}}, "caligola999": {"win": 4, "lost": 0, "battle_sets": {"Surf_Smokescreen_EjectButton": {"win": 4, "lost": 0}}}, "\u7adc\u821e\u3071\u3089\u3066\u3083": {"win": 13, "lost": 8, "battle_sets": {"Surf_Smokescreen_XAttack": {"win": 13, "lost": 8}}}, "20FF": {"win": 1, "lost": 2, "battle_sets": {"Surf_Smokescreen_XAttack": {"win": 1, "lost": 2}}}, "MugiwarcTTV": {"win": 19, "lost": 3, "battle_sets": {"Water Shuriken_Double Team_Potion": {"win": 18, "lost": 3}, "Surf_Double Team_Potion": {"win": 1, "lost": 0}}}, "\u6b7batited04": {"win": 4, "lost": 2, "battle_sets": {"Water Shuriken_Smokescreen_XAttack": {"win": 1, "lost": 0}, "Surf_Smokescreen_XAttack": {"win": 3, "lost": 2}}}, "\u3042_\u3052": {"win": 6, "lost": 2, "battle_sets": {"Surf_Smokescreen_XAttack": {"win": 6, "lost": 2}}}, "OMO\u30e1Nafylno": {"win": 2, "lost": 0, "battle_sets": {"Surf_Smokescreen_XAttack": {"win": 2, "lost": 0}}}, "S\u012bmp": {"win": 2, "lost": 1, "battle_sets": {"Surf_Smokescreen_XAttack": {"win": 2, "lost": 1}}}, "5i\u30fbKeep": {"win": 1, "lost": 0, "battle_sets": {"Surf_Smokescreen_EjectButton": {"win": 1, "lost": 0}}}, "Trafyyy": {"win": 14, "lost": 12, "battle_sets": {"Surf_Smokescreen_EjectButton": {"win": 14, "lost": 12}}}, "TILTED\u00d7Y\u00fbta": {"win": 1, "lost": 0, "battle_sets": {"Surf_Smokescreen_EjectButton": {"win": 1, "lost": 0}}}, "\u30fbJohn\u30fb": {"win": 4, "lost": 0, "battle_sets": {"Surf_Smokescreen_XAttack": {"win": 4, "lost": 0}}}, "S4L-": {"win": 0, "lost": 1, "battle_sets": {"Surf_Smokescreen_XAttack": {"win": 0, "lost": 1}}}, "T2_Mame": {"win": 2, "lost": 1, "battle_sets": {"Surf_Smokescreen_XAttack": {"win": 2, "lost": 1}}}, "\u96a0\u5c45\u3057\u307e\u3057\u305f": {"win": 1, "lost": 0, "battle_sets": {"Surf_Smokescreen_XAttack": {"win": 1, "lost": 0}}}, "\u5b9f\u306f\u30d4\u30af\u30bd\u30eb": {"win": 0, "lost": 1, "battle_sets": {"Surf_Smokescreen_EjectButton": {"win": 0, "lost": 1}}}, "Jaypa\u30c4": {"win": 0, "lost": 1, "battle_sets": {"Surf_Smokescreen_EjectButton": {"win": 0, "lost": 1}}}, "Overseert": {"win": 6, "lost": 2, "battle_sets": {"Surf_Smokescreen_Purify": {"win": 6, "lost": 2}}}, "\u6953\u5c02\u304b\u3073\u304d\u3089": {"win": 0, "lost": 1, "battle_sets": {"Surf_Smokescreen_XAttack": {"win": 0, "lost": 1}}}}, "battle_sets": {"Surf_Smokescreen_XAttack": {"win": 36, "lost": 19}, "Surf_Smokescreen_Purify": {"win": 8, "lost": 4}, "Water Shuriken_Double Team_EjectButton": {"win": 1, "lost": 0}, "Surf_Smokescreen_EjectButton": {"win": 22, "lost": 14}, "Water Shuriken_Double Team_Potion": {"win": 18, "lost": 3}, "Surf_Double Team_Potion": {"win": 1, "lost": 0}, "Water Shuriken_Smokescreen_XAttack": {"win": 1, "lost": 0}}}, "Mamoswine": {"win": 32, "lost": 14, "players": {"RJG\u30fbRuvis": {"win": 1, "lost": 0, "battle_sets": {"Ice Fang_High Horsepower_EjectButton": {"win": 1, "lost": 0}}}, "Metallic\u30c4": {"win": 1, "lost": 1, "battle_sets": {"Icicle Crash_High Horsepower_EjectButton": {"win": 1, "lost": 1}}}, "Jjacky": {"win": 23, "lost": 9, "battle_sets": {"Icicle Crash_High Horsepower_Potion": {"win": 19, "lost": 8}, "Ice Fang_High Horsepower_Potion": {"win": 4, "lost": 1}}}, "\u3042_\u3052": {"win": 0, "lost": 1, "battle_sets": {"Icicle Crash_High Horsepower_EjectButton": {"win": 0, "lost": 1}}}, "\ud6c8\ud3ec\ub3c4": {"win": 4, "lost": 2, "battle_sets": {"Ice Fang_Earthquake_Potion": {"win": 1, "lost": 0}, "Ice Fang_High Horsepower_Potion": {"win": 3, "lost": 1}, "Icicle Crash_High Horsepower_Potion": {"win": 0, "lost": 1}}}, "Jaypa\u30c4": {"win": 2, "lost": 0, "battle_sets": {"Icicle Crash_High Horsepower_EjectButton": {"win": 2, "lost": 0}}}, "j\u0139": {"win": 1, "lost": 1, "battle_sets": {"Icicle Crash_High Horsepower_Potion": {"win": 1, "lost": 1}}}}, "battle_sets": {"Ice Fang_High Horsepower_EjectButton": {"win": 1, "lost": 0}, "Icicle Crash_High Horsepower_EjectButton": {"win": 3, "lost": 2}, "Icicle Crash_High Horsepower_Potion": {"win": 20, "lost": 10}, "Ice Fang_High Horsepower_Potion": {"win": 7, "lost": 2}, "Ice Fang_Earthquake_Potion": {"win": 1, "lost": 0}}}, "Snorlax": {"win": 8, "lost": 9, "players": {"RJG\u30fbRuvis": {"win": 1, "lost": 0, "battle_sets": {"__XSpeed": {"win": 1, "lost": 0}}}, "DanielMil": {"win": 1, "lost": 1, "battle_sets": {"__EjectButton": {"win": 1, "lost": 1}}}, "\u3042_\u3052": {"win": 2, "lost": 2, "battle_sets": {"__XSpeed": {"win": 2, "lost": 2}}}, "\u96a0\u5c45\u3057\u307e\u3057\u305f": {"win": 1, "lost": 0, "battle_sets": {"__XSpeed": {"win": 1, "lost": 0}}}, "Evilgenius2": {"win": 0, "lost": 3, "battle_sets": {"__XSpeed": {"win": 0, "lost": 3}}}, "Jaypa\u30c4": {"win": 1, "lost": 1, "battle_sets": {"__XSpeed": {"win": 1, "lost": 1}}}, "Cr\u00f3ng": {"win": 2, "lost": 2, "battle_sets": {"__EjectButton": {"win": 2, "lost": 2}}}}, "battle_sets": {"__XSpeed": {"win": 5, "lost": 6}, "__EjectButton": {"win": 3, "lost": 3}}}, "Charizard": {"win": 26, "lost": 8, "players": {"Wulf?": {"win": 16, "lost": 2, "battle_sets": {"Flamethrower_Fire Blast_XAttack": {"win": 14, "lost": 2}, "Flamethrower_Flare Blitz_XAttack": {"win": 1, "lost": 0}, "Fire Punch_Fire Blast_XAttack": {"win": 1, "lost": 0}}}, "AramisCe": {"win": 0, "lost": 1, "battle_sets": {"Flamethrower_Fire Blast_XSpeed": {"win": 0, "lost": 1}}}, "TE\u30fbFreaK": {"win": 3, "lost": 1, "battle_sets": {"Flamethrower_Fire Blast_XSpeed": {"win": 3, "lost": 1}}}, "S\u012bmp": {"win": 0, "lost": 1, "battle_sets": {"Flamethrower_Flare Blitz_XAttack": {"win": 0, "lost": 1}}}, "T2_Mame": {"win": 1, "lost": 0, "battle_sets": {"Flamethrower_Fire Blast_XSpeed": {"win": 1, "lost": 0}}}, "ttv_mMALIKx": {"win": 2, "lost": 1, "battle_sets": {"Flamethrower_Fire Blast_XAttack": {"win": 2, "lost": 1}}}, "RENAMED": {"win": 4, "lost": 1, "battle_sets": {"Flamethrower_Fire Blast_XSpeed": {"win": 4, "lost": 1}}}, "Overseert": {"win": 0, "lost": 1, "battle_sets": {"Flamethrower_Fire Blast_XSpeed": {"win": 0, "lost": 1}}}}, "battle_sets": {"Flamethrower_Fire Blast_XAttack": {"win": 16, "lost": 3}, "Flamethrower_Flare Blitz_XAttack": {"win": 1, "lost": 1}, "Fire Punch_Fire Blast_XAttack": {"win": 1, "lost": 0}, "Flamethrower_Fire Blast_XSpeed": {"win": 8, "lost": 4}}}, "Mr. Mime": {"win": 9, "lost": 8, "players": {"Metallic\u30c4": {"win": 2, "lost": 1, "battle_sets": {"Confusion_Barrier_XAttack": {"win": 2, "lost": 1}}}, "\u9811\u5f35\u308d\u3046ww": {"win": 4, "lost": 1, "battle_sets": {"Confusion_Guard Swap_XSpeed": {"win": 4, "lost": 1}}}, "\u79cb\u6d25\u831c": {"win": 0, "lost": 1, "battle_sets": {"Confusion_Guard Swap_XSpeed": {"win": 0, "lost": 1}}}, "\u62b1\u3048\u843d\u3061\u8b66\u5bdf": {"win": 0, "lost": 1, "battle_sets": {"Confusion_Guard Swap_XSpeed": {"win": 0, "lost": 1}}}, "McToffin": {"win": 3, "lost": 4, "battle_sets": {"Confusion_Guard Swap_XSpeed": {"win": 3, "lost": 4}}}}, "battle_sets": {"Confusion_Barrier_XAttack": {"win": 2, "lost": 1}, "Confusion_Guard Swap_XSpeed": {"win": 7, "lost": 7}}}, "Absol": {"win": 2, "lost": 2, "players": {"Metallic\u30c4": {"win": 1, "lost": 1, "battle_sets": {"Pursuit_Psycho Cut_XAttack": {"win": 1, "lost": 1}}}, "Trafyyy": {"win": 1, "lost": 0, "battle_sets": {"Night Slash_Psycho Cut_Tail": {"win": 1, "lost": 0}}}, "SirWaddleChu": {"win": 0, "lost": 1, "battle_sets": {"Pursuit_Sucker Punch_EjectButton": {"win": 0, "lost": 1}}}}, "battle_sets": {"Pursuit_Psycho Cut_XAttack": {"win": 1, "lost": 1}, "Night Slash_Psycho Cut_Tail": {"win": 1, "lost": 0}, "Pursuit_Sucker Punch_EjectButton": {"win": 0, "lost": 1}}}, "Crustle": {"win": 7, "lost": 3, "players": {"Metallic\u30c4": {"win": 2, "lost": 0, "battle_sets": {"Shell Smash_X-Scissor_XAttack": {"win": 2, "lost": 0}}}, "TE\u30fbFreaK": {"win": 1, "lost": 0, "battle_sets": {"Shell Smash_X-Scissor_XAttack": {"win": 1, "lost": 0}}}, "99\u30e0Sensei": {"win": 2, "lost": 3, "battle_sets": {"Rock Tomb_X-Scissor_EjectButton": {"win": 1, "lost": 0}, "Shell Smash_X-Scissor_EjectButton": {"win": 1, "lost": 3}}}, "McToffin": {"win": 2, "lost": 0, "battle_sets": {"Shell Smash_X-Scissor_XSpeed": {"win": 2, "lost": 0}}}}, "battle_sets": {"Shell Smash_X-Scissor_XAttack": {"win": 3, "lost": 0}, "Rock Tomb_X-Scissor_EjectButton": {"win": 1, "lost": 0}, "Shell Smash_X-Scissor_EjectButton": {"win": 1, "lost": 3}, "Shell Smash_X-Scissor_XSpeed": {"win": 2, "lost": 0}}}, "Azumarill": {"win": 79, "lost": 29, "players": {"AFR\u30fbMiva": {"win": 6, "lost": 4, "battle_sets": {"Water Pulse_Whirlpool_XSpeed": {"win": 5, "lost": 3}, "Play Rough_Whirlpool_XSpeed": {"win": 1, "lost": 1}}}, "LuvYusuf": {"win": 33, "lost": 6, "battle_sets": {"Water Pulse_Whirlpool_XAttack": {"win": 33, "lost": 6}}}, "\u6b7batited04": {"win": 1, "lost": 0, "battle_sets": {"Water Pulse_Whirlpool_XSpeed": {"win": 1, "lost": 0}}}, "ZPRR.Nevorix": {"win": 23, "lost": 7, "battle_sets": {"Water Pulse_Aqua Tail_XAttack": {"win": 23, "lost": 7}}}, "\u5b9f\u306f\u30d4\u30af\u30bd\u30eb": {"win": 1, "lost": 0, "battle_sets": {"Water Pulse_Aqua Tail_XAttack": {"win": 1, "lost": 0}}}, "\ud6c8\ud3ec\ub3c4": {"win": 0, "lost": 1, "battle_sets": {"Water Pulse_Whirlpool_XAttack": {"win": 0, "lost": 1}}}, "\u79cb\u6d25\u831c": {"win": 3, "lost": 0, "battle_sets": {"Play Rough_Whirlpool_XAttack": {"win": 3, "lost": 0}}}, "McToffin": {"win": 12, "lost": 11, "battle_sets": {"Water Pulse_Aqua Tail_XSpeed": {"win": 12, "lost": 11}}}}, "battle_sets": {"Water Pulse_Whirlpool_XSpeed": {"win": 6, "lost": 3}, "Play Rough_Whirlpool_XSpeed": {"win": 1, "lost": 1}, "Water Pulse_Whirlpool_XAttack": {"win": 33, "lost": 7}, "Water Pulse_Aqua Tail_XAttack": {"win": 24, "lost": 7}, "Play Rough_Whirlpool_XAttack": {"win": 3, "lost": 0}, "Water Pulse_Aqua Tail_XSpeed": {"win": 12, "lost": 11}}}, "Blastoise": {"win": 18, "lost": 3, "players": {"\u9811\u5f35\u308d\u3046ww": {"win": 1, "lost": 1, "battle_sets": {"Water Spout_Rapid Spin_EjectButton": {"win": 1, "lost": 1}}}, "ttvGhatlue": {"win": 1, "lost": 0, "battle_sets": {"Water Spout_Rapid Spin_EjectButton": {"win": 1, "lost": 0}}}, "\ud37c\ubc0d": {"win": 1, "lost": 0, "battle_sets": {"Water Spout_Rapid Spin_EjectButton": {"win": 1, "lost": 0}}}, "TE\u30fbFreaK": {"win": 2, "lost": 0, "battle_sets": {"Hydro Pump_Surf_EjectButton": {"win": 1, "lost": 0}, "Hydro Pump_Rapid Spin_EjectButton": {"win": 1, "lost": 0}}}, "S\u012bmp": {"win": 1, "lost": 0, "battle_sets": {"Water Spout_Rapid Spin_EjectButton": {"win": 1, "lost": 0}}}, "\u5b9f\u306f\u30d4\u30af\u30bd\u30eb": {"win": 3, "lost": 0, "battle_sets": {"Hydro Pump_Surf_EjectButton": {"win": 3, "lost": 0}}}, "\ud6c8\ud3ec\ub3c4": {"win": 8, "lost": 1, "battle_sets": {"Water Spout_Rapid Spin_EjectButton": {"win": 8, "lost": 1}}}, "Jaypa\u30c4": {"win": 0, "lost": 1, "battle_sets": {"Hydro Pump_Surf_EjectButton": {"win": 0, "lost": 1}}}, "Cr\u00f3ng": {"win": 1, "lost": 0, "battle_sets": {"Water Spout_Rapid Spin_EjectButton": {"win": 1, "lost": 0}}}}, "battle_sets": {"Water Spout_Rapid Spin_EjectButton": {"win": 13, "lost": 2}, "Hydro Pump_Surf_EjectButton": {"win": 4, "lost": 1}, "Hydro Pump_Rapid Spin_EjectButton": {"win": 1, "lost": 0}}}, "Gengar": {"win": 38, "lost": 20, "players": {"ttvGhatlue": {"win": 1, "lost": 1, "battle_sets": {"Shadow Ball_Dream Eater_EjectButton": {"win": 1, "lost": 0}, "Sludge Bomb_Hex_EjectButton": {"win": 0, "lost": 1}}}, "MW\u30fbAngel\u30b7": {"win": 1, "lost": 0, "battle_sets": {"Shadow Ball_Dream Eater_EjectButton": {"win": 1, "lost": 0}}}, "AramisCe": {"win": 0, "lost": 1, "battle_sets": {"Shadow Ball_Dream Eater_EjectButton": {"win": 0, "lost": 1}}}, "\u3042_\u3052": {"win": 4, "lost": 0, "battle_sets": {"Sludge Bomb_Hex_Purify": {"win": 4, "lost": 0}}}, "OMO\u30e1Nafylno": {"win": 1, "lost": 0, "battle_sets": {"Sludge Bomb_Hex_EjectButton": {"win": 1, "lost": 0}}}, "5i\u30fbKeep": {"win": 1, "lost": 0, "battle_sets": {"Shadow Ball_Dream Eater_EjectButton": {"win": 1, "lost": 0}}}, "Espoir\u0421\u0432\u0451\u0442": {"win": 0, "lost": 2, "battle_sets": {"Shadow Ball_Dream Eater_XAttack": {"win": 0, "lost": 1}, "Sludge Bomb_Hex_XAttack": {"win": 0, "lost": 1}}}, "S4L-": {"win": 1, "lost": 0, "battle_sets": {"Shadow Ball_Dream Eater_EjectButton": {"win": 1, "lost": 0}}}, "T2_Mame": {"win": 9, "lost": 3, "battle_sets": {"Sludge Bomb_Hex_XSpeed": {"win": 4, "lost": 1}, "Shadow Ball_Dream Eater_XSpeed": {"win": 1, "lost": 1}, "Sludge Bomb_Hex_Purify": {"win": 4, "lost": 1}}}, "BoraReach": {"win": 19, "lost": 11, "battle_sets": {"Sludge Bomb_Hex_XSpeed": {"win": 19, "lost": 11}}}, "Evilgenius2": {"win": 1, "lost": 0, "battle_sets": {"Shadow Ball_Dream Eater_EjectButton": {"win": 1, "lost": 0}}}, "ADESu23\u30fbTTV": {"win": 0, "lost": 1, "battle_sets": {"Sludge Bomb_Hex_Purify": {"win": 0, "lost": 1}}}, "\u6953\u5c02\u304b\u3073\u304d\u3089": {"win": 0, "lost": 1, "battle_sets": {"Sludge Bomb_Hex_Purify": {"win": 0, "lost": 1}}}}, "battle_sets": {"Shadow Ball_Dream Eater_EjectButton": {"win": 5, "lost": 1}, "Sludge Bomb_Hex_EjectButton": {"win": 1, "lost": 1}, "Sludge Bomb_Hex_Purify": {"win": 8, "lost": 3}, "Shadow Ball_Dream Eater_XAttack": {"win": 0, "lost": 1}, "Sludge Bomb_Hex_XAttack": {"win": 0, "lost": 1}, "Sludge Bomb_Hex_XSpeed": {"win": 23, "lost": 12}, "Shadow Ball_Dream Eater_XSpeed": {"win": 1, "lost": 1}}}, "Greedent": {"win": 87, "lost": 27, "players": {"ttvGhatlue": {"win": 1, "lost": 1, "battle_sets": {"Belch_Covet_Tail": {"win": 1, "lost": 1}}}, "TE\u30fbFreaK": {"win": 0, "lost": 1, "battle_sets": {"Belch_Covet_Ganrao": {"win": 0, "lost": 1}}}, "99\u30e0Sensei": {"win": 17, "lost": 5, "battle_sets": {"Belch_Covet_Tail": {"win": 17, "lost": 5}}}, "\u6b7batited04": {"win": 24, "lost": 6, "battle_sets": {"Belch_Covet_XSpeed": {"win": 3, "lost": 3}, "Belch_Covet_Tail": {"win": 16, "lost": 3}, "Belch_Stuff Cheeks_Tail": {"win": 1, "lost": 0}, "Bullet Seed_Stuff Cheeks_Tail": {"win": 1, "lost": 0}, "Bullet Seed_Stuff Cheeks_XSpeed": {"win": 2, "lost": 0}, "Belch_Stuff Cheeks_XSpeed": {"win": 1, "lost": 0}}}, "BabyTurtle4": {"win": 34, "lost": 9, "battle_sets": {"Belch_Covet_Potion": {"win": 34, "lost": 9}}}, "\u79cb\u6d25\u831c": {"win": 1, "lost": 1, "battle_sets": {"Belch_Covet_Tail": {"win": 1, "lost": 1}}}, "\u3064\u306b\u304d": {"win": 10, "lost": 4, "battle_sets": {"Belch_Covet_Tail": {"win": 10, "lost": 4}}}}, "battle_sets": {"Belch_Covet_Tail": {"win": 45, "lost": 14}, "Belch_Covet_Ganrao": {"win": 0, "lost": 1}, "Belch_Covet_XSpeed": {"win": 3, "lost": 3}, "Belch_Stuff Cheeks_Tail": {"win": 1, "lost": 0}, "Bullet Seed_Stuff Cheeks_Tail": {"win": 1, "lost": 0}, "Bullet Seed_Stuff Cheeks_XSpeed": {"win": 2, "lost": 0}, "Belch_Stuff Cheeks_XSpeed": {"win": 1, "lost": 0}, "Belch_Covet_Potion": {"win": 34, "lost": 9}}}, "Cinderace": {"win": 58, "lost": 19, "players": {"ENT\u30fbScepTer": {"win": 1, "lost": 0, "battle_sets": {"Blaze Kick_Flame Charge_Purify": {"win": 1, "lost": 0}}}, "caligola999": {"win": 0, "lost": 1, "battle_sets": {"Blaze Kick_Flame Charge_EjectButton": {"win": 0, "lost": 1}}}, "OMO\u30e1Phoenix": {"win": 0, "lost": 1, "battle_sets": {"Blaze Kick_Flame Charge_EjectButton": {"win": 0, "lost": 1}}}, "\ub108\ub3c4\ub0b4\uaebc": {"win": 1, "lost": 0, "battle_sets": {"Blaze Kick_Flame Charge_EjectButton": {"win": 1, "lost": 0}}}, "IsWillTV\u30c4": {"win": 1, "lost": 0, "battle_sets": {"Blaze Kick_Flame Charge_EjectButton": {"win": 1, "lost": 0}}}, "BB\u30fbOsIrIs": {"win": 2, "lost": 0, "battle_sets": {"Blaze Kick_Flame Charge_XAttack": {"win": 2, "lost": 0}}}, "20FF": {"win": 13, "lost": 5, "battle_sets": {"Blaze Kick_Flame Charge_XAttack": {"win": 13, "lost": 5}}}, "\u3042_\u3052": {"win": 5, "lost": 2, "battle_sets": {"Blaze Kick_Flame Charge_XAttack": {"win": 5, "lost": 2}}}, "S\u012bmp": {"win": 5, "lost": 0, "battle_sets": {"Blaze Kick_Flame Charge_EjectButton": {"win": 5, "lost": 0}}}, "5i\u30fbKeep": {"win": 1, "lost": 0, "battle_sets": {"Blaze Kick_Flame Charge_EjectButton": {"win": 1, "lost": 0}}}, "Trafyyy": {"win": 1, "lost": 3, "battle_sets": {"Blaze Kick_Flame Charge_EjectButton": {"win": 1, "lost": 3}}}, "TILTED\u00d7Y\u00fbta": {"win": 1, "lost": 0, "battle_sets": {"Blaze Kick_Flame Charge_EjectButton": {"win": 1, "lost": 0}}}, "\u30fbJohn\u30fb": {"win": 7, "lost": 2, "battle_sets": {"Blaze Kick_Flame Charge_EjectButton": {"win": 7, "lost": 2}}}, "T2_Mame": {"win": 0, "lost": 1, "battle_sets": {"Blaze Kick_Flame Charge_EjectButton": {"win": 0, "lost": 1}}}, "\u5b9f\u306f\u30d4\u30af\u30bd\u30eb": {"win": 1, "lost": 1, "battle_sets": {"Blaze Kick_Flame Charge_EjectButton": {"win": 1, "lost": 1}}}, "ttv_mMALIKx": {"win": 19, "lost": 2, "battle_sets": {"Blaze Kick_Flame Charge_EjectButton": {"win": 19, "lost": 2}}}, "Overseert": {"win": 0, "lost": 1, "battle_sets": {"Blaze Kick_Flame Charge_Purify": {"win": 0, "lost": 1}}}}, "battle_sets": {"Blaze Kick_Flame Charge_Purify": {"win": 1, "lost": 1}, "Blaze Kick_Flame Charge_EjectButton": {"win": 37, "lost": 11}, "Blaze Kick_Flame Charge_XAttack": {"win": 20, "lost": 7}}}, "Duraludon": {"win": 21, "lost": 8, "players": {"OMO\u30e1Phoenix": {"win": 1, "lost": 0, "battle_sets": {"Dragon Pulse_Dragon Tail_XAttack": {"win": 1, "lost": 0}}}, "IsWillTV\u30c4": {"win": 12, "lost": 4, "battle_sets": {"Dragon Pulse_Dragon Tail_XAttack": {"win": 12, "lost": 4}}}, "\u3042_\u3052": {"win": 0, "lost": 1, "battle_sets": {"Flash Cannon_Stealth Rock_Purify": {"win": 0, "lost": 1}}}, "BB\u30fbSkyfire": {"win": 0, "lost": 1, "battle_sets": {"Dragon Pulse_Dragon Tail_XAttack": {"win": 0, "lost": 1}}}, "\u5b9f\u306f\u30d4\u30af\u30bd\u30eb": {"win": 1, "lost": 0, "battle_sets": {"Flash Cannon_Dragon Tail_Purify": {"win": 1, "lost": 0}}}, "Jaypa\u30c4": {"win": 7, "lost": 2, "battle_sets": {"Dragon Pulse_Stealth Rock_XAttack": {"win": 1, "lost": 0}, "Dragon Pulse_Dragon Tail_XAttack": {"win": 5, "lost": 2}, "Flash Cannon_Dragon Tail_XAttack": {"win": 1, "lost": 0}}}}, "battle_sets": {"Dragon Pulse_Dragon Tail_XAttack": {"win": 18, "lost": 7}, "Flash Cannon_Stealth Rock_Purify": {"win": 0, "lost": 1}, "Flash Cannon_Dragon Tail_Purify": {"win": 1, "lost": 0}, "Dragon Pulse_Stealth Rock_XAttack": {"win": 1, "lost": 0}, "Flash Cannon_Dragon Tail_XAttack": {"win": 1, "lost": 0}}}, "Espeon": {"win": 13, "lost": 2, "players": {"5i\u30fbInferno": {"win": 4, "lost": 1, "battle_sets": {"Psyshock_Psybeam_EjectButton": {"win": 4, "lost": 1}}}, "AkumaCx": {"win": 2, "lost": 0, "battle_sets": {"Psyshock_Psybeam_XSpeed": {"win": 2, "lost": 0}}}, "ttvSixsies": {"win": 7, "lost": 1, "battle_sets": {"Psyshock_Future Sight_XSpeed": {"win": 1, "lost": 0}, "Psyshock_Psybeam_XSpeed": {"win": 6, "lost": 1}}}}, "battle_sets": {"Psyshock_Psybeam_EjectButton": {"win": 4, "lost": 1}, "Psyshock_Psybeam_XSpeed": {"win": 8, "lost": 1}, "Psyshock_Future Sight_XSpeed": {"win": 1, "lost": 0}}}, "Talonflame": {"win": 8, "lost": 2, "players": {"OMO\u30e1Nafylno": {"win": 1, "lost": 0, "battle_sets": {"__EjectButton": {"win": 1, "lost": 0}}}, "S\u012bmp": {"win": 1, "lost": 0, "battle_sets": {"__XAttack": {"win": 1, "lost": 0}}}, "EMPxSorA\u53f3": {"win": 1, "lost": 0, "battle_sets": {"__EjectButton": {"win": 1, "lost": 0}}}, "T2_Mame": {"win": 2, "lost": 1, "battle_sets": {"__XAttack": {"win": 1, "lost": 0}, "__Ganrao": {"win": 1, "lost": 1}}}, "\u5b9f\u306f\u30d4\u30af\u30bd\u30eb": {"win": 1, "lost": 0, "battle_sets": {"__EjectButton": {"win": 1, "lost": 0}}}, "ttv_mMALIKx": {"win": 2, "lost": 0, "battle_sets": {"__XAttack": {"win": 2, "lost": 0}}}, "\u79cb\u6d25\u831c": {"win": 0, "lost": 1, "battle_sets": {"__XAttack": {"win": 0, "lost": 1}}}}, "battle_sets": {"__EjectButton": {"win": 3, "lost": 0}, "__XAttack": {"win": 4, "lost": 1}, "__Ganrao": {"win": 1, "lost": 1}}}, "Eldegoss": {"win": 0, "lost": 1, "players": {"Trafyyy": {"win": 0, "lost": 1, "battle_sets": {"Leaf Tornado_Cotton Guard_XAttack": {"win": 0, "lost": 1}}}}, "battle_sets": {"Leaf Tornado_Cotton Guard_XAttack": {"win": 0, "lost": 1}}}}, "match_count": 1702}