{"pokemons": {"Pikachu": {"win": 70, "lost": 26, "players": {"CeS\u68a6Inf\u00ed": {"win": 34, "lost": 8, "battle_sets": {"Thunder_Thunderbolt_XSpeed": {"win": 33, "lost": 5}, "Electro Ball_Volt Tackle_XSpeed": {"win": 1, "lost": 3}}}, "ENT\u30fbScepTer": {"win": 3, "lost": 0, "battle_sets": {"Thunder_Thunderbolt_EjectButton": {"win": 3, "lost": 0}}}, "5i\u30fbKeep": {"win": 0, "lost": 1, "battle_sets": {"Electro Ball_Volt Tackle_Potion": {"win": 0, "lost": 1}}}, "MW\u30fbMax": {"win": 1, "lost": 0, "battle_sets": {"Thunder_Thunderbolt_EjectButton": {"win": 1, "lost": 0}}}, "GZ\u30fbJoe": {"win": 1, "lost": 1, "battle_sets": {"Electro Ball_Volt Tackle_XSpeed": {"win": 1, "lost": 1}}}, "RJG\u30fbRuvis": {"win": 0, "lost": 1, "battle_sets": {"Thunder_Volt Tackle_XSpeed": {"win": 0, "lost": 1}}}, "5i\u30fbInferno": {"win": 1, "lost": 0, "battle_sets": {"Electro Ball_Thunderbolt_EjectButton": {"win": 1, "lost": 0}}}, "YORU04": {"win": 4, "lost": 0, "battle_sets": {"Thunder_Thunderbolt_XSpeed": {"win": 4, "lost": 0}}}, "\u308f\u3089\u3089\u308a\u3063\u304f": {"win": 1, "lost": 0, "battle_sets": {"Thunder_Volt Tackle_EjectButton": {"win": 1, "lost": 0}}}, "Aurimakii": {"win": 2, "lost": 2, "battle_sets": {"Electro Ball_Volt Tackle_EjectButton": {"win": 1, "lost": 1}, "Electro Ball_Thunderbolt_EjectButton": {"win": 0, "lost": 1}, "Thunder_Thunderbolt_EjectButton": {"win": 1, "lost": 0}}}, "\u304a\u3044\u304b\u3073\u304d\u3089": {"win": 0, "lost": 2, "battle_sets": {"Thunder_Thunderbolt_XSpeed": {"win": 0, "lost": 2}}}, "ZapWarudo": {"win": 1, "lost": 1, "battle_sets": {"Thunder_Thunderbolt_EjectButton": {"win": 1, "lost": 1}}}, "jatinjwin": {"win": 11, "lost": 4, "battle_sets": {"Thunder_Thunderbolt_XSpeed": {"win": 11, "lost": 4}}}, "Kuus\u00ed": {"win": 1, "lost": 1, "battle_sets": {"Thunder_Thunderbolt_EjectButton": {"win": 1, "lost": 1}}}, "KK_4E": {"win": 4, "lost": 1, "battle_sets": {"Thunder_Thunderbolt_XSpeed": {"win": 4, "lost": 1}}}, "01Agno": {"win": 0, "lost": 1, "battle_sets": {"Thunder_Thunderbolt_EjectButton": {"win": 0, "lost": 1}}}, "RJG\u30fbikura": {"win": 1, "lost": 0, "battle_sets": {"Thunder_Volt Tackle_EjectButton": {"win": 1, "lost": 0}}}, "HMB_runpa": {"win": 1, "lost": 0, "battle_sets": {"Electro Ball_Volt Tackle_EjectButton": {"win": 1, "lost": 0}}}, "SirWaddleChu": {"win": 4, "lost": 2, "battle_sets": {"Thunder_Thunderbolt_XSpeed": {"win": 4, "lost": 2}}}, "\u5bc4\u751f\u5263\u5080\u5121\u5efb": {"win": 0, "lost": 1, "battle_sets": {"Electro Ball_Volt Tackle_EjectButton": {"win": 0, "lost": 1}}}}, "battle_sets": {"Thunder_Thunderbolt_XSpeed": {"win": 56, "lost": 14}, "Electro Ball_Volt Tackle_XSpeed": {"win": 2, "lost": 4}, "Thunder_Thunderbolt_EjectButton": {"win": 7, "lost": 3}, "Electro Ball_Volt Tackle_Potion": {"win": 0, "lost": 1}, "Thunder_Volt Tackle_XSpeed": {"win": 0, "lost": 1}, "Electro Ball_Thunderbolt_EjectButton": {"win": 1, "lost": 1}, "Thunder_Volt Tackle_EjectButton": {"win": 2, "lost": 0}, "Electro Ball_Volt Tackle_EjectButton": {"win": 2, "lost": 2}}}, "Blissey": {"win": 108, "lost": 31, "players": {"CeS\u68a6Inf\u00ed": {"win": 1, "lost": 0, "battle_sets": {"Egg Bomb_Safeguard_XSpeed": {"win": 1, "lost": 0}}}, "KlausVIII": {"win": 2, "lost": 0, "battle_sets": {"Egg Bomb_Safeguard_XSpeed": {"win": 1, "lost": 0}, "Egg Bomb_Soft-Boiled_XSpeed": {"win": 1, "lost": 0}}}, "\u3042_\u3052": {"win": 2, "lost": 0, "battle_sets": {"Helping Hand_Safeguard_XSpeed": {"win": 2, "lost": 0}}}, "RNS\u30e4NT\u30c4": {"win": 21, "lost": 7, "battle_sets": {"Egg Bomb_Soft-Boiled_XSpeed": {"win": 19, "lost": 5}, "Helping Hand_Safeguard_XSpeed": {"win": 1, "lost": 2}, "Helping Hand_Soft-Boiled_XSpeed": {"win": 1, "lost": 0}}}, "MW\u30fbTwoKiiL": {"win": 21, "lost": 4, "battle_sets": {"Egg Bomb_Safeguard_XSpeed": {"win": 9, "lost": 2}, "Helping Hand_Safeguard_XSpeed": {"win": 11, "lost": 2}, "Egg Bomb_Soft-Boiled_XSpeed": {"win": 1, "lost": 0}}}, "PotatoUwU": {"win": 2, "lost": 1, "battle_sets": {"Egg Bomb_Soft-Boiled_XAttack": {"win": 2, "lost": 0}, "Egg Bomb_Soft-Boiled_XSpeed": {"win": 0, "lost": 1}}}, "MW\u30fbMax": {"win": 2, "lost": 0, "battle_sets": {"Egg Bomb_Safeguard_XSpeed": {"win": 2, "lost": 0}}}, "TO\u30fbDrako": {"win": 3, "lost": 2, "battle_sets": {"Egg Bomb_Safeguard_XSpeed": {"win": 3, "lost": 2}}}, "RJG\u30fbRuvis": {"win": 5, "lost": 3, "battle_sets": {"Helping Hand_Safeguard_XSpeed": {"win": 1, "lost": 1}, "Egg Bomb_Soft-Boiled_XSpeed": {"win": 4, "lost": 1}, "Egg Bomb_Safeguard_XSpeed": {"win": 0, "lost": 1}}}, "TE\u30fbTibi": {"win": 4, "lost": 3, "battle_sets": {"Egg Bomb_Soft-Boiled_XSpeed": {"win": 2, "lost": 0}, "Helping Hand_Safeguard_XSpeed": {"win": 2, "lost": 3}}}, "ttvSixsies": {"win": 2, "lost": 0, "battle_sets": {"Egg Bomb_Soft-Boiled_XSpeed": {"win": 2, "lost": 0}}}, ":p-Bnj": {"win": 1, "lost": 0, "battle_sets": {"Egg Bomb_Soft-Boiled_XSpeed": {"win": 1, "lost": 0}}}, "\u3086\u3081\u306b\u3083\u3093": {"win": 21, "lost": 1, "battle_sets": {"Egg Bomb_Soft-Boiled_XSpeed": {"win": 20, "lost": 1}, "Egg Bomb_Soft-Boiled_EjectButton": {"win": 1, "lost": 0}}}, "TAC\u30fbWalt": {"win": 2, "lost": 2, "battle_sets": {"Egg Bomb_Safeguard_XSpeed": {"win": 2, "lost": 0}, "Egg Bomb_Soft-Boiled_XSpeed": {"win": 0, "lost": 1}, "Helping Hand_Safeguard_XSpeed": {"win": 0, "lost": 1}}}, "Kuus\u00ed": {"win": 0, "lost": 1, "battle_sets": {"Egg Bomb_Safeguard_XSpeed": {"win": 0, "lost": 1}}}, "\u6687\u306a\u6771\u5927\u751f": {"win": 0, "lost": 1, "battle_sets": {"Helping Hand_Safeguard_EjectButton": {"win": 0, "lost": 1}}}, "Bolbi": {"win": 6, "lost": 2, "battle_sets": {"Egg Bomb_Soft-Boiled_XSpeed": {"win": 5, "lost": 1}, "Helping Hand_Safeguard_XSpeed": {"win": 1, "lost": 0}, "Egg Bomb_Safeguard_XSpeed": {"win": 0, "lost": 1}}}, "STMN\u30fbKira": {"win": 4, "lost": 0, "battle_sets": {"Egg Bomb_Safeguard_XSpeed": {"win": 3, "lost": 0}, "Egg Bomb_Soft-Boiled_XSpeed": {"win": 1, "lost": 0}}}, "\u4e5bMyst": {"win": 4, "lost": 0, "battle_sets": {"Egg Bomb_Safeguard_XSpeed": {"win": 4, "lost": 0}}}, "RJG\u30fbikura": {"win": 1, "lost": 0, "battle_sets": {"Helping Hand_Safeguard_XSpeed": {"win": 1, "lost": 0}}}, "tvAtlasTauri": {"win": 1, "lost": 1, "battle_sets": {"Egg Bomb_Safeguard_XSpeed": {"win": 1, "lost": 1}}}, "\u30d1\u30ca\u30d7\u541b": {"win": 0, "lost": 1, "battle_sets": {"Helping Hand_Safeguard_XSpeed": {"win": 0, "lost": 1}}}, "LINH": {"win": 1, "lost": 0, "battle_sets": {"Helping Hand_Safeguard_Gear": {"win": 1, "lost": 0}}}, "\u5bc4\u751f\u5263\u5080\u5121\u5efb": {"win": 1, "lost": 0, "battle_sets": {"Helping Hand_Safeguard_XSpeed": {"win": 1, "lost": 0}}}, "BB\u30fbAwita": {"win": 1, "lost": 2, "battle_sets": {"Helping Hand_Safeguard_XSpeed": {"win": 1, "lost": 2}}}}, "battle_sets": {"Egg Bomb_Safeguard_XSpeed": {"win": 26, "lost": 8}, "Egg Bomb_Soft-Boiled_XSpeed": {"win": 56, "lost": 10}, "Helping Hand_Safeguard_XSpeed": {"win": 21, "lost": 12}, "Helping Hand_Soft-Boiled_XSpeed": {"win": 1, "lost": 0}, "Egg Bomb_Soft-Boiled_XAttack": {"win": 2, "lost": 0}, "Egg Bomb_Soft-Boiled_EjectButton": {"win": 1, "lost": 0}, "Helping Hand_Safeguard_EjectButton": {"win": 0, "lost": 1}, "Helping Hand_Safeguard_Gear": {"win": 1, "lost": 0}}}, "Machamp": {"win": 108, "lost": 37, "players": {"CeS\u68a6Inf\u00ed": {"win": 2, "lost": 1, "battle_sets": {"Cross Chop_Dynamic Punch_EjectButton": {"win": 2, "lost": 1}}}, "Xante": {"win": 12, "lost": 4, "battle_sets": {"Close Combat_Dynamic Punch_EjectButton": {"win": 6, "lost": 4}, "Cross Chop_Dynamic Punch_EjectButton": {"win": 6, "lost": 0}}}, "KlausVIII": {"win": 2, "lost": 0, "battle_sets": {"Cross Chop_Dynamic Punch_EjectButton": {"win": 2, "lost": 0}}}, "ZelotYT": {"win": 2, "lost": 1, "battle_sets": {"Cross Chop_Dynamic Punch_EjectButton": {"win": 2, "lost": 1}}}, "\u30e2\u30c1\u3082\u3061\u3082\u3061": {"win": 1, "lost": 1, "battle_sets": {"Close Combat_Dynamic Punch_XAttack": {"win": 1, "lost": 1}}}, "TO\u30fbDrako": {"win": 0, "lost": 1, "battle_sets": {"Cross Chop_Dynamic Punch_EjectButton": {"win": 0, "lost": 1}}}, "GZ\u30fbJoe": {"win": 4, "lost": 0, "battle_sets": {"Close Combat_Dynamic Punch_EjectButton": {"win": 4, "lost": 0}}}, "Metallic\u30c4": {"win": 9, "lost": 2, "battle_sets": {"Cross Chop_Dynamic Punch_EjectButton": {"win": 8, "lost": 2}, "Close Combat_Dynamic Punch_EjectButton": {"win": 1, "lost": 0}}}, "ttvSixsies": {"win": 1, "lost": 0, "battle_sets": {"Cross Chop_Dynamic Punch_EjectButton": {"win": 1, "lost": 0}}}, "\u308f\u3089\u3089\u308a\u3063\u304f": {"win": 5, "lost": 2, "battle_sets": {"Close Combat_Dynamic Punch_EjectButton": {"win": 5, "lost": 2}}}, "STMN\u30fbFroy": {"win": 2, "lost": 1, "battle_sets": {"Close Combat_Dynamic Punch_EjectButton": {"win": 2, "lost": 1}}}, "i9\u7231Crow": {"win": 1, "lost": 1, "battle_sets": {"Close Combat_Dynamic Punch_EjectButton": {"win": 0, "lost": 1}, "Cross Chop_Submission_EjectButton": {"win": 1, "lost": 0}}}, "GyZ": {"win": 0, "lost": 1, "battle_sets": {"Cross Chop_Dynamic Punch_EjectButton": {"win": 0, "lost": 1}}}, "jatinjwin": {"win": 0, "lost": 1, "battle_sets": {"Close Combat_Dynamic Punch_EjectButton": {"win": 0, "lost": 1}}}, "UT_Kotori": {"win": 8, "lost": 4, "battle_sets": {"Cross Chop_Dynamic Punch_EjectButton": {"win": 8, "lost": 4}}}, "Kuus\u00ed": {"win": 2, "lost": 1, "battle_sets": {"Cross Chop_Dynamic Punch_EjectButton": {"win": 2, "lost": 0}, "Close Combat_Dynamic Punch_EjectButton": {"win": 0, "lost": 1}}}, "\u685c\u6a39\u96ea\u7a42": {"win": 27, "lost": 8, "battle_sets": {"Cross Chop_Dynamic Punch_XAttack": {"win": 26, "lost": 7}, "Cross Chop_Submission_XAttack": {"win": 0, "lost": 1}, "Close Combat_Dynamic Punch_XAttack": {"win": 1, "lost": 0}}}, "99\u30e0\u4efb\u4e49\u4f1f": {"win": 7, "lost": 4, "battle_sets": {"Cross Chop_Dynamic Punch_XAttack": {"win": 7, "lost": 3}, "Close Combat_Dynamic Punch_XAttack": {"win": 0, "lost": 1}}}, "\u30e1\u30fbM'AMK0": {"win": 1, "lost": 1, "battle_sets": {"Cross Chop_Dynamic Punch_XAttack": {"win": 1, "lost": 1}}}, "Bolbi": {"win": 2, "lost": 0, "battle_sets": {"Cross Chop_Dynamic Punch_EjectButton": {"win": 2, "lost": 0}}}, "DanielMil": {"win": 19, "lost": 3, "battle_sets": {"Cross Chop_Dynamic Punch_EjectButton": {"win": 19, "lost": 3}}}, "\u30d1\u30ca\u30d7\u541b": {"win": 1, "lost": 0, "battle_sets": {"Cross Chop_Dynamic Punch_EjectButton": {"win": 1, "lost": 0}}}}, "battle_sets": {"Cross Chop_Dynamic Punch_EjectButton": {"win": 53, "lost": 13}, "Close Combat_Dynamic Punch_EjectButton": {"win": 18, "lost": 10}, "Close Combat_Dynamic Punch_XAttack": {"win": 2, "lost": 2}, "Cross Chop_Submission_EjectButton": {"win": 1, "lost": 0}, "Cross Chop_Dynamic Punch_XAttack": {"win": 34, "lost": 11}, "Cross Chop_Submission_XAttack": {"win": 0, "lost": 1}}}, "Delphox": {"win": 50, "lost": 17, "players": {"CeS\u68a6Inf\u00ed": {"win": 2, "lost": 0, "battle_sets": {"Mystical Fire_Fire Spin_XSpeed": {"win": 2, "lost": 0}}}, "ENT\u30fbScepTer": {"win": 2, "lost": 0, "battle_sets": {"Mystical Fire_Fire Spin_EjectButton": {"win": 2, "lost": 0}}}, "RNS\u30e4Kamiru": {"win": 2, "lost": 2, "battle_sets": {"Mystical Fire_Fire Spin_EjectButton": {"win": 2, "lost": 2}}}, "GZ\u30fbJoe": {"win": 0, "lost": 1, "battle_sets": {"Mystical Fire_Flame Charge_XSpeed": {"win": 0, "lost": 1}}}, "GyZ": {"win": 1, "lost": 0, "battle_sets": {"Fire Blast_Fire Spin_XSpeed": {"win": 1, "lost": 0}}}, "CeS\u68a6KiD": {"win": 8, "lost": 0, "battle_sets": {"Mystical Fire_Fire Spin_XSpeed": {"win": 8, "lost": 0}}}, "ZapWarudo": {"win": 2, "lost": 0, "battle_sets": {"Fire Blast_Fire Spin_XSpeed": {"win": 2, "lost": 0}}}, "99\u30e0\u4efb\u4e49\u4f1f": {"win": 1, "lost": 0, "battle_sets": {"Mystical Fire_Fire Spin_EjectButton": {"win": 1, "lost": 0}}}, "RJG\u30fb\u6210\u5f1f": {"win": 2, "lost": 0, "battle_sets": {"Mystical Fire_Fire Spin_EjectButton": {"win": 2, "lost": 0}}}, "STMN\u30fbKira": {"win": 1, "lost": 0, "battle_sets": {"Fire Blast_Fire Spin_EjectButton": {"win": 1, "lost": 0}}}, "\u4e5bMyst": {"win": 2, "lost": 0, "battle_sets": {"Mystical Fire_Fire Spin_XSpeed": {"win": 2, "lost": 0}}}, "tvAtlasTauri": {"win": 17, "lost": 7, "battle_sets": {"Mystical Fire_Fire Spin_EjectButton": {"win": 17, "lost": 7}}}, "ryanxoxo": {"win": 3, "lost": 4, "battle_sets": {"Mystical Fire_Fire Spin_EjectButton": {"win": 3, "lost": 4}}}, "MoneyMaxTTV": {"win": 4, "lost": 2, "battle_sets": {"Mystical Fire_Fire Spin_EjectButton": {"win": 3, "lost": 1}, "Mystical Fire_Fire Spin_XSpeed": {"win": 1, "lost": 1}}}, "Trafyyy": {"win": 3, "lost": 1, "battle_sets": {"Mystical Fire_Fire Spin_EjectButton": {"win": 3, "lost": 1}}}}, "battle_sets": {"Mystical Fire_Fire Spin_XSpeed": {"win": 13, "lost": 1}, "Mystical Fire_Fire Spin_EjectButton": {"win": 33, "lost": 15}, "Mystical Fire_Flame Charge_XSpeed": {"win": 0, "lost": 1}, "Fire Blast_Fire Spin_XSpeed": {"win": 3, "lost": 0}, "Fire Blast_Fire Spin_EjectButton": {"win": 1, "lost": 0}}}, "Duraludon": {"win": 42, "lost": 21, "players": {"TE\u30fbFreaK": {"win": 12, "lost": 9, "battle_sets": {"Flash Cannon_Dragon Tail_XAttack": {"win": 12, "lost": 9}}}, "IsWillTV\u30c4": {"win": 19, "lost": 7, "battle_sets": {"Dragon Pulse_Dragon Tail_XAttack": {"win": 19, "lost": 6}, "Flash Cannon_Dragon Tail_XAttack": {"win": 0, "lost": 1}}}, "5i\u30fbKeep": {"win": 1, "lost": 0, "battle_sets": {"Flash Cannon_Dragon Tail_XAttack": {"win": 1, "lost": 0}}}, "GyZ": {"win": 1, "lost": 0, "battle_sets": {"Flash Cannon_Dragon Tail_Purify": {"win": 1, "lost": 0}}}, ":p-Bnj": {"win": 0, "lost": 1, "battle_sets": {"Dragon Pulse_Dragon Tail_XAttack": {"win": 0, "lost": 1}}}, "\u30d1\u30ca\u30d7\u541b": {"win": 9, "lost": 3, "battle_sets": {"Dragon Pulse_Stealth Rock_XAttack": {"win": 9, "lost": 3}}}, "LINH": {"win": 0, "lost": 1, "battle_sets": {"Flash Cannon_Dragon Tail_EjectButton": {"win": 0, "lost": 1}}}}, "battle_sets": {"Flash Cannon_Dragon Tail_XAttack": {"win": 13, "lost": 10}, "Dragon Pulse_Dragon Tail_XAttack": {"win": 19, "lost": 7}, "Flash Cannon_Dragon Tail_Purify": {"win": 1, "lost": 0}, "Dragon Pulse_Stealth Rock_XAttack": {"win": 9, "lost": 3}, "Flash Cannon_Dragon Tail_EjectButton": {"win": 0, "lost": 1}}}, "Azumarill": {"win": 35, "lost": 16, "players": {"TE\u30fbFreaK": {"win": 11, "lost": 4, "battle_sets": {"Water Pulse_Whirlpool_XAttack": {"win": 11, "lost": 4}}}, "Xante": {"win": 1, "lost": 0, "battle_sets": {"Water Pulse_Whirlpool_XSpeed": {"win": 1, "lost": 0}}}, "\ub108\ub3c4\ub0b4\uaebc": {"win": 0, "lost": 1, "battle_sets": {"Water Pulse_Whirlpool_XAttack": {"win": 0, "lost": 1}}}, "dordori": {"win": 14, "lost": 1, "battle_sets": {"Water Pulse_Whirlpool_XAttack": {"win": 14, "lost": 1}}}, "XIS\u30fbMazo": {"win": 0, "lost": 1, "battle_sets": {"Play Rough_Aqua Tail_XSpeed": {"win": 0, "lost": 1}}}, "\ud6c8\ud3ec\ub3c4": {"win": 1, "lost": 2, "battle_sets": {"Water Pulse_Whirlpool_XAttack": {"win": 1, "lost": 2}}}, "GZ\u30fbJoe": {"win": 0, "lost": 2, "battle_sets": {"Water Pulse_Whirlpool_XSpeed": {"win": 0, "lost": 1}, "Water Pulse_Aqua Tail_XSpeed": {"win": 0, "lost": 1}}}, "MW\u30fbAngel\u30b7": {"win": 1, "lost": 0, "battle_sets": {"Water Pulse_Aqua Tail_XSpeed": {"win": 1, "lost": 0}}}, "\uacf5\uae09": {"win": 1, "lost": 0, "battle_sets": {"Water Pulse_Whirlpool_XAttack": {"win": 1, "lost": 0}}}, "GyZ": {"win": 1, "lost": 0, "battle_sets": {"Play Rough_Whirlpool_XSpeed": {"win": 1, "lost": 0}}}, "\u304a\u3044\u304b\u3073\u304d\u3089": {"win": 0, "lost": 1, "battle_sets": {"Water Pulse_Whirlpool_XAttack": {"win": 0, "lost": 1}}}, "99\u30e0\u4efb\u4e49\u4f1f": {"win": 0, "lost": 1, "battle_sets": {"Water Pulse_Whirlpool_XSpeed": {"win": 0, "lost": 1}}}, "N_O_B": {"win": 1, "lost": 1, "battle_sets": {"Water Pulse_Whirlpool_XAttack": {"win": 1, "lost": 1}}}, "Bolbi": {"win": 0, "lost": 1, "battle_sets": {"Play Rough_Aqua Tail_XAttack": {"win": 0, "lost": 1}}}, "RJG\u30fbikura": {"win": 3, "lost": 1, "battle_sets": {"Water Pulse_Whirlpool_XSpeed": {"win": 2, "lost": 1}, "Play Rough_Whirlpool_XSpeed": {"win": 1, "lost": 0}}}, "TnK_KAITO": {"win": 1, "lost": 0, "battle_sets": {"Play Rough_Whirlpool_XAttack": {"win": 1, "lost": 0}}}}, "battle_sets": {"Water Pulse_Whirlpool_XAttack": {"win": 28, "lost": 10}, "Water Pulse_Whirlpool_XSpeed": {"win": 3, "lost": 3}, "Play Rough_Aqua Tail_XSpeed": {"win": 0, "lost": 1}, "Water Pulse_Aqua Tail_XSpeed": {"win": 1, "lost": 1}, "Play Rough_Whirlpool_XSpeed": {"win": 2, "lost": 0}, "Play Rough_Aqua Tail_XAttack": {"win": 0, "lost": 1}, "Play Rough_Whirlpool_XAttack": {"win": 1, "lost": 0}}}, "Sylveon": {"win": 56, "lost": 13, "players": {"TE\u30fbFreaK": {"win": 0, "lost": 1, "battle_sets": {"Hyper Voice_Calm Mind_XSpeed": {"win": 0, "lost": 1}}}, "ENT\u30fbScepTer": {"win": 1, "lost": 0, "battle_sets": {"Hyper Voice_Calm Mind_XSpeed": {"win": 1, "lost": 0}}}, "ZelotYT": {"win": 0, "lost": 1, "battle_sets": {"Hyper Voice_Calm Mind_XSpeed": {"win": 0, "lost": 1}}}, "XIS\u30fbMazo": {"win": 1, "lost": 0, "battle_sets": {"Hyper Voice_Calm Mind_XSpeed": {"win": 1, "lost": 0}}}, "5i\u30fbInferno": {"win": 19, "lost": 2, "battle_sets": {"Hyper Voice_Calm Mind_EjectButton": {"win": 19, "lost": 2}}}, "MMT\u30fbCanniel": {"win": 1, "lost": 0, "battle_sets": {"Hyper Voice_Calm Mind_EjectButton": {"win": 1, "lost": 0}}}, "Aurimakii": {"win": 1, "lost": 0, "battle_sets": {"Hyper Voice_Calm Mind_XSpeed": {"win": 1, "lost": 0}}}, "\u663c\u5bdd\u3072\u307f": {"win": 24, "lost": 6, "battle_sets": {"Hyper Voice_Calm Mind_EjectButton": {"win": 24, "lost": 6}}}, "ZapWarudo": {"win": 9, "lost": 2, "battle_sets": {"Hyper Voice_Calm Mind_XSpeed": {"win": 9, "lost": 2}}}, "Trafyyy": {"win": 0, "lost": 1, "battle_sets": {"Hyper Voice_Calm Mind_XSpeed": {"win": 0, "lost": 1}}}}, "battle_sets": {"Hyper Voice_Calm Mind_XSpeed": {"win": 12, "lost": 5}, "Hyper Voice_Calm Mind_EjectButton": {"win": 44, "lost": 8}}}, "Trevenant": {"win": 23, "lost": 9, "players": {"TE\u30fbFreaK": {"win": 4, "lost": 0, "battle_sets": {"Curse_Horn Leech_Potion": {"win": 4, "lost": 0}}}, "Xante": {"win": 2, "lost": 0, "battle_sets": {"Curse_Horn Leech_XSpeed": {"win": 2, "lost": 0}}}, "TO\u30fbDrako": {"win": 0, "lost": 1, "battle_sets": {"Curse_Horn Leech_Potion": {"win": 0, "lost": 1}}}, "RJG\u30fbRuvis": {"win": 1, "lost": 0, "battle_sets": {"Curse_Horn Leech_Potion": {"win": 1, "lost": 0}}}, "i9\u7231Crow": {"win": 1, "lost": 0, "battle_sets": {"Curse_Horn Leech_XSpeed": {"win": 1, "lost": 0}}}, "GyZ": {"win": 2, "lost": 1, "battle_sets": {"Curse_Horn Leech_XSpeed": {"win": 2, "lost": 1}}}, "\u663c\u5bdd\u3072\u307f": {"win": 1, "lost": 0, "battle_sets": {"Curse_Horn Leech_Potion": {"win": 1, "lost": 0}}}, "jatinjwin": {"win": 9, "lost": 4, "battle_sets": {"Curse_Horn Leech_Potion": {"win": 9, "lost": 4}}}, "Kuus\u00ed": {"win": 1, "lost": 1, "battle_sets": {"Curse_Horn Leech_Potion": {"win": 1, "lost": 1}}}, "MeloskaPokki": {"win": 2, "lost": 2, "battle_sets": {"Curse_Horn Leech_Potion": {"win": 2, "lost": 2}}}}, "battle_sets": {"Curse_Horn Leech_Potion": {"win": 18, "lost": 8}, "Curse_Horn Leech_XSpeed": {"win": 5, "lost": 1}}}, "Slowbro": {"win": 36, "lost": 15, "players": {"Xante": {"win": 1, "lost": 1, "battle_sets": {"Scald_Amnesia_Potion": {"win": 1, "lost": 0}, "Scald_Telekinesis_Potion": {"win": 0, "lost": 1}}}, "KlausVIII": {"win": 1, "lost": 0, "battle_sets": {"Scald_Amnesia_XSpeed": {"win": 1, "lost": 0}}}, "Gh\u00f5st": {"win": 1, "lost": 0, "battle_sets": {"Scald_Amnesia_EjectButton": {"win": 1, "lost": 0}}}, "XIS\u30fbMazo": {"win": 4, "lost": 1, "battle_sets": {"Scald_Telekinesis_XSpeed": {"win": 4, "lost": 1}}}, "\u3042_\u3052": {"win": 1, "lost": 0, "battle_sets": {"Surf_Amnesia_Potion": {"win": 1, "lost": 0}}}, "PotatoUwU": {"win": 4, "lost": 2, "battle_sets": {"Scald_Amnesia_Potion": {"win": 1, "lost": 0}, "Scald_Amnesia_XSpeed": {"win": 3, "lost": 2}}}, "MW\u30fbMax": {"win": 2, "lost": 0, "battle_sets": {"Scald_Telekinesis_EjectButton": {"win": 2, "lost": 0}}}, "TO\u30fbDrako": {"win": 2, "lost": 1, "battle_sets": {"Scald_Amnesia_Potion": {"win": 2, "lost": 1}}}, "GZ\u30fbJoe": {"win": 0, "lost": 1, "battle_sets": {"Scald_Amnesia_Potion": {"win": 0, "lost": 1}}}, "RJG\u30fbRuvis": {"win": 1, "lost": 1, "battle_sets": {"Scald_Telekinesis_EjectButton": {"win": 1, "lost": 1}}}, "ttvSixsies": {"win": 7, "lost": 1, "battle_sets": {"Scald_Telekinesis_XSpeed": {"win": 5, "lost": 0}, "Scald_Telekinesis_Potion": {"win": 1, "lost": 1}, "Scald_Amnesia_XSpeed": {"win": 1, "lost": 0}}}, "Aurimakii": {"win": 1, "lost": 1, "battle_sets": {"Scald_Amnesia_Potion": {"win": 1, "lost": 1}}}, "MW\u30fbJuan\u3048": {"win": 4, "lost": 2, "battle_sets": {"Scald_Amnesia_XSpeed": {"win": 4, "lost": 2}}}, "Bolbi": {"win": 0, "lost": 1, "battle_sets": {"Scald_Telekinesis_Potion": {"win": 0, "lost": 1}}}, "\u4e5bMyst": {"win": 0, "lost": 1, "battle_sets": {"Scald_Amnesia_XSpeed": {"win": 0, "lost": 1}}}, "01Agno": {"win": 2, "lost": 0, "battle_sets": {"Scald_Amnesia_Potion": {"win": 2, "lost": 0}}}, "RJG\u30fbikura": {"win": 1, "lost": 1, "battle_sets": {"Scald_Amnesia_Potion": {"win": 1, "lost": 1}}}, "HMB_runpa": {"win": 2, "lost": 0, "battle_sets": {"Scald_Telekinesis_Potion": {"win": 1, "lost": 0}, "Scald_Amnesia_Potion": {"win": 1, "lost": 0}}}, "tvAtlasTauri": {"win": 1, "lost": 0, "battle_sets": {"Scald_Amnesia_Potion": {"win": 1, "lost": 0}}}, "TnK_KAITO": {"win": 1, "lost": 0, "battle_sets": {"Scald_Amnesia_Potion": {"win": 1, "lost": 0}}}, "Trafyyy": {"win": 0, "lost": 1, "battle_sets": {"Scald_Amnesia_Potion": {"win": 0, "lost": 1}}}}, "battle_sets": {"Scald_Amnesia_Potion": {"win": 11, "lost": 5}, "Scald_Telekinesis_Potion": {"win": 2, "lost": 3}, "Scald_Amnesia_XSpeed": {"win": 9, "lost": 5}, "Scald_Amnesia_EjectButton": {"win": 1, "lost": 0}, "Scald_Telekinesis_XSpeed": {"win": 9, "lost": 1}, "Surf_Amnesia_Potion": {"win": 1, "lost": 0}, "Scald_Telekinesis_EjectButton": {"win": 3, "lost": 1}}}, "Dragonite": {"win": 186, "lost": 62, "players": {"Xante": {"win": 1, "lost": 1, "battle_sets": {"Dragon Dance_Hyper Beam_Purify": {"win": 1, "lost": 1}}}, "KlausVIII": {"win": 9, "lost": 5, "battle_sets": {"Dragon Dance_Hyper Beam_XAttack": {"win": 9, "lost": 5}}}, "ENT\u30fbScepTer": {"win": 6, "lost": 0, "battle_sets": {"Dragon Dance_Hyper Beam_Purify": {"win": 6, "lost": 0}}}, "\ub108\ub3c4\ub0b4\uaebc": {"win": 0, "lost": 1, "battle_sets": {"Dragon Dance_Hyper Beam_EjectButton": {"win": 0, "lost": 1}}}, "5i\u30fbKeep": {"win": 32, "lost": 5, "battle_sets": {"Dragon Dance_Hyper Beam_XAttack": {"win": 32, "lost": 5}}}, "\ud6c8\ud3ec\ub3c4": {"win": 0, "lost": 1, "battle_sets": {"Dragon Dance_Hyper Beam_Purify": {"win": 0, "lost": 1}}}, "TO\u30fbDrako": {"win": 15, "lost": 7, "battle_sets": {"Dragon Dance_Hyper Beam_Purify": {"win": 14, "lost": 6}, "Extreme Speed_Outrage_Purify": {"win": 0, "lost": 1}, "Dragon Dance_Outrage_Purify": {"win": 1, "lost": 0}}}, "GZ\u30fbJoe": {"win": 1, "lost": 0, "battle_sets": {"Extreme Speed_Outrage_XSpeed": {"win": 1, "lost": 0}}}, "HMB_WKAIRYUW": {"win": 30, "lost": 14, "battle_sets": {"Dragon Dance_Hyper Beam_Purify": {"win": 29, "lost": 14}, "Dragon Dance_Hyper Beam_EjectButton": {"win": 1, "lost": 0}}}, "TE\u30fbTibi": {"win": 7, "lost": 1, "battle_sets": {"Dragon Dance_Hyper Beam_Purify": {"win": 7, "lost": 1}}}, "ttvSixsies": {"win": 4, "lost": 0, "battle_sets": {"Dragon Dance_Hyper Beam_XAttack": {"win": 4, "lost": 0}}}, "STMN\u30fbFroy": {"win": 1, "lost": 0, "battle_sets": {"Dragon Dance_Hyper Beam_XAttack": {"win": 1, "lost": 0}}}, "CSC\u30fbf3rZera": {"win": 9, "lost": 2, "battle_sets": {"Dragon Dance_Hyper Beam_Purify": {"win": 9, "lost": 2}}}, "Suix\u3164": {"win": 28, "lost": 1, "battle_sets": {"Dragon Dance_Hyper Beam_EjectButton": {"win": 28, "lost": 1}}}, "\u82a5\u5ddd\u3042\u304d": {"win": 0, "lost": 1, "battle_sets": {"Dragon Dance_Hyper Beam_EjectButton": {"win": 0, "lost": 1}}}, "Kuus\u00ed": {"win": 1, "lost": 0, "battle_sets": {"Dragon Dance_Hyper Beam_Purify": {"win": 1, "lost": 0}}}, "Bolbi": {"win": 11, "lost": 5, "battle_sets": {"Dragon Dance_Hyper Beam_Purify": {"win": 11, "lost": 5}}}, "KK_4E": {"win": 19, "lost": 8, "battle_sets": {"Dragon Dance_Hyper Beam_Purify": {"win": 19, "lost": 8}}}, "\u9811\u5f35\u308d\u3046ww": {"win": 4, "lost": 1, "battle_sets": {"Dragon Dance_Hyper Beam_EjectButton": {"win": 4, "lost": 1}}}, "\u00c6\u00b7666": {"win": 3, "lost": 4, "battle_sets": {"Dragon Dance_Hyper Beam_Purify": {"win": 3, "lost": 4}}}, "\u30d1\u30ca\u30d7\u541b": {"win": 0, "lost": 1, "battle_sets": {"Dragon Dance_Hyper Beam_Purify": {"win": 0, "lost": 1}}}, "Trafyyy": {"win": 5, "lost": 4, "battle_sets": {"Dragon Dance_Hyper Beam_Purify": {"win": 3, "lost": 2}, "Dragon Dance_Outrage_Purify": {"win": 1, "lost": 2}, "Dragon Dance_Outrage_XAttack": {"win": 1, "lost": 0}}}}, "battle_sets": {"Dragon Dance_Hyper Beam_Purify": {"win": 103, "lost": 45}, "Dragon Dance_Hyper Beam_XAttack": {"win": 46, "lost": 10}, "Dragon Dance_Hyper Beam_EjectButton": {"win": 33, "lost": 4}, "Extreme Speed_Outrage_Purify": {"win": 0, "lost": 1}, "Dragon Dance_Outrage_Purify": {"win": 2, "lost": 2}, "Extreme Speed_Outrage_XSpeed": {"win": 1, "lost": 0}, "Dragon Dance_Outrage_XAttack": {"win": 1, "lost": 0}}}, "Lucario": {"win": 397, "lost": 151, "players": {"Xante": {"win": 3, "lost": 0, "battle_sets": {"Power-Up Punch_Bone Rush_XSpeed": {"win": 1, "lost": 0}, "Power-Up Punch_Close Combat_XAttack": {"win": 2, "lost": 0}}}, "KlausVIII": {"win": 11, "lost": 1, "battle_sets": {"Power-Up Punch_Close Combat_XSpeed": {"win": 6, "lost": 0}, "Extreme Speed_Bone Rush_XSpeed": {"win": 5, "lost": 1}}}, "\ub108\ub3c4\ub0b4\uaebc": {"win": 35, "lost": 12, "battle_sets": {"Extreme Speed_Bone Rush_Purify": {"win": 35, "lost": 12}}}, "ZelotYT": {"win": 30, "lost": 16, "battle_sets": {"Extreme Speed_Bone Rush_XSpeed": {"win": 30, "lost": 16}}}, "Gh\u00f5st": {"win": 0, "lost": 1, "battle_sets": {"Extreme Speed_Bone Rush_Purify": {"win": 0, "lost": 1}}}, "dordori": {"win": 8, "lost": 4, "battle_sets": {"Extreme Speed_Bone Rush_Purify": {"win": 8, "lost": 4}}}, "\u3042_\u3052": {"win": 7, "lost": 6, "battle_sets": {"Extreme Speed_Bone Rush_Purify": {"win": 7, "lost": 6}}}, "PotatoUwU": {"win": 1, "lost": 2, "battle_sets": {"Extreme Speed_Bone Rush_Purify": {"win": 1, "lost": 2}}}, "NoL_Reirei": {"win": 27, "lost": 11, "battle_sets": {"Extreme Speed_Bone Rush_Purify": {"win": 26, "lost": 9}, "Power-Up Punch_Close Combat_EjectButton": {"win": 0, "lost": 1}, "Power-Up Punch_Close Combat_Purify": {"win": 1, "lost": 1}}}, "\ud6c8\ud3ec\ub3c4": {"win": 7, "lost": 1, "battle_sets": {"Extreme Speed_Bone Rush_Purify": {"win": 6, "lost": 1}, "Extreme Speed_Close Combat_Purify": {"win": 1, "lost": 0}}}, "AFR\u30fbMiva": {"win": 17, "lost": 9, "battle_sets": {"Power-Up Punch_Close Combat_EjectButton": {"win": 17, "lost": 9}}}, "MW\u30fbMax": {"win": 8, "lost": 1, "battle_sets": {"Extreme Speed_Bone Rush_Purify": {"win": 8, "lost": 1}}}, "TO\u30fbDrako": {"win": 8, "lost": 4, "battle_sets": {"Extreme Speed_Bone Rush_XSpeed": {"win": 8, "lost": 4}}}, "AX\u30fbKyluKzz": {"win": 12, "lost": 5, "battle_sets": {"Extreme Speed_Bone Rush_Purify": {"win": 11, "lost": 5}, "Extreme Speed_Bone Rush_XSpeed": {"win": 1, "lost": 0}}}, "RJG\u30fbRuvis": {"win": 1, "lost": 0, "battle_sets": {"Extreme Speed_Bone Rush_XSpeed": {"win": 1, "lost": 0}}}, "MW\u30fbAngel\u30b7": {"win": 7, "lost": 0, "battle_sets": {"Extreme Speed_Bone Rush_Purify": {"win": 7, "lost": 0}}}, "TE\u30fbTibi": {"win": 13, "lost": 5, "battle_sets": {"Power-Up Punch_Close Combat_XAttack": {"win": 11, "lost": 4}, "Extreme Speed_Bone Rush_XAttack": {"win": 1, "lost": 1}, "Extreme Speed_Close Combat_XAttack": {"win": 1, "lost": 0}}}, "ttvSixsies": {"win": 1, "lost": 1, "battle_sets": {"Power-Up Punch_Close Combat_XAttack": {"win": 1, "lost": 1}}}, "Aurimakii": {"win": 21, "lost": 11, "battle_sets": {"Extreme Speed_Bone Rush_XSpeed": {"win": 17, "lost": 5}, "Power-Up Punch_Close Combat_XSpeed": {"win": 2, "lost": 5}, "Extreme Speed_Close Combat_XSpeed": {"win": 2, "lost": 1}}}, "STMN\u30fbFroy": {"win": 5, "lost": 1, "battle_sets": {"Power-Up Punch_Close Combat_XAttack": {"win": 1, "lost": 1}, "Extreme Speed_Bone Rush_XAttack": {"win": 4, "lost": 0}}}, "i9\u7231Crow": {"win": 17, "lost": 3, "battle_sets": {"Extreme Speed_Bone Rush_XSpeed": {"win": 16, "lost": 3}, "Extreme Speed_Close Combat_XSpeed": {"win": 1, "lost": 0}}}, "Espoir\u0421\u0432\u0451\u0442": {"win": 29, "lost": 12, "battle_sets": {"Extreme Speed_Bone Rush_Purify": {"win": 29, "lost": 12}}}, ":p-Bnj": {"win": 12, "lost": 2, "battle_sets": {"Extreme Speed_Bone Rush_XSpeed": {"win": 8, "lost": 0}, "Extreme Speed_Close Combat_XSpeed": {"win": 4, "lost": 2}}}, "\u304a\u3044\u304b\u3073\u304d\u3089": {"win": 2, "lost": 0, "battle_sets": {"Extreme Speed_Bone Rush_Purify": {"win": 1, "lost": 0}, "Extreme Speed_Close Combat_Purify": {"win": 1, "lost": 0}}}, "ZapWarudo": {"win": 3, "lost": 0, "battle_sets": {"Power-Up Punch_Close Combat_XAttack": {"win": 1, "lost": 0}, "Power-Up Punch_Bone Rush_XAttack": {"win": 1, "lost": 0}, "Power-Up Punch_Close Combat_XSpeed": {"win": 1, "lost": 0}}}, "\u82a5\u5ddd\u3042\u304d": {"win": 21, "lost": 1, "battle_sets": {"Extreme Speed_Bone Rush_Purify": {"win": 21, "lost": 1}}}, "UT_Kotori": {"win": 1, "lost": 1, "battle_sets": {"Extreme Speed_Bone Rush_Purify": {"win": 1, "lost": 1}}}, "OGwastaken": {"win": 12, "lost": 7, "battle_sets": {"Extreme Speed_Bone Rush_XSpeed": {"win": 11, "lost": 6}, "Extreme Speed_Close Combat_XSpeed": {"win": 1, "lost": 1}}}, "Kuus\u00ed": {"win": 17, "lost": 4, "battle_sets": {"Extreme Speed_Bone Rush_Purify": {"win": 13, "lost": 4}, "Power-Up Punch_Close Combat_XAttack": {"win": 3, "lost": 0}, "Power-Up Punch_Close Combat_XSpeed": {"win": 1, "lost": 0}}}, "Parasite": {"win": 1, "lost": 3, "battle_sets": {"Extreme Speed_Bone Rush_Purify": {"win": 1, "lost": 3}}}, "Bolbi": {"win": 3, "lost": 0, "battle_sets": {"Power-Up Punch_Close Combat_XSpeed": {"win": 2, "lost": 0}, "Extreme Speed_Bone Rush_XSpeed": {"win": 1, "lost": 0}}}, "LeCodingTTV": {"win": 15, "lost": 5, "battle_sets": {"Extreme Speed_Bone Rush_XSpeed": {"win": 15, "lost": 5}}}, "\u9811\u5f35\u308d\u3046ww": {"win": 3, "lost": 5, "battle_sets": {"Extreme Speed_Bone Rush_Purify": {"win": 1, "lost": 4}, "Power-Up Punch_Close Combat_Potion": {"win": 1, "lost": 0}, "Power-Up Punch_Bone Rush_Purify": {"win": 1, "lost": 1}}}, "\u4e5bMyst": {"win": 2, "lost": 0, "battle_sets": {"Power-Up Punch_Close Combat_XAttack": {"win": 2, "lost": 0}}}, "\u4ffa\u306e\u30eb\u30ab\u30ea\u30aa": {"win": 7, "lost": 2, "battle_sets": {"Extreme Speed_Bone Rush_Purify": {"win": 7, "lost": 2}}}, "RJG\u30fbikura": {"win": 2, "lost": 1, "battle_sets": {"Extreme Speed_Bone Rush_Purify": {"win": 2, "lost": 1}}}, "HMB_runpa": {"win": 11, "lost": 6, "battle_sets": {"Extreme Speed_Bone Rush_Purify": {"win": 10, "lost": 6}, "Power-Up Punch_Close Combat_Potion": {"win": 1, "lost": 0}}}, "\u5bc4\u751f\u5263\u5080\u5121\u5efb": {"win": 7, "lost": 4, "battle_sets": {"Extreme Speed_Bone Rush_Purify": {"win": 7, "lost": 3}, "Power-Up Punch_Close Combat_Purify": {"win": 0, "lost": 1}}}, "TV\u30fbManoTv": {"win": 10, "lost": 4, "battle_sets": {"Extreme Speed_Bone Rush_Purify": {"win": 8, "lost": 4}, "Power-Up Punch_Bone Rush_XAttack": {"win": 2, "lost": 0}}}}, "battle_sets": {"Power-Up Punch_Bone Rush_XSpeed": {"win": 1, "lost": 0}, "Power-Up Punch_Close Combat_XAttack": {"win": 21, "lost": 6}, "Power-Up Punch_Close Combat_XSpeed": {"win": 12, "lost": 5}, "Extreme Speed_Bone Rush_XSpeed": {"win": 113, "lost": 40}, "Extreme Speed_Bone Rush_Purify": {"win": 210, "lost": 82}, "Power-Up Punch_Close Combat_EjectButton": {"win": 17, "lost": 10}, "Power-Up Punch_Close Combat_Purify": {"win": 1, "lost": 2}, "Extreme Speed_Close Combat_Purify": {"win": 2, "lost": 0}, "Extreme Speed_Bone Rush_XAttack": {"win": 5, "lost": 1}, "Extreme Speed_Close Combat_XAttack": {"win": 1, "lost": 0}, "Extreme Speed_Close Combat_XSpeed": {"win": 8, "lost": 4}, "Power-Up Punch_Bone Rush_XAttack": {"win": 3, "lost": 0}, "Power-Up Punch_Close Combat_Potion": {"win": 2, "lost": 0}, "Power-Up Punch_Bone Rush_Purify": {"win": 1, "lost": 1}}}, "Blastoise": {"win": 44, "lost": 35, "players": {"Xante": {"win": 1, "lost": 1, "battle_sets": {"Water Spout_Rapid Spin_EjectButton": {"win": 1, "lost": 1}}}, "\u3042_\u3052": {"win": 1, "lost": 0, "battle_sets": {"Hydro Pump_Rapid Spin_EjectButton": {"win": 1, "lost": 0}}}, "PotatoUwU": {"win": 2, "lost": 1, "battle_sets": {"Water Spout_Rapid Spin_EjectButton": {"win": 2, "lost": 1}}}, "\ud6c8\ud3ec\ub3c4": {"win": 13, "lost": 4, "battle_sets": {"Water Spout_Rapid Spin_EjectButton": {"win": 13, "lost": 4}}}, "GZ\u30fbJoe": {"win": 0, "lost": 1, "battle_sets": {"Hydro Pump_Surf_EjectButton": {"win": 0, "lost": 1}}}, "FlyGuyShyGuy": {"win": 21, "lost": 19, "battle_sets": {"Water Spout_Rapid Spin_EjectButton": {"win": 19, "lost": 18}, "Hydro Pump_Rapid Spin_EjectButton": {"win": 2, "lost": 1}}}, "\u304a\u3044\u304b\u3073\u304d\u3089": {"win": 1, "lost": 0, "battle_sets": {"Water Spout_Rapid Spin_EjectButton": {"win": 1, "lost": 0}}}, "ZapWarudo": {"win": 0, "lost": 1, "battle_sets": {"Water Spout_Rapid Spin_EjectButton": {"win": 0, "lost": 1}}}, "UT_Kotori": {"win": 0, "lost": 1, "battle_sets": {"Hydro Pump_Surf_EjectButton": {"win": 0, "lost": 1}}}, "Kuus\u00ed": {"win": 0, "lost": 1, "battle_sets": {"Water Spout_Rapid Spin_EjectButton": {"win": 0, "lost": 1}}}, "\u9811\u5f35\u308d\u3046ww": {"win": 2, "lost": 4, "battle_sets": {"Water Spout_Rapid Spin_EjectButton": {"win": 2, "lost": 3}, "Hydro Pump_Surf_EjectButton": {"win": 0, "lost": 1}}}, "\u4e5bMyst": {"win": 1, "lost": 0, "battle_sets": {"Water Spout_Rapid Spin_EjectButton": {"win": 1, "lost": 0}}}, "\u30d1\u30ca\u30d7\u541b": {"win": 1, "lost": 0, "battle_sets": {"Water Spout_Rapid Spin_XSpeed": {"win": 1, "lost": 0}}}, "\u5bc4\u751f\u5263\u5080\u5121\u5efb": {"win": 1, "lost": 2, "battle_sets": {"Water Spout_Rapid Spin_EjectButton": {"win": 1, "lost": 2}}}}, "battle_sets": {"Water Spout_Rapid Spin_EjectButton": {"win": 40, "lost": 31}, "Hydro Pump_Rapid Spin_EjectButton": {"win": 3, "lost": 1}, "Hydro Pump_Surf_EjectButton": {"win": 0, "lost": 3}, "Water Spout_Rapid Spin_XSpeed": {"win": 1, "lost": 0}}}, "Tsareena": {"win": 113, "lost": 56, "players": {"Xante": {"win": 1, "lost": 0, "battle_sets": {"Stomp_Trop Kick_XSpeed": {"win": 1, "lost": 0}}}, "dordori": {"win": 6, "lost": 0, "battle_sets": {"Stomp_Trop Kick_XAttack": {"win": 6, "lost": 0}}}, "\u3042_\u3052": {"win": 0, "lost": 1, "battle_sets": {"Stomp_Trop Kick_XSpeed": {"win": 0, "lost": 1}}}, "MW\u30fbMax": {"win": 3, "lost": 1, "battle_sets": {"Stomp_Trop Kick_Purify": {"win": 3, "lost": 1}}}, "GZ\u30fbJoe": {"win": 0, "lost": 2, "battle_sets": {"Stomp_Trop Kick_Purify": {"win": 0, "lost": 2}}}, "MW\u30fbAngel\u30b7": {"win": 3, "lost": 1, "battle_sets": {"Stomp_Grassy Glide_Tail": {"win": 2, "lost": 0}, "Stomp_Grassy Glide_XAttack": {"win": 0, "lost": 1}, "Stomp_Grassy Glide_XSpeed": {"win": 1, "lost": 0}}}, "5i\u30fbInferno": {"win": 2, "lost": 1, "battle_sets": {"Stomp_Grassy Glide_Purify": {"win": 2, "lost": 1}}}, "STMN\u30fbFroy": {"win": 1, "lost": 0, "battle_sets": {"Stomp_Trop Kick_XSpeed": {"win": 1, "lost": 0}}}, "i9\u7231Crow": {"win": 1, "lost": 0, "battle_sets": {"Stomp_Trop Kick_XSpeed": {"win": 1, "lost": 0}}}, "\u304a\u3044\u304b\u3073\u304d\u3089": {"win": 11, "lost": 8, "battle_sets": {"Stomp_Trop Kick_Purify": {"win": 8, "lost": 7}, "Stomp_Grassy Glide_Purify": {"win": 0, "lost": 1}, "Triple Axel_Trop Kick_Purify": {"win": 3, "lost": 0}}}, "RNS\u30e3pyi": {"win": 27, "lost": 1, "battle_sets": {"Stomp_Trop Kick_XAttack": {"win": 26, "lost": 1}, "Stomp_Trop Kick_XSpeed": {"win": 1, "lost": 0}}}, "\u82a5\u5ddd\u3042\u304d": {"win": 2, "lost": 0, "battle_sets": {"Stomp_Trop Kick_XAttack": {"win": 2, "lost": 0}}}, "99\u30e0\u4efb\u4e49\u4f1f": {"win": 1, "lost": 5, "battle_sets": {"Stomp_Trop Kick_Purify": {"win": 1, "lost": 5}}}, "RJG\u30fb\u6210\u5f1f": {"win": 8, "lost": 0, "battle_sets": {"Stomp_Trop Kick_Purify": {"win": 8, "lost": 0}}}, "LeCodingTTV": {"win": 1, "lost": 2, "battle_sets": {"Stomp_Grassy Glide_XSpeed": {"win": 1, "lost": 2}}}, "\u9811\u5f35\u308d\u3046ww": {"win": 1, "lost": 0, "battle_sets": {"Stomp_Trop Kick_XSpeed": {"win": 1, "lost": 0}}}, "\u4e5bMyst": {"win": 0, "lost": 1, "battle_sets": {"Stomp_Trop Kick_XSpeed": {"win": 0, "lost": 1}}}, "RJG\u30fbikura": {"win": 5, "lost": 2, "battle_sets": {"Stomp_Trop Kick_XSpeed": {"win": 5, "lost": 2}}}, "HMB_runpa": {"win": 5, "lost": 3, "battle_sets": {"Stomp_Grassy Glide_XSpeed": {"win": 3, "lost": 2}, "Stomp_Grassy Glide_Purify": {"win": 1, "lost": 1}, "Stomp_Grassy Glide_XAttack": {"win": 1, "lost": 0}}}, "\u30d1\u30ca\u30d7\u541b": {"win": 9, "lost": 8, "battle_sets": {"Stomp_Trop Kick_XSpeed": {"win": 0, "lost": 2}, "Stomp_Trop Kick_XAttack": {"win": 9, "lost": 5}, "Triple Axel_Grassy Glide_XAttack": {"win": 0, "lost": 1}}}, "TnK_KAITO": {"win": 1, "lost": 2, "battle_sets": {"Stomp_Grassy Glide_XAttack": {"win": 1, "lost": 2}}}, "\u5bc4\u751f\u5263\u5080\u5121\u5efb": {"win": 0, "lost": 1, "battle_sets": {"Stomp_Trop Kick_Potion": {"win": 0, "lost": 1}}}, "Trafyyy": {"win": 0, "lost": 1, "battle_sets": {"Stomp_Trop Kick_Purify": {"win": 0, "lost": 1}}}, "MeloskaPokki": {"win": 25, "lost": 16, "battle_sets": {"Stomp_Grassy Glide_Potion": {"win": 25, "lost": 15}, "Triple Axel_Grassy Glide_Potion": {"win": 0, "lost": 1}}}}, "battle_sets": {"Stomp_Trop Kick_XSpeed": {"win": 10, "lost": 6}, "Stomp_Trop Kick_XAttack": {"win": 43, "lost": 6}, "Stomp_Trop Kick_Purify": {"win": 20, "lost": 16}, "Stomp_Grassy Glide_Tail": {"win": 2, "lost": 0}, "Stomp_Grassy Glide_XAttack": {"win": 2, "lost": 3}, "Stomp_Grassy Glide_XSpeed": {"win": 5, "lost": 4}, "Stomp_Grassy Glide_Purify": {"win": 3, "lost": 3}, "Triple Axel_Trop Kick_Purify": {"win": 3, "lost": 0}, "Triple Axel_Grassy Glide_XAttack": {"win": 0, "lost": 1}, "Stomp_Trop Kick_Potion": {"win": 0, "lost": 1}, "Stomp_Grassy Glide_Potion": {"win": 25, "lost": 15}, "Triple Axel_Grassy Glide_Potion": {"win": 0, "lost": 1}}}, "Glaceon": {"win": 109, "lost": 48, "players": {"Xante": {"win": 1, "lost": 0, "battle_sets": {"Icicle Spear_Ice Shard_EjectButton": {"win": 1, "lost": 0}}}, "XIS\u30fbMazo": {"win": 6, "lost": 1, "battle_sets": {"Icicle Spear_Ice Shard_XSpeed": {"win": 6, "lost": 1}}}, "RJG\u30fbRuvis": {"win": 10, "lost": 3, "battle_sets": {"Icicle Spear_Ice Shard_XSpeed": {"win": 10, "lost": 3}}}, "5i\u30fbInferno": {"win": 5, "lost": 2, "battle_sets": {"Icicle Spear_Ice Shard_EjectButton": {"win": 5, "lost": 2}}}, "Metallic\u30c4": {"win": 20, "lost": 14, "battle_sets": {"Icicle Spear_Ice Shard_XSpeed": {"win": 20, "lost": 14}}}, "\u308f\u3089\u3089\u308a\u3063\u304f": {"win": 3, "lost": 2, "battle_sets": {"Icicle Spear_Ice Shard_XSpeed": {"win": 2, "lost": 1}, "Icicle Spear_Freeze-Dry_XSpeed": {"win": 1, "lost": 1}}}, "GyZ": {"win": 2, "lost": 0, "battle_sets": {"Icy Wind_Ice Shard_XSpeed": {"win": 1, "lost": 0}, "Icicle Spear_Ice Shard_XSpeed": {"win": 1, "lost": 0}}}, "\u663c\u5bdd\u3072\u307f": {"win": 15, "lost": 4, "battle_sets": {"Icicle Spear_Ice Shard_EjectButton": {"win": 15, "lost": 4}}}, ":p-Bnj": {"win": 7, "lost": 2, "battle_sets": {"Icicle Spear_Ice Shard_XSpeed": {"win": 7, "lost": 2}}}, "99\u30e0\u4efb\u4e49\u4f1f": {"win": 9, "lost": 9, "battle_sets": {"Icicle Spear_Ice Shard_XSpeed": {"win": 4, "lost": 5}, "Icicle Spear_Freeze-Dry_XSpeed": {"win": 5, "lost": 4}}}, "STMN\u30fbKira": {"win": 14, "lost": 4, "battle_sets": {"Icicle Spear_Ice Shard_EjectButton": {"win": 14, "lost": 4}}}, "tvAtlasTauri": {"win": 8, "lost": 3, "battle_sets": {"Icicle Spear_Ice Shard_EjectButton": {"win": 5, "lost": 1}, "Icicle Spear_Ice Shard_XSpeed": {"win": 3, "lost": 2}}}, "\u00c6\u00b7666": {"win": 7, "lost": 4, "battle_sets": {"Icy Wind_Freeze-Dry_XSpeed": {"win": 1, "lost": 1}, "Icicle Spear_Ice Shard_XSpeed": {"win": 6, "lost": 1}, "Icicle Spear_Freeze-Dry_XSpeed": {"win": 0, "lost": 1}, "Icy Wind_Ice Shard_XSpeed": {"win": 0, "lost": 1}}}, "Savior": {"win": 2, "lost": 0, "battle_sets": {"Icicle Spear_Ice Shard_XSpeed": {"win": 2, "lost": 0}}}}, "battle_sets": {"Icicle Spear_Ice Shard_EjectButton": {"win": 40, "lost": 11}, "Icicle Spear_Ice Shard_XSpeed": {"win": 61, "lost": 29}, "Icicle Spear_Freeze-Dry_XSpeed": {"win": 6, "lost": 6}, "Icy Wind_Ice Shard_XSpeed": {"win": 1, "lost": 1}, "Icy Wind_Freeze-Dry_XSpeed": {"win": 1, "lost": 1}}}, "Greedent": {"win": 14, "lost": 7, "players": {"Xante": {"win": 1, "lost": 1, "battle_sets": {"Belch_Covet_Tail": {"win": 1, "lost": 1}}}, "RJG\u30fbRuvis": {"win": 1, "lost": 0, "battle_sets": {"Belch_Covet_Tail": {"win": 1, "lost": 0}}}, "TE\u30fbTibi": {"win": 8, "lost": 2, "battle_sets": {"Belch_Covet_Tail": {"win": 8, "lost": 2}}}, "STMN\u30fbFroy": {"win": 1, "lost": 0, "battle_sets": {"Belch_Covet_Tail": {"win": 1, "lost": 0}}}, "ZapWarudo": {"win": 1, "lost": 2, "battle_sets": {"Belch_Covet_Potion": {"win": 1, "lost": 2}}}, "\u9811\u5f35\u308d\u3046ww": {"win": 2, "lost": 2, "battle_sets": {"Belch_Covet_Tail": {"win": 2, "lost": 2}}}}, "battle_sets": {"Belch_Covet_Tail": {"win": 13, "lost": 5}, "Belch_Covet_Potion": {"win": 1, "lost": 2}}}, "Venusaur": {"win": 8, "lost": 6, "players": {"Xante": {"win": 1, "lost": 0, "battle_sets": {"Giga Drain_Petal Dance_Purify": {"win": 1, "lost": 0}}}, "GZ\u30fbJoe": {"win": 1, "lost": 0, "battle_sets": {"Giga Drain_Petal Dance_Purify": {"win": 1, "lost": 0}}}, "ZapWarudo": {"win": 1, "lost": 0, "battle_sets": {"Sludge Bomb_Solar Beam_XSpeed": {"win": 1, "lost": 0}}}, "UT_Kotori": {"win": 1, "lost": 0, "battle_sets": {"Giga Drain_Solar Beam_Purify": {"win": 1, "lost": 0}}}, "Kuus\u00ed": {"win": 1, "lost": 1, "battle_sets": {"Giga Drain_Solar Beam_EjectButton": {"win": 1, "lost": 1}}}, "\u6687\u306a\u6771\u5927\u751f": {"win": 3, "lost": 3, "battle_sets": {"Giga Drain_Solar Beam_Purify": {"win": 1, "lost": 1}, "Giga Drain_Solar Beam_EjectButton": {"win": 0, "lost": 1}, "Sludge Bomb_Solar Beam_EjectButton": {"win": 0, "lost": 1}, "Giga Drain_Petal Dance_Purify": {"win": 2, "lost": 0}}}, "RJG\u30fbikura": {"win": 0, "lost": 1, "battle_sets": {"Giga Drain_Solar Beam_Purify": {"win": 0, "lost": 1}}}, "\u00c6\u00b7666": {"win": 0, "lost": 1, "battle_sets": {"Giga Drain_Petal Dance_Purify": {"win": 0, "lost": 1}}}}, "battle_sets": {"Giga Drain_Petal Dance_Purify": {"win": 4, "lost": 1}, "Sludge Bomb_Solar Beam_XSpeed": {"win": 1, "lost": 0}, "Giga Drain_Solar Beam_Purify": {"win": 2, "lost": 2}, "Giga Drain_Solar Beam_EjectButton": {"win": 1, "lost": 2}, "Sludge Bomb_Solar Beam_EjectButton": {"win": 0, "lost": 1}}}, "Cinderace": {"win": 103, "lost": 40, "players": {"KlausVIII": {"win": 2, "lost": 0, "battle_sets": {"Blaze Kick_Flame Charge_EjectButton": {"win": 2, "lost": 0}}}, "ENT\u30fbScepTer": {"win": 1, "lost": 0, "battle_sets": {"Blaze Kick_Flame Charge_Purify": {"win": 1, "lost": 0}}}, "IsWillTV\u30c4": {"win": 3, "lost": 0, "battle_sets": {"Blaze Kick_Flame Charge_EjectButton": {"win": 3, "lost": 0}}}, "XIS\u30fbMazo": {"win": 1, "lost": 0, "battle_sets": {"Blaze Kick_Flame Charge_Tail": {"win": 1, "lost": 0}}}, "\u3042_\u3052": {"win": 0, "lost": 2, "battle_sets": {"Blaze Kick_Flame Charge_XAttack": {"win": 0, "lost": 2}}}, "MW\u30fbMax": {"win": 1, "lost": 0, "battle_sets": {"Blaze Kick_Flame Charge_Purify": {"win": 1, "lost": 0}}}, "AX\u30fbKyluKzz": {"win": 2, "lost": 0, "battle_sets": {"Blaze Kick_Flame Charge_EjectButton": {"win": 1, "lost": 0}, "Blaze Kick_Flame Charge_Purify": {"win": 1, "lost": 0}}}, "MW\u30fbAngel\u30b7": {"win": 5, "lost": 1, "battle_sets": {"Blaze Kick_Flame Charge_Purify": {"win": 5, "lost": 1}}}, "STMN\u30fbFroy": {"win": 2, "lost": 0, "battle_sets": {"Blaze Kick_Flame Charge_EjectButton": {"win": 2, "lost": 0}}}, "CSC\u30fbf3rZera": {"win": 0, "lost": 1, "battle_sets": {"Blaze Kick_Flame Charge_Purify": {"win": 0, "lost": 1}}}, "\u30e1\u30fbM'AMK0": {"win": 17, "lost": 8, "battle_sets": {"Blaze Kick_Flame Charge_EjectButton": {"win": 17, "lost": 8}}}, "\u6687\u306a\u6771\u5927\u751f": {"win": 14, "lost": 7, "battle_sets": {"Pyro Ball_Flame Charge_XAttack": {"win": 14, "lost": 5}, "Blaze Kick_Flame Charge_EjectButton": {"win": 0, "lost": 2}}}, "Bolbi": {"win": 3, "lost": 0, "battle_sets": {"Blaze Kick_Flame Charge_EjectButton": {"win": 3, "lost": 0}}}, "20FF": {"win": 6, "lost": 3, "battle_sets": {"Blaze Kick_Flame Charge_XAttack": {"win": 6, "lost": 3}}}, "\u00c6\u00b7666": {"win": 2, "lost": 1, "battle_sets": {"Blaze Kick_Flame Charge_EjectButton": {"win": 2, "lost": 1}}}, "\u30d1\u30ca\u30d7\u541b": {"win": 2, "lost": 0, "battle_sets": {"Blaze Kick_Feint_EjectButton": {"win": 2, "lost": 0}}}, "TnK_KAITO": {"win": 12, "lost": 3, "battle_sets": {"Blaze Kick_Flame Charge_XAttack": {"win": 12, "lost": 3}}}, "\u5bc4\u751f\u5263\u5080\u5121\u5efb": {"win": 2, "lost": 1, "battle_sets": {"Blaze Kick_Flame Charge_EjectButton": {"win": 2, "lost": 1}}}, "Savior": {"win": 24, "lost": 10, "battle_sets": {"Blaze Kick_Flame Charge_EjectButton": {"win": 24, "lost": 10}}}, "Trafyyy": {"win": 4, "lost": 3, "battle_sets": {"Blaze Kick_Flame Charge_EjectButton": {"win": 4, "lost": 3}}}}, "battle_sets": {"Blaze Kick_Flame Charge_EjectButton": {"win": 60, "lost": 25}, "Blaze Kick_Flame Charge_Purify": {"win": 8, "lost": 2}, "Blaze Kick_Flame Charge_Tail": {"win": 1, "lost": 0}, "Blaze Kick_Flame Charge_XAttack": {"win": 18, "lost": 8}, "Pyro Ball_Flame Charge_XAttack": {"win": 14, "lost": 5}, "Blaze Kick_Feint_EjectButton": {"win": 2, "lost": 0}}}, "Garchomp": {"win": 77, "lost": 35, "players": {"ttvNintendil": {"win": 31, "lost": 14, "battle_sets": {"Dragon Rush_Dragon Claw_EjectButton": {"win": 31, "lost": 13}, "Dig_Earthquake_EjectButton": {"win": 0, "lost": 1}}}, "PotatoUwU": {"win": 9, "lost": 4, "battle_sets": {"Dragon Rush_Dragon Claw_EjectButton": {"win": 9, "lost": 4}}}, "Aurimakii": {"win": 1, "lost": 0, "battle_sets": {"Dragon Rush_Dragon Claw_EjectButton": {"win": 1, "lost": 0}}}, "STMN\u30fbFroy": {"win": 2, "lost": 2, "battle_sets": {"Dragon Rush_Dragon Claw_EjectButton": {"win": 2, "lost": 2}}}, "\u30c8\u30e9\u30df\u30fcVT": {"win": 34, "lost": 15, "battle_sets": {"Dragon Rush_Dragon Claw_EjectButton": {"win": 34, "lost": 15}}}}, "battle_sets": {"Dragon Rush_Dragon Claw_EjectButton": {"win": 77, "lost": 34}, "Dig_Earthquake_EjectButton": {"win": 0, "lost": 1}}}, "Zeraora": {"win": 105, "lost": 52, "players": {"ENT\u30fbScepTer": {"win": 11, "lost": 4, "battle_sets": {"Volt Switch_Discharge_XAttack": {"win": 11, "lost": 4}}}, "RNS\u30e4Kamiru": {"win": 3, "lost": 2, "battle_sets": {"Volt Switch_Discharge_EjectButton": {"win": 2, "lost": 1}, "Volt Switch_Discharge_XAttack": {"win": 1, "lost": 1}}}, "S8uL\u30fbGhoul": {"win": 1, "lost": 2, "battle_sets": {"Spark_Discharge_XAttack": {"win": 0, "lost": 1}, "Volt Switch_Discharge_XAttack": {"win": 1, "lost": 1}}}, "\u3042_\u3052": {"win": 5, "lost": 1, "battle_sets": {"Volt Switch_Discharge_Tail": {"win": 5, "lost": 1}}}, "\u30e2\u30c1\u3082\u3061\u3082\u3061": {"win": 2, "lost": 3, "battle_sets": {"Spark_Discharge_Purify": {"win": 1, "lost": 1}, "Volt Switch_Discharge_Purify": {"win": 1, "lost": 1}, "Spark_Wild Charge_Purify": {"win": 0, "lost": 1}}}, "AFR\u30fbMiva": {"win": 9, "lost": 1, "battle_sets": {"Volt Switch_Discharge_XAttack": {"win": 9, "lost": 1}}}, "GZ\u30fbJoe": {"win": 4, "lost": 3, "battle_sets": {"Volt Switch_Discharge_XSpeed": {"win": 2, "lost": 0}, "Spark_Discharge_XSpeed": {"win": 0, "lost": 1}, "Volt Switch_Discharge_XAttack": {"win": 2, "lost": 2}}}, "AX\u30fbKyluKzz": {"win": 7, "lost": 1, "battle_sets": {"Spark_Wild Charge_XAttack": {"win": 6, "lost": 1}, "Volt Switch_Discharge_XAttack": {"win": 1, "lost": 0}}}, "RJG\u30fbRuvis": {"win": 1, "lost": 0, "battle_sets": {"Volt Switch_Discharge_XAttack": {"win": 1, "lost": 0}}}, "TE\u30fbTibi": {"win": 0, "lost": 1, "battle_sets": {"Volt Switch_Discharge_XAttack": {"win": 0, "lost": 1}}}, "MMT\u30fbCanniel": {"win": 26, "lost": 10, "battle_sets": {"Spark_Wild Charge_XAttack": {"win": 26, "lost": 10}}}, "Aurimakii": {"win": 0, "lost": 1, "battle_sets": {"Volt Switch_Discharge_Purify": {"win": 0, "lost": 1}}}, "STMN\u30fbFroy": {"win": 6, "lost": 1, "battle_sets": {"Volt Switch_Discharge_XAttack": {"win": 6, "lost": 1}}}, "GyZ": {"win": 1, "lost": 0, "battle_sets": {"Volt Switch_Discharge_XAttack": {"win": 1, "lost": 0}}}, "CeS\u68a6KiD": {"win": 13, "lost": 5, "battle_sets": {"Volt Switch_Discharge_XAttack": {"win": 12, "lost": 5}, "Spark_Wild Charge_XAttack": {"win": 1, "lost": 0}}}, "\u304a\u3044\u304b\u3073\u304d\u3089": {"win": 0, "lost": 3, "battle_sets": {"Volt Switch_Discharge_XAttack": {"win": 0, "lost": 3}}}, "jatinjwin": {"win": 3, "lost": 4, "battle_sets": {"Volt Switch_Discharge_Potion": {"win": 2, "lost": 3}, "Volt Switch_Discharge_XAttack": {"win": 1, "lost": 1}}}, "\u30e1\u30fbM'AMK0": {"win": 2, "lost": 3, "battle_sets": {"Volt Switch_Discharge_Purify": {"win": 2, "lost": 3}}}, "\u6687\u306a\u6771\u5927\u751f": {"win": 1, "lost": 0, "battle_sets": {"Spark_Discharge_EjectButton": {"win": 1, "lost": 0}}}, "\u9811\u5f35\u308d\u3046ww": {"win": 5, "lost": 4, "battle_sets": {"Volt Switch_Discharge_Purify": {"win": 5, "lost": 4}}}, "\u4e5bMyst": {"win": 2, "lost": 3, "battle_sets": {"Volt Switch_Discharge_Potion": {"win": 2, "lost": 3}}}, "Trafyyy": {"win": 3, "lost": 0, "battle_sets": {"Volt Switch_Discharge_EjectButton": {"win": 1, "lost": 0}, "Volt Switch_Discharge_XSpeed": {"win": 2, "lost": 0}}}}, "battle_sets": {"Volt Switch_Discharge_XAttack": {"win": 46, "lost": 20}, "Volt Switch_Discharge_EjectButton": {"win": 3, "lost": 1}, "Spark_Discharge_XAttack": {"win": 0, "lost": 1}, "Volt Switch_Discharge_Tail": {"win": 5, "lost": 1}, "Spark_Discharge_Purify": {"win": 1, "lost": 1}, "Volt Switch_Discharge_Purify": {"win": 8, "lost": 9}, "Spark_Wild Charge_Purify": {"win": 0, "lost": 1}, "Volt Switch_Discharge_XSpeed": {"win": 4, "lost": 0}, "Spark_Discharge_XSpeed": {"win": 0, "lost": 1}, "Spark_Wild Charge_XAttack": {"win": 33, "lost": 11}, "Volt Switch_Discharge_Potion": {"win": 4, "lost": 6}, "Spark_Discharge_EjectButton": {"win": 1, "lost": 0}}}, "Decidueye": {"win": 5, "lost": 3, "players": {"ENT\u30fbScepTer": {"win": 2, "lost": 0, "battle_sets": {"Spirit Shackle_Shadow Sneak_XSpeed": {"win": 2, "lost": 0}}}, "XIS\u30fbMazo": {"win": 1, "lost": 0, "battle_sets": {"Spirit Shackle_Shadow Sneak_EjectButton": {"win": 1, "lost": 0}}}, "\u30e2\u30c1\u3082\u3061\u3082\u3061": {"win": 1, "lost": 0, "battle_sets": {"Spirit Shackle_Shadow Sneak_XSpeed": {"win": 1, "lost": 0}}}, "\u308f\u3089\u3089\u308a\u3063\u304f": {"win": 1, "lost": 1, "battle_sets": {"Spirit Shackle_Shadow Sneak_EjectButton": {"win": 1, "lost": 1}}}, "ZapWarudo": {"win": 0, "lost": 1, "battle_sets": {"Spirit Shackle_Shadow Sneak_XSpeed": {"win": 0, "lost": 1}}}, "jatinjwin": {"win": 0, "lost": 1, "battle_sets": {"Spirit Shackle_Shadow Sneak_EjectButton": {"win": 0, "lost": 1}}}}, "battle_sets": {"Spirit Shackle_Shadow Sneak_XSpeed": {"win": 3, "lost": 1}, "Spirit Shackle_Shadow Sneak_EjectButton": {"win": 2, "lost": 2}}}, "Cramorant": {"win": 110, "lost": 31, "players": {"ENT\u30fbScepTer": {"win": 1, "lost": 1, "battle_sets": {"Dive_Air Slash_Potion": {"win": 1, "lost": 1}}}, "RNS\u30e4Kamiru": {"win": 1, "lost": 0, "battle_sets": {"Surf_Hurricane_EjectButton": {"win": 1, "lost": 0}}}, "S8uL\u30fbGhoul": {"win": 24, "lost": 4, "battle_sets": {"Surf_Hurricane_EjectButton": {"win": 24, "lost": 4}}}, "XIS\u30fbMazo": {"win": 10, "lost": 2, "battle_sets": {"Dive_Air Slash_EjectButton": {"win": 10, "lost": 2}}}, "\u3042_\u3052": {"win": 1, "lost": 0, "battle_sets": {"Dive_Air Slash_EjectButton": {"win": 1, "lost": 0}}}, "\u30e2\u30c1\u3082\u3061\u3082\u3061": {"win": 32, "lost": 8, "battle_sets": {"Surf_Air Slash_XAttack": {"win": 29, "lost": 7}, "Surf_Hurricane_XAttack": {"win": 2, "lost": 1}, "Surf_Air Slash_Potion": {"win": 1, "lost": 0}}}, "MW\u30fbTwoKiiL": {"win": 1, "lost": 0, "battle_sets": {"Dive_Air Slash_EjectButton": {"win": 1, "lost": 0}}}, "RJG\u30fbRuvis": {"win": 1, "lost": 0, "battle_sets": {"Surf_Hurricane_EjectButton": {"win": 1, "lost": 0}}}, "i9\u7231Crow": {"win": 1, "lost": 0, "battle_sets": {"Dive_Air Slash_Potion": {"win": 1, "lost": 0}}}, "\u304a\u3044\u304b\u3073\u304d\u3089": {"win": 4, "lost": 6, "battle_sets": {"Surf_Air Slash_EjectButton": {"win": 1, "lost": 1}, "Surf_Hurricane_EjectButton": {"win": 3, "lost": 4}, "Dive_Air Slash_EjectButton": {"win": 0, "lost": 1}}}, "UT_Kotori": {"win": 0, "lost": 1, "battle_sets": {"Surf_Air Slash_EjectButton": {"win": 0, "lost": 1}}}, "Kuus\u00ed": {"win": 6, "lost": 2, "battle_sets": {"Dive_Air Slash_EjectButton": {"win": 5, "lost": 2}, "Surf_Hurricane_EjectButton": {"win": 1, "lost": 0}}}, "HMB_runpa": {"win": 0, "lost": 1, "battle_sets": {"Dive_Air Slash_EjectButton": {"win": 0, "lost": 1}}}, "SirWaddleChu": {"win": 26, "lost": 6, "battle_sets": {"Dive_Air Slash_EjectButton": {"win": 26, "lost": 6}}}, "MeloskaPokki": {"win": 2, "lost": 0, "battle_sets": {"Dive_Air Slash_EjectButton": {"win": 2, "lost": 0}}}}, "battle_sets": {"Dive_Air Slash_Potion": {"win": 2, "lost": 1}, "Surf_Hurricane_EjectButton": {"win": 30, "lost": 8}, "Dive_Air Slash_EjectButton": {"win": 45, "lost": 12}, "Surf_Air Slash_XAttack": {"win": 29, "lost": 7}, "Surf_Hurricane_XAttack": {"win": 2, "lost": 1}, "Surf_Air Slash_Potion": {"win": 1, "lost": 0}, "Surf_Air Slash_EjectButton": {"win": 1, "lost": 2}}}, "Gardevoir": {"win": 82, "lost": 34, "players": {"RNS\u30e4Kamiru": {"win": 28, "lost": 11, "battle_sets": {"Moonblast_Psyshock_EjectButton": {"win": 28, "lost": 10}, "Psychic_Psyshock_EjectButton": {"win": 0, "lost": 1}}}, "\u79cb\u6d25\u831c": {"win": 1, "lost": 0, "battle_sets": {"Moonblast_Future Sight_XSpeed": {"win": 1, "lost": 0}}}, "\u304a\u3044\u304b\u3073\u304d\u3089": {"win": 2, "lost": 0, "battle_sets": {"Moonblast_Psyshock_XSpeed": {"win": 1, "lost": 0}, "Moonblast_Future Sight_XSpeed": {"win": 1, "lost": 0}}}, "KK_4E": {"win": 2, "lost": 1, "battle_sets": {"Psychic_Future Sight_EjectButton": {"win": 2, "lost": 1}}}, "blushUwU": {"win": 28, "lost": 12, "battle_sets": {"Moonblast_Future Sight_EjectButton": {"win": 28, "lost": 12}}}, "ryanxoxo": {"win": 21, "lost": 10, "battle_sets": {"Moonblast_Future Sight_EjectButton": {"win": 20, "lost": 10}, "Psychic_Future Sight_EjectButton": {"win": 1, "lost": 0}}}}, "battle_sets": {"Moonblast_Psyshock_EjectButton": {"win": 28, "lost": 10}, "Psychic_Psyshock_EjectButton": {"win": 0, "lost": 1}, "Moonblast_Future Sight_XSpeed": {"win": 2, "lost": 0}, "Moonblast_Psyshock_XSpeed": {"win": 1, "lost": 0}, "Psychic_Future Sight_EjectButton": {"win": 3, "lost": 1}, "Moonblast_Future Sight_EjectButton": {"win": 48, "lost": 22}}}, "Greninja": {"win": 193, "lost": 80, "players": {"RNS\u30e4Kamiru": {"win": 0, "lost": 1, "battle_sets": {"Surf_Smokescreen_XAttack": {"win": 0, "lost": 1}}}, "caligola999": {"win": 23, "lost": 3, "battle_sets": {"Surf_Smokescreen_EjectButton": {"win": 23, "lost": 3}}}, "\u30e2\u30c1\u3082\u3061\u3082\u3061": {"win": 0, "lost": 1, "battle_sets": {"Surf_Smokescreen_XAttack": {"win": 0, "lost": 1}}}, "PotatoUwU": {"win": 2, "lost": 0, "battle_sets": {"Surf_Smokescreen_XAttack": {"win": 2, "lost": 0}}}, "GZ\u30fbJoe": {"win": 12, "lost": 4, "battle_sets": {"Surf_Smokescreen_XAttack": {"win": 12, "lost": 4}}}, "MW\u30fbAngel\u30b7": {"win": 3, "lost": 0, "battle_sets": {"Surf_Smokescreen_XAttack": {"win": 3, "lost": 0}}}, "ttvSixsies": {"win": 0, "lost": 2, "battle_sets": {"Surf_Smokescreen_EjectButton": {"win": 0, "lost": 2}}}, "\u308f\u3089\u3089\u308a\u3063\u304f": {"win": 18, "lost": 8, "battle_sets": {"Surf_Smokescreen_XAttack": {"win": 18, "lost": 8}}}, "Aurimakii": {"win": 2, "lost": 1, "battle_sets": {"Surf_Smokescreen_Purify": {"win": 2, "lost": 1}}}, "\uacf5\uae09": {"win": 32, "lost": 17, "battle_sets": {"Water Shuriken_Smokescreen_XAttack": {"win": 4, "lost": 4}, "Surf_Smokescreen_XAttack": {"win": 28, "lost": 13}}}, "STMN\u30fbFroy": {"win": 1, "lost": 0, "battle_sets": {"Surf_Smokescreen_XAttack": {"win": 1, "lost": 0}}}, "\u304a\u3044\u304b\u3073\u304d\u3089": {"win": 3, "lost": 2, "battle_sets": {"Surf_Smokescreen_XAttack": {"win": 2, "lost": 2}, "Water Shuriken_Smokescreen_XAttack": {"win": 1, "lost": 0}}}, "UT_Kotori": {"win": 1, "lost": 1, "battle_sets": {"Surf_Smokescreen_XAttack": {"win": 1, "lost": 1}}}, "N_O_B": {"win": 26, "lost": 9, "battle_sets": {"Surf_Smokescreen_XAttack": {"win": 26, "lost": 9}}}, "\u6687\u306a\u6771\u5927\u751f": {"win": 1, "lost": 3, "battle_sets": {"Surf_Smokescreen_XAttack": {"win": 1, "lost": 3}}}, "RJG\u30fb\u6210\u5f1f": {"win": 8, "lost": 3, "battle_sets": {"Surf_Smokescreen_XAttack": {"win": 8, "lost": 3}}}, "\u4ffa\u306e\u30eb\u30ab\u30ea\u30aa": {"win": 16, "lost": 5, "battle_sets": {"Surf_Smokescreen_XAttack": {"win": 16, "lost": 5}}}, "20FF": {"win": 14, "lost": 7, "battle_sets": {"Surf_Smokescreen_XAttack": {"win": 14, "lost": 6}, "Water Shuriken_Double Team_XAttack": {"win": 0, "lost": 1}}}, "\u00c6\u00b7666": {"win": 3, "lost": 5, "battle_sets": {"Surf_Smokescreen_XAttack": {"win": 3, "lost": 5}}}, "TnK_KAITO": {"win": 13, "lost": 4, "battle_sets": {"Surf_Smokescreen_XAttack": {"win": 13, "lost": 4}}}, "\u5bc4\u751f\u5263\u5080\u5121\u5efb": {"win": 2, "lost": 2, "battle_sets": {"Surf_Smokescreen_XAttack": {"win": 2, "lost": 2}}}, "Trafyyy": {"win": 11, "lost": 2, "battle_sets": {"Surf_Smokescreen_EjectButton": {"win": 11, "lost": 2}}}, "MeloskaPokki": {"win": 2, "lost": 0, "battle_sets": {"Surf_Smokescreen_Purify": {"win": 1, "lost": 0}, "Surf_Smokescreen_XAttack": {"win": 1, "lost": 0}}}}, "battle_sets": {"Surf_Smokescreen_XAttack": {"win": 151, "lost": 67}, "Surf_Smokescreen_EjectButton": {"win": 34, "lost": 7}, "Surf_Smokescreen_Purify": {"win": 3, "lost": 1}, "Water Shuriken_Smokescreen_XAttack": {"win": 5, "lost": 4}, "Water Shuriken_Double Team_XAttack": {"win": 0, "lost": 1}}}, "Hoopa": {"win": 168, "lost": 59, "players": {"\ub108\ub3c4\ub0b4\uaebc": {"win": 1, "lost": 0, "battle_sets": {"Hyperspace Fury_Psybeam_XSpeed": {"win": 1, "lost": 0}}}, "5i\u30fbKeep": {"win": 1, "lost": 0, "battle_sets": {"Shadow Ball_Hyperspace Hole_XAttack": {"win": 1, "lost": 0}}}, "dordori": {"win": 0, "lost": 1, "battle_sets": {"Phantom Force_Hyperspace Hole_XSpeed": {"win": 0, "lost": 1}}}, "caligola999": {"win": 2, "lost": 0, "battle_sets": {"Phantom Force_Hyperspace Hole_XSpeed": {"win": 2, "lost": 0}}}, "XIS\u30fbMazo": {"win": 1, "lost": 0, "battle_sets": {"Phantom Force_Hyperspace Hole_EjectButton": {"win": 1, "lost": 0}}}, "PotatoUwU": {"win": 0, "lost": 1, "battle_sets": {"Phantom Force_Hyperspace Hole_XSpeed": {"win": 0, "lost": 1}}}, "GZ\u30fbJoe": {"win": 0, "lost": 1, "battle_sets": {"Phantom Force_Hyperspace Hole_XAttack": {"win": 0, "lost": 1}}}, "RJG\u30fbRuvis": {"win": 3, "lost": 3, "battle_sets": {"Phantom Force_Hyperspace Hole_XSpeed": {"win": 1, "lost": 1}, "Shadow Ball_Hyperspace Hole_XSpeed": {"win": 1, "lost": 1}, "Hyperspace Fury_Psybeam_XSpeed": {"win": 1, "lost": 1}}}, "TE\u30fbTibi": {"win": 1, "lost": 1, "battle_sets": {"Phantom Force_Hyperspace Hole_XSpeed": {"win": 1, "lost": 1}}}, "ttvSixsies": {"win": 3, "lost": 1, "battle_sets": {"Phantom Force_Hyperspace Hole_XSpeed": {"win": 3, "lost": 1}}}, "GyZ": {"win": 13, "lost": 2, "battle_sets": {"Phantom Force_Hyperspace Hole_XSpeed": {"win": 8, "lost": 2}, "Hyperspace Fury_Psybeam_XSpeed": {"win": 5, "lost": 0}}}, "ENT\u30fbProD": {"win": 17, "lost": 3, "battle_sets": {"Shadow Ball_Hyperspace Hole_Potion": {"win": 13, "lost": 3}, "Hyperspace Fury_Psybeam_Potion": {"win": 3, "lost": 0}, "Phantom Force_Hyperspace Hole_Potion": {"win": 1, "lost": 0}}}, "iamJPN": {"win": 22, "lost": 1, "battle_sets": {"Phantom Force_Hyperspace Hole_EjectButton": {"win": 17, "lost": 1}, "Hyperspace Fury_Psybeam_EjectButton": {"win": 5, "lost": 0}}}, "jatinjwin": {"win": 3, "lost": 1, "battle_sets": {"Phantom Force_Hyperspace Hole_XAttack": {"win": 1, "lost": 0}, "Hyperspace Fury_Psybeam_Potion": {"win": 2, "lost": 0}, "Phantom Force_Hyperspace Hole_Potion": {"win": 0, "lost": 1}}}, "TAC\u30fbWalt": {"win": 23, "lost": 11, "battle_sets": {"Phantom Force_Hyperspace Hole_XSpeed": {"win": 15, "lost": 9}, "Shadow Ball_Hyperspace Hole_XSpeed": {"win": 1, "lost": 0}, "Hyperspace Fury_Psybeam_XSpeed": {"win": 6, "lost": 2}, "Phantom Force_Trick_XSpeed": {"win": 1, "lost": 0}}}, "MW\u30fbJuan\u3048": {"win": 12, "lost": 1, "battle_sets": {"Hyperspace Fury_Psybeam_XSpeed": {"win": 3, "lost": 0}, "Phantom Force_Hyperspace Hole_XSpeed": {"win": 9, "lost": 1}}}, "STMN\u30fbKira": {"win": 6, "lost": 3, "battle_sets": {"Phantom Force_Hyperspace Hole_XSpeed": {"win": 3, "lost": 3}, "Hyperspace Fury_Psybeam_XSpeed": {"win": 3, "lost": 0}}}, "\u4e5bMyst": {"win": 8, "lost": 6, "battle_sets": {"Hyperspace Fury_Psybeam_XAttack": {"win": 2, "lost": 0}, "Phantom Force_Hyperspace Hole_XAttack": {"win": 6, "lost": 4}, "Shadow Ball_Hyperspace Hole_XAttack": {"win": 0, "lost": 1}, "Phantom Force_Trick_XAttack": {"win": 0, "lost": 1}}}, "01Agno": {"win": 5, "lost": 2, "battle_sets": {"Phantom Force_Hyperspace Hole_EjectButton": {"win": 3, "lost": 1}, "Shadow Ball_Hyperspace Hole_EjectButton": {"win": 1, "lost": 0}, "Hyperspace Fury_Psybeam_EjectButton": {"win": 1, "lost": 1}}}, "RJG\u30fbikura": {"win": 7, "lost": 4, "battle_sets": {"Shadow Ball_Hyperspace Hole_EjectButton": {"win": 2, "lost": 3}, "Hyperspace Fury_Psybeam_EjectButton": {"win": 5, "lost": 1}}}, "\u30d1\u30ca\u30d7\u541b": {"win": 1, "lost": 0, "battle_sets": {"Hyperspace Fury_Psybeam_XSpeed": {"win": 1, "lost": 0}}}, "MoneyMaxTTV": {"win": 20, "lost": 5, "battle_sets": {"Phantom Force_Hyperspace Hole_XSpeed": {"win": 17, "lost": 4}, "Hyperspace Fury_Psybeam_XSpeed": {"win": 3, "lost": 1}}}, "BB\u30fbAwita": {"win": 19, "lost": 12, "battle_sets": {"Shadow Ball_Hyperspace Hole_XSpeed": {"win": 12, "lost": 10}, "Phantom Force_Hyperspace Hole_XSpeed": {"win": 2, "lost": 0}, "Hyperspace Fury_Psybeam_XSpeed": {"win": 4, "lost": 2}, "Shadow Ball_Trick_XSpeed": {"win": 1, "lost": 0}}}}, "battle_sets": {"Hyperspace Fury_Psybeam_XSpeed": {"win": 27, "lost": 6}, "Shadow Ball_Hyperspace Hole_XAttack": {"win": 1, "lost": 1}, "Phantom Force_Hyperspace Hole_XSpeed": {"win": 61, "lost": 24}, "Phantom Force_Hyperspace Hole_EjectButton": {"win": 21, "lost": 2}, "Phantom Force_Hyperspace Hole_XAttack": {"win": 7, "lost": 5}, "Shadow Ball_Hyperspace Hole_XSpeed": {"win": 14, "lost": 11}, "Shadow Ball_Hyperspace Hole_Potion": {"win": 13, "lost": 3}, "Hyperspace Fury_Psybeam_Potion": {"win": 5, "lost": 0}, "Phantom Force_Hyperspace Hole_Potion": {"win": 1, "lost": 1}, "Hyperspace Fury_Psybeam_EjectButton": {"win": 11, "lost": 2}, "Phantom Force_Trick_XSpeed": {"win": 1, "lost": 0}, "Hyperspace Fury_Psybeam_XAttack": {"win": 2, "lost": 0}, "Phantom Force_Trick_XAttack": {"win": 0, "lost": 1}, "Shadow Ball_Hyperspace Hole_EjectButton": {"win": 3, "lost": 3}, "Shadow Ball_Trick_XSpeed": {"win": 1, "lost": 0}}}, "Eldegoss": {"win": 3, "lost": 1, "players": {"IsWillTV\u30c4": {"win": 3, "lost": 1, "battle_sets": {"Pollen Puff_Cotton Guard_XSpeed": {"win": 3, "lost": 1}}}}, "battle_sets": {"Pollen Puff_Cotton Guard_XSpeed": {"win": 3, "lost": 1}}}, "Aegislash": {"win": 12, "lost": 8, "players": {"5i\u30fbKeep": {"win": 1, "lost": 0, "battle_sets": {"Sacred Sword_Wide Guard_EjectButton": {"win": 1, "lost": 0}}}, "PotatoUwU": {"win": 1, "lost": 1, "battle_sets": {"Sacred Sword_Wide Guard_Purify": {"win": 1, "lost": 1}}}, "AFR\u30fbMiva": {"win": 1, "lost": 1, "battle_sets": {"Sacred Sword_Wide Guard_Potion": {"win": 1, "lost": 1}}}, "MW\u30fbMax": {"win": 1, "lost": 0, "battle_sets": {"Sacred Sword_Wide Guard_Purify": {"win": 1, "lost": 0}}}, "GyZ": {"win": 1, "lost": 1, "battle_sets": {"Sacred Sword_Wide Guard_EjectButton": {"win": 1, "lost": 1}}}, "\u304a\u3044\u304b\u3073\u304d\u3089": {"win": 1, "lost": 2, "battle_sets": {"Shadow Claw_Wide Guard_Potion": {"win": 1, "lost": 0}, "Sacred Sword_Wide Guard_Potion": {"win": 0, "lost": 2}}}, "Parasite": {"win": 2, "lost": 0, "battle_sets": {"Sacred Sword_Wide Guard_EjectButton": {"win": 1, "lost": 0}, "Sacred Sword_Wide Guard_Purify": {"win": 1, "lost": 0}}}, "99\u30e0\u4efb\u4e49\u4f1f": {"win": 1, "lost": 1, "battle_sets": {"Sacred Sword_Wide Guard_XAttack": {"win": 1, "lost": 1}}}, "\u6687\u306a\u6771\u5927\u751f": {"win": 0, "lost": 1, "battle_sets": {"Sacred Sword_Wide Guard_Potion": {"win": 0, "lost": 1}}}, "LeCodingTTV": {"win": 1, "lost": 0, "battle_sets": {"Sacred Sword_Wide Guard_XAttack": {"win": 1, "lost": 0}}}, "HMB_runpa": {"win": 2, "lost": 0, "battle_sets": {"Sacred Sword_Wide Guard_Potion": {"win": 2, "lost": 0}}}, "\u30d1\u30ca\u30d7\u541b": {"win": 0, "lost": 1, "battle_sets": {"Sacred Sword_Wide Guard_Potion": {"win": 0, "lost": 1}}}}, "battle_sets": {"Sacred Sword_Wide Guard_EjectButton": {"win": 3, "lost": 1}, "Sacred Sword_Wide Guard_Purify": {"win": 3, "lost": 1}, "Sacred Sword_Wide Guard_Potion": {"win": 3, "lost": 5}, "Shadow Claw_Wide Guard_Potion": {"win": 1, "lost": 0}, "Sacred Sword_Wide Guard_XAttack": {"win": 2, "lost": 1}}}, "Gengar": {"win": 101, "lost": 34, "players": {"Gh\u00f5st": {"win": 31, "lost": 11, "battle_sets": {"Shadow Ball_Dream Eater_EjectButton": {"win": 31, "lost": 11}}}, "XIS\u30fbMazo": {"win": 1, "lost": 0, "battle_sets": {"Shadow Ball_Dream Eater_EjectButton": {"win": 1, "lost": 0}}}, "\u79cb\u6d25\u831c": {"win": 30, "lost": 10, "battle_sets": {"Sludge Bomb_Hex_EjectButton": {"win": 29, "lost": 10}, "Shadow Ball_Hex_EjectButton": {"win": 1, "lost": 0}}}, "YORU04": {"win": 35, "lost": 10, "battle_sets": {"Shadow Ball_Dream Eater_XSpeed": {"win": 35, "lost": 10}}}, "STMN\u30fbFroy": {"win": 0, "lost": 1, "battle_sets": {"Shadow Ball_Dream Eater_EjectButton": {"win": 0, "lost": 1}}}, "Kuus\u00ed": {"win": 1, "lost": 0, "battle_sets": {"Sludge Bomb_Hex_EjectButton": {"win": 1, "lost": 0}}}, "\u00c6\u00b7666": {"win": 3, "lost": 1, "battle_sets": {"Sludge Bomb_Hex_EjectButton": {"win": 3, "lost": 1}}}, "LINH": {"win": 0, "lost": 1, "battle_sets": {"Shadow Ball_Dream Eater_EjectButton": {"win": 0, "lost": 1}}}}, "battle_sets": {"Shadow Ball_Dream Eater_EjectButton": {"win": 32, "lost": 13}, "Sludge Bomb_Hex_EjectButton": {"win": 33, "lost": 11}, "Shadow Ball_Hex_EjectButton": {"win": 1, "lost": 0}, "Shadow Ball_Dream Eater_XSpeed": {"win": 35, "lost": 10}}}, "Charizard": {"win": 22, "lost": 11, "players": {"XIS\u30fbMazo": {"win": 1, "lost": 0, "battle_sets": {"Flamethrower_Fire Blast_XAttack": {"win": 1, "lost": 0}}}, "\ud6c8\ud3ec\ub3c4": {"win": 1, "lost": 0, "battle_sets": {"Flamethrower_Fire Blast_XSpeed": {"win": 1, "lost": 0}}}, "GZ\u30fbJoe": {"win": 0, "lost": 1, "battle_sets": {"Flamethrower_Fire Blast_XSpeed": {"win": 0, "lost": 1}}}, "MW\u30fbAngel\u30b7": {"win": 1, "lost": 0, "battle_sets": {"Flamethrower_Fire Blast_EjectButton": {"win": 1, "lost": 0}}}, "CSC\u30fbf3rZera": {"win": 0, "lost": 1, "battle_sets": {"Fire Punch_Fire Blast_Purify": {"win": 0, "lost": 1}}}, "\u304a\u3044\u304b\u3073\u304d\u3089": {"win": 1, "lost": 0, "battle_sets": {"Flamethrower_Flare Blitz_XSpeed": {"win": 1, "lost": 0}}}, "ZapWarudo": {"win": 6, "lost": 4, "battle_sets": {"Flamethrower_Flare Blitz_XAttack": {"win": 1, "lost": 0}, "Flamethrower_Fire Blast_XAttack": {"win": 3, "lost": 4}, "Flamethrower_Fire Blast_Purify": {"win": 2, "lost": 0}}}, "UT_Kotori": {"win": 0, "lost": 1, "battle_sets": {"Flamethrower_Fire Blast_XSpeed": {"win": 0, "lost": 1}}}, "SirWaddleChu": {"win": 0, "lost": 1, "battle_sets": {"Flamethrower_Fire Blast_XSpeed": {"win": 0, "lost": 1}}}, "LINH": {"win": 12, "lost": 3, "battle_sets": {"Flamethrower_Fire Blast_Gear": {"win": 12, "lost": 3}}}}, "battle_sets": {"Flamethrower_Fire Blast_XAttack": {"win": 4, "lost": 4}, "Flamethrower_Fire Blast_XSpeed": {"win": 1, "lost": 3}, "Flamethrower_Fire Blast_EjectButton": {"win": 1, "lost": 0}, "Fire Punch_Fire Blast_Purify": {"win": 0, "lost": 1}, "Flamethrower_Flare Blitz_XSpeed": {"win": 1, "lost": 0}, "Flamethrower_Flare Blitz_XAttack": {"win": 1, "lost": 0}, "Flamethrower_Fire Blast_Purify": {"win": 2, "lost": 0}, "Flamethrower_Fire Blast_Gear": {"win": 12, "lost": 3}}}, "Snorlax": {"win": 69, "lost": 22, "players": {"\u3042_\u3052": {"win": 8, "lost": 1, "battle_sets": {"Heavy Slam_Block_XSpeed": {"win": 8, "lost": 1}}}, "RNS\u30e4NT\u30c4": {"win": 1, "lost": 0, "battle_sets": {"Heavy Slam_Block_EjectButton": {"win": 1, "lost": 0}}}, "NoL_Reirei": {"win": 1, "lost": 0, "battle_sets": {"Heavy Slam_Block_XSpeed": {"win": 1, "lost": 0}}}, "GZ\u30fbJoe": {"win": 1, "lost": 0, "battle_sets": {"Heavy Slam_Block_XSpeed": {"win": 1, "lost": 0}}}, "RJG\u30fbRuvis": {"win": 4, "lost": 2, "battle_sets": {"Heavy Slam_Block_XSpeed": {"win": 4, "lost": 2}}}, "GyZ": {"win": 7, "lost": 2, "battle_sets": {"Heavy Slam_Block_EjectButton": {"win": 7, "lost": 2}}}, "CeS\u68a6KiD": {"win": 0, "lost": 1, "battle_sets": {"Heavy Slam_Block_EjectButton": {"win": 0, "lost": 1}}}, "ENT\u30fbProD": {"win": 2, "lost": 1, "battle_sets": {"Heavy Slam_Block_EjectButton": {"win": 2, "lost": 1}}}, "\u304a\u3044\u304b\u3073\u304d\u3089": {"win": 1, "lost": 0, "battle_sets": {"Heavy Slam_Yawn_XSpeed": {"win": 1, "lost": 0}}}, "Kuus\u00ed": {"win": 0, "lost": 1, "battle_sets": {"Heavy Slam_Block_XSpeed": {"win": 0, "lost": 1}}}, "CeS\u68a6Luffy": {"win": 21, "lost": 5, "battle_sets": {"Heavy Slam_Block_EjectButton": {"win": 21, "lost": 5}}}, "\u9811\u5f35\u308d\u3046ww": {"win": 1, "lost": 1, "battle_sets": {"Heavy Slam_Block_XSpeed": {"win": 1, "lost": 1}}}, "\u4e5bMyst": {"win": 2, "lost": 0, "battle_sets": {"Heavy Slam_Block_EjectButton": {"win": 2, "lost": 0}}}, "01Agno": {"win": 1, "lost": 0, "battle_sets": {"Heavy Slam_Block_EjectButton": {"win": 1, "lost": 0}}}, "\u00c6\u00b7666": {"win": 6, "lost": 0, "battle_sets": {"Heavy Slam_Block_EjectButton": {"win": 1, "lost": 0}, "Heavy Slam_Block_XSpeed": {"win": 5, "lost": 0}}}, "\u30d1\u30ca\u30d7\u541b": {"win": 4, "lost": 3, "battle_sets": {"Heavy Slam_Block_XSpeed": {"win": 4, "lost": 3}}}, "LINH": {"win": 9, "lost": 4, "battle_sets": {"Flail_Yawn_Potion": {"win": 9, "lost": 4}}}, "\u5bc4\u751f\u5263\u5080\u5121\u5efb": {"win": 0, "lost": 1, "battle_sets": {"Heavy Slam_Block_XSpeed": {"win": 0, "lost": 1}}}}, "battle_sets": {"Heavy Slam_Block_XSpeed": {"win": 24, "lost": 9}, "Heavy Slam_Block_EjectButton": {"win": 35, "lost": 9}, "Heavy Slam_Yawn_XSpeed": {"win": 1, "lost": 0}, "Flail_Yawn_Potion": {"win": 9, "lost": 4}}}, "Alolan Ninetales": {"win": 7, "lost": 1, "players": {"\u3042_\u3052": {"win": 2, "lost": 0, "battle_sets": {"Dazzling Gleam_Aurora Veil_XAttack": {"win": 2, "lost": 0}}}, "MW\u30fbMax": {"win": 2, "lost": 0, "battle_sets": {"Dazzling Gleam_Blizzard_EjectButton": {"win": 1, "lost": 0}, "Avalanche_Blizzard_EjectButton": {"win": 1, "lost": 0}}}, "ZapWarudo": {"win": 1, "lost": 0, "battle_sets": {"Dazzling Gleam_Aurora Veil_Purify": {"win": 1, "lost": 0}}}, "UT_Kotori": {"win": 1, "lost": 0, "battle_sets": {"Dazzling Gleam_Aurora Veil_XAttack": {"win": 1, "lost": 0}}}, "RJG\u30fbikura": {"win": 1, "lost": 0, "battle_sets": {"Dazzling Gleam_Aurora Veil_XAttack": {"win": 1, "lost": 0}}}, "HMB_runpa": {"win": 0, "lost": 1, "battle_sets": {"Avalanche_Blizzard_XAttack": {"win": 0, "lost": 1}}}}, "battle_sets": {"Dazzling Gleam_Aurora Veil_XAttack": {"win": 4, "lost": 0}, "Dazzling Gleam_Blizzard_EjectButton": {"win": 1, "lost": 0}, "Avalanche_Blizzard_EjectButton": {"win": 1, "lost": 0}, "Dazzling Gleam_Aurora Veil_Purify": {"win": 1, "lost": 0}, "Avalanche_Blizzard_XAttack": {"win": 0, "lost": 1}}}, "Espeon": {"win": 7, "lost": 9, "players": {"\u3042_\u3052": {"win": 1, "lost": 0, "battle_sets": {"Psyshock_Psybeam_EjectButton": {"win": 1, "lost": 0}}}, "5i\u30fbInferno": {"win": 2, "lost": 0, "battle_sets": {"Psyshock_Future Sight_EjectButton": {"win": 2, "lost": 0}}}, "ttvSixsies": {"win": 1, "lost": 1, "battle_sets": {"Psyshock_Psybeam_XSpeed": {"win": 1, "lost": 1}}}, "Aurimakii": {"win": 0, "lost": 1, "battle_sets": {"Psyshock_Psybeam_XSpeed": {"win": 0, "lost": 1}}}, "ZapWarudo": {"win": 1, "lost": 2, "battle_sets": {"Psyshock_Future Sight_XSpeed": {"win": 1, "lost": 2}}}, "RJG\u30fbikura": {"win": 0, "lost": 2, "battle_sets": {"Psyshock_Future Sight_XSpeed": {"win": 0, "lost": 2}}}, "MoneyMaxTTV": {"win": 2, "lost": 3, "battle_sets": {"Psyshock_Future Sight_XSpeed": {"win": 2, "lost": 3}}}}, "battle_sets": {"Psyshock_Psybeam_EjectButton": {"win": 1, "lost": 0}, "Psyshock_Future Sight_EjectButton": {"win": 2, "lost": 0}, "Psyshock_Psybeam_XSpeed": {"win": 1, "lost": 2}, "Psyshock_Future Sight_XSpeed": {"win": 3, "lost": 7}}}, "Mamoswine": {"win": 6, "lost": 1, "players": {"\u3042_\u3052": {"win": 1, "lost": 0, "battle_sets": {"Icicle Crash_High Horsepower_EjectButton": {"win": 1, "lost": 0}}}, "YORU04": {"win": 0, "lost": 1, "battle_sets": {"Icicle Crash_High Horsepower_Potion": {"win": 0, "lost": 1}}}, "GyZ": {"win": 1, "lost": 0, "battle_sets": {"Icicle Crash_High Horsepower_Gear": {"win": 1, "lost": 0}}}, "01Agno": {"win": 4, "lost": 0, "battle_sets": {"Icicle Crash_High Horsepower_Potion": {"win": 3, "lost": 0}, "Icicle Crash_Earthquake_Potion": {"win": 1, "lost": 0}}}}, "battle_sets": {"Icicle Crash_High Horsepower_EjectButton": {"win": 1, "lost": 0}, "Icicle Crash_High Horsepower_Potion": {"win": 3, "lost": 1}, "Icicle Crash_High Horsepower_Gear": {"win": 1, "lost": 0}, "Icicle Crash_Earthquake_Potion": {"win": 1, "lost": 0}}}, "Mr. Mime": {"win": 25, "lost": 12, "players": {"\u3042_\u3052": {"win": 0, "lost": 1, "battle_sets": {"Confusion_Barrier_XSpeed": {"win": 0, "lost": 1}}}, "UT_Kotori": {"win": 18, "lost": 11, "battle_sets": {"Confusion_Guard Swap_XSpeed": {"win": 18, "lost": 11}}}, "01Agno": {"win": 7, "lost": 0, "battle_sets": {"Confusion_Barrier_XSpeed": {"win": 6, "lost": 0}, "Psychic_Guard Swap_XSpeed": {"win": 1, "lost": 0}}}}, "battle_sets": {"Confusion_Barrier_XSpeed": {"win": 6, "lost": 1}, "Confusion_Guard Swap_XSpeed": {"win": 18, "lost": 11}, "Psychic_Guard Swap_XSpeed": {"win": 1, "lost": 0}}}, "Wigglytuff": {"win": 20, "lost": 5, "players": {"NoL_Reirei": {"win": 2, "lost": 1, "battle_sets": {"Dazzling Gleam_Sing_EjectButton": {"win": 2, "lost": 1}}}, "Aurimakii": {"win": 1, "lost": 0, "battle_sets": {"Dazzling Gleam_Sing_EjectButton": {"win": 1, "lost": 0}}}, "Parasite": {"win": 16, "lost": 4, "battle_sets": {"Dazzling Gleam_Rollout_EjectButton": {"win": 16, "lost": 4}}}, "RJG\u30fbikura": {"win": 1, "lost": 0, "battle_sets": {"Dazzling Gleam_Rollout_EjectButton": {"win": 1, "lost": 0}}}}, "battle_sets": {"Dazzling Gleam_Sing_EjectButton": {"win": 3, "lost": 1}, "Dazzling Gleam_Rollout_EjectButton": {"win": 17, "lost": 4}}}, "Talonflame": {"win": 15, "lost": 7, "players": {"ttvSixsies": {"win": 1, "lost": 1, "battle_sets": {"Flame Charge_Fly_EjectButton": {"win": 1, "lost": 1}}}, "STMN\u30fbFroy": {"win": 3, "lost": 1, "battle_sets": {"Flame Charge_Fly_Potion": {"win": 3, "lost": 1}}}, "\u6687\u306a\u6771\u5927\u751f": {"win": 11, "lost": 5, "battle_sets": {"Flame Charge_Fly_EjectButton": {"win": 9, "lost": 2}, "Aerial Ace_Brave Bird_XAttack": {"win": 0, "lost": 3}, "Flame Charge_Fly_XAttack": {"win": 1, "lost": 0}, "Aerial Ace_Brave Bird_EjectButton": {"win": 1, "lost": 0}}}}, "battle_sets": {"Flame Charge_Fly_EjectButton": {"win": 10, "lost": 3}, "Flame Charge_Fly_Potion": {"win": 3, "lost": 1}, "Aerial Ace_Brave Bird_XAttack": {"win": 0, "lost": 3}, "Flame Charge_Fly_XAttack": {"win": 1, "lost": 0}, "Aerial Ace_Brave Bird_EjectButton": {"win": 1, "lost": 0}}}, "Absol": {"win": 5, "lost": 7, "players": {"STMN\u30fbFroy": {"win": 1, "lost": 0, "battle_sets": {"Night Slash_Sucker Punch_EjectButton": {"win": 1, "lost": 0}}}, "\u30e1\u30fbM'AMK0": {"win": 2, "lost": 4, "battle_sets": {"Night Slash_Psycho Cut_Purify": {"win": 2, "lost": 4}}}, "\u00c6\u00b7666": {"win": 1, "lost": 0, "battle_sets": {"Night Slash_Sucker Punch_Purify": {"win": 1, "lost": 0}}}, "SirWaddleChu": {"win": 1, "lost": 1, "battle_sets": {"Pursuit_Sucker Punch_EjectButton": {"win": 1, "lost": 1}}}, "Trafyyy": {"win": 0, "lost": 2, "battle_sets": {"Night Slash_Psycho Cut_Tail": {"win": 0, "lost": 2}}}}, "battle_sets": {"Night Slash_Sucker Punch_EjectButton": {"win": 1, "lost": 0}, "Night Slash_Psycho Cut_Purify": {"win": 2, "lost": 4}, "Night Slash_Sucker Punch_Purify": {"win": 1, "lost": 0}, "Pursuit_Sucker Punch_EjectButton": {"win": 1, "lost": 1}, "Night Slash_Psycho Cut_Tail": {"win": 0, "lost": 2}}}, "Crustle": {"win": 1, "lost": 0, "players": {"MeloskaPokki": {"win": 1, "lost": 0, "battle_sets": {"Shell Smash_X-Scissor_Ganrao": {"win": 1, "lost": 0}}}}, "battle_sets": {"Shell Smash_X-Scissor_Ganrao": {"win": 1, "lost": 0}}}}, "match_count": 2197}