{"pokemons": {"Mr. Mime": {"win": 277, "lost": 78, "players": {"MoneyMaxTV": {"win": 14, "lost": 2, "battle_sets": {"Confusion_Power Swap_XSpeed": {"win": 14, "lost": 2}}}, "NoobHuVai!": {"win": 7, "lost": 0, "battle_sets": {"Confusion_Power Swap_XSpeed": {"win": 7, "lost": 0}}}, "Teerawatb": {"win": 9, "lost": 1, "battle_sets": {"Confusion_Power Swap_XSpeed": {"win": 9, "lost": 1}}}, "SilentSheeps": {"win": 14, "lost": 3, "battle_sets": {"Confusion_Power Swap_XSpeed": {"win": 14, "lost": 3}}}, "1LevUP": {"win": 12, "lost": 3, "battle_sets": {"Confusion_Power Swap_XSpeed": {"win": 12, "lost": 3}}}, "TE\u30fbBarnW": {"win": 4, "lost": 4, "battle_sets": {"Confusion_Power Swap_XSpeed": {"win": 4, "lost": 4}}}, "OMO\u30e1Phoenix": {"win": 12, "lost": 2, "battle_sets": {"Confusion_Power Swap_XSpeed": {"win": 12, "lost": 2}}}, "\ucf54\ubbf8_\u3053\u307f": {"win": 9, "lost": 2, "battle_sets": {"Confusion_Power Swap_XSpeed": {"win": 9, "lost": 1}, "Psychic_Power Swap_XSpeed": {"win": 0, "lost": 1}}}, "pardisfat": {"win": 6, "lost": 1, "battle_sets": {"Confusion_Power Swap_XSpeed": {"win": 6, "lost": 1}}}, "KellyJT_\u9670\u967d": {"win": 17, "lost": 9, "battle_sets": {"Confusion_Power Swap_XSpeed": {"win": 16, "lost": 8}, "Confusion_Barrier_XSpeed": {"win": 1, "lost": 1}}}, "\u30a2\u30ce\u30fc\u30ea\u30ab": {"win": 2, "lost": 1, "battle_sets": {"Confusion_Power Swap_XSpeed": {"win": 2, "lost": 1}}}, "lRelentless": {"win": 3, "lost": 1, "battle_sets": {"Confusion_Power Swap_XSpeed": {"win": 3, "lost": 1}}}, "\u9006\u5f35\u308a\u30e4\u4e00\u30c9": {"win": 1, "lost": 0, "battle_sets": {"Confusion_Power Swap_XSpeed": {"win": 1, "lost": 0}}}, "\u30ea\u30ea\u30a3\u51db\u83ef": {"win": 16, "lost": 5, "battle_sets": {"Confusion_Power Swap_Potion": {"win": 16, "lost": 5}}}, "MW\u30fbTwoKiiL": {"win": 21, "lost": 5, "battle_sets": {"Confusion_Power Swap_Potion": {"win": 21, "lost": 5}}}, "VER\u30fbDaniel\u025e": {"win": 12, "lost": 3, "battle_sets": {"Confusion_Power Swap_XSpeed": {"win": 12, "lost": 3}}}, "Sunshine\u529b": {"win": 18, "lost": 1, "battle_sets": {"Confusion_Power Swap_XSpeed": {"win": 17, "lost": 1}, "Psychic_Power Swap_XSpeed": {"win": 1, "lost": 0}}}, "S\u4e28MarKGod": {"win": 6, "lost": 3, "battle_sets": {"Confusion_Power Swap_XSpeed": {"win": 6, "lost": 3}}}, "\u3072\u308d\u307d\u3059\u305f": {"win": 5, "lost": 1, "battle_sets": {"Confusion_Power Swap_XSpeed": {"win": 5, "lost": 1}}}, "RS_\u795e\u901f\u30de\u30f3": {"win": 1, "lost": 1, "battle_sets": {"Confusion_Power Swap_Tail": {"win": 1, "lost": 1}}}, "Chobo.": {"win": 9, "lost": 5, "battle_sets": {"Confusion_Power Swap_XSpeed": {"win": 9, "lost": 5}}}, "kxm\u00e0": {"win": 4, "lost": 0, "battle_sets": {"Confusion_Power Swap_XSpeed": {"win": 4, "lost": 0}}}, "OG\u3072Ice": {"win": 1, "lost": 0, "battle_sets": {"Confusion_Power Swap_XSpeed": {"win": 1, "lost": 0}}}, "\u5b9f\u306f\u30d4\u30af\u30bd\u30eb": {"win": 13, "lost": 6, "battle_sets": {"Confusion_Power Swap_XSpeed": {"win": 13, "lost": 6}}}, "CPH>NARUTO": {"win": 2, "lost": 0, "battle_sets": {"Confusion_Power Swap_XSpeed": {"win": 2, "lost": 0}}}, "INF\u30fbAnemo": {"win": 1, "lost": 0, "battle_sets": {"Confusion_Power Swap_XSpeed": {"win": 1, "lost": 0}}}, "\u91ce\u3061\u3083\u3044": {"win": 1, "lost": 0, "battle_sets": {"Confusion_Power Swap_XSpeed": {"win": 1, "lost": 0}}}, "Ansh_Blade": {"win": 5, "lost": 2, "battle_sets": {"Confusion_Power Swap_XSpeed": {"win": 5, "lost": 2}}}, "18V_piwai": {"win": 3, "lost": 0, "battle_sets": {"Confusion_Power Swap_XSpeed": {"win": 3, "lost": 0}}}, "INF\u30fbDrakenN": {"win": 4, "lost": 0, "battle_sets": {"Confusion_Power Swap_XSpeed": {"win": 4, "lost": 0}}}, "DG\u30fbGoku": {"win": 7, "lost": 2, "battle_sets": {"Confusion_Power Swap_XSpeed": {"win": 7, "lost": 2}}}, "Metallic\u30c4": {"win": 1, "lost": 2, "battle_sets": {"Confusion_Power Swap_XSpeed": {"win": 1, "lost": 2}}}, "RB_\u3086\u3081\u306b\u3083": {"win": 1, "lost": 2, "battle_sets": {"Confusion_Power Swap_XSpeed": {"win": 1, "lost": 2}}}, "Twist3xd": {"win": 6, "lost": 1, "battle_sets": {"Confusion_Power Swap_XSpeed": {"win": 6, "lost": 1}}}, "TheRedluvTTV": {"win": 0, "lost": 1, "battle_sets": {"Confusion_Power Swap_XSpeed": {"win": 0, "lost": 1}}}, "Sasuk\u00e9?": {"win": 8, "lost": 1, "battle_sets": {"Confusion_Power Swap_XSpeed": {"win": 8, "lost": 1}}}, "LEOJI.": {"win": 4, "lost": 1, "battle_sets": {"Confusion_Power Swap_XSpeed": {"win": 4, "lost": 1}}}, "99ASH99": {"win": 3, "lost": 0, "battle_sets": {"Confusion_Power Swap_XSpeed": {"win": 3, "lost": 0}}}, "DISapple": {"win": 1, "lost": 2, "battle_sets": {"Confusion_Power Swap_XSpeed": {"win": 0, "lost": 2}, "Psychic_Power Swap_XSpeed": {"win": 1, "lost": 0}}}, "Schenti": {"win": 14, "lost": 5, "battle_sets": {"Confusion_Power Swap_XSpeed": {"win": 14, "lost": 5}}}}, "battle_sets": {"Confusion_Power Swap_XSpeed": {"win": 236, "lost": 65}, "Psychic_Power Swap_XSpeed": {"win": 2, "lost": 1}, "Confusion_Barrier_XSpeed": {"win": 1, "lost": 1}, "Confusion_Power Swap_Potion": {"win": 37, "lost": 10}, "Confusion_Power Swap_Tail": {"win": 1, "lost": 1}}}, "Aegislash": {"win": 125, "lost": 47, "players": {"YT_DanielMil": {"win": 13, "lost": 1, "battle_sets": {"Sacred Sword_Wide Guard_XSpeed": {"win": 13, "lost": 1}}}, "Edgy777": {"win": 1, "lost": 0, "battle_sets": {"Sacred Sword_Wide Guard_Potion": {"win": 1, "lost": 0}}}, "1LevUP": {"win": 3, "lost": 0, "battle_sets": {"Sacred Sword_Wide Guard_Potion": {"win": 3, "lost": 0}}}, "\ucf54\ubbf8_\u3053\u307f": {"win": 0, "lost": 1, "battle_sets": {"Sacred Sword_Wide Guard_Potion": {"win": 0, "lost": 1}}}, "\u307f\u305f\u3089\u3057girl": {"win": 17, "lost": 5, "battle_sets": {"Sacred Sword_Wide Guard_Potion": {"win": 17, "lost": 5}}}, "MW\u30fbTwoKiiL": {"win": 5, "lost": 1, "battle_sets": {"Sacred Sword_Wide Guard_XSpeed": {"win": 5, "lost": 1}}}, "mare__": {"win": 6, "lost": 0, "battle_sets": {"Sacred Sword_Wide Guard_Potion": {"win": 6, "lost": 0}}}, "Galleta04": {"win": 1, "lost": 0, "battle_sets": {"Sacred Sword_Wide Guard_Potion": {"win": 1, "lost": 0}}}, "KylukIFood": {"win": 4, "lost": 2, "battle_sets": {"Sacred Sword_Wide Guard_Purify": {"win": 4, "lost": 2}}}, "S\u4e28MarKGod": {"win": 1, "lost": 1, "battle_sets": {"Sacred Sword_Wide Guard_Potion": {"win": 1, "lost": 1}}}, "RNT\u30fbXesoL": {"win": 7, "lost": 4, "battle_sets": {"Sacred Sword_Wide Guard_Potion": {"win": 7, "lost": 4}}}, "CPH>NARUTO": {"win": 1, "lost": 1, "battle_sets": {"Sacred Sword_Wide Guard_Potion": {"win": 1, "lost": 1}}}, "INF\u30fbAnemo": {"win": 1, "lost": 1, "battle_sets": {"Sacred Sword_Wide Guard_Potion": {"win": 1, "lost": 1}}}, "\ub2e4\ubbf8_\u30d2\u30e1\u00b0": {"win": 1, "lost": 0, "battle_sets": {"Sacred Sword_Wide Guard_Potion": {"win": 1, "lost": 0}}}, "Ansh_Blade": {"win": 0, "lost": 1, "battle_sets": {"Sacred Sword_Wide Guard_Potion": {"win": 0, "lost": 1}}}, "18V_piwai": {"win": 4, "lost": 1, "battle_sets": {"Sacred Sword_Wide Guard_Potion": {"win": 4, "lost": 1}}}, "INF\u30fbDrakenN": {"win": 5, "lost": 1, "battle_sets": {"Sacred Sword_Wide Guard_Potion": {"win": 5, "lost": 1}}}, "OMO\u30e1Zoe": {"win": 1, "lost": 0, "battle_sets": {"Sacred Sword_Wide Guard_Potion": {"win": 1, "lost": 0}}}, "Sasuk\u00e9?": {"win": 1, "lost": 0, "battle_sets": {"Sacred Sword_Wide Guard_Potion": {"win": 1, "lost": 0}}}, "TtvPikaGod22": {"win": 1, "lost": 6, "battle_sets": {"Sacred Sword_Wide Guard_Potion": {"win": 1, "lost": 1}, "Sacred Sword_Wide Guard_Purify": {"win": 0, "lost": 5}}}, "S2_piui": {"win": 9, "lost": 5, "battle_sets": {"Sacred Sword_Wide Guard_Purify": {"win": 9, "lost": 5}}}, "\u5c04\u9e21\u51a0\u519b": {"win": 14, "lost": 5, "battle_sets": {"Sacred Sword_Wide Guard_Potion": {"win": 13, "lost": 5}, "Shadow Claw_Wide Guard_Potion": {"win": 1, "lost": 0}}}, "\u306b\u3079\u3066\u3083": {"win": 25, "lost": 8, "battle_sets": {"Sacred Sword_Wide Guard_Potion": {"win": 25, "lost": 8}}}, "RNT\u30fbNovaa": {"win": 0, "lost": 2, "battle_sets": {"Sacred Sword_Wide Guard_Potion": {"win": 0, "lost": 2}}}, "DISapple": {"win": 3, "lost": 1, "battle_sets": {"Sacred Sword_Wide Guard_Potion": {"win": 3, "lost": 1}}}, "\u3053\u3053\u3042\u3063\u305f": {"win": 1, "lost": 0, "battle_sets": {"Sacred Sword_Wide Guard_Potion": {"win": 1, "lost": 0}}}}, "battle_sets": {"Sacred Sword_Wide Guard_XSpeed": {"win": 18, "lost": 2}, "Sacred Sword_Wide Guard_Potion": {"win": 93, "lost": 33}, "Sacred Sword_Wide Guard_Purify": {"win": 13, "lost": 12}, "Shadow Claw_Wide Guard_Potion": {"win": 1, "lost": 0}}}, "Tsareena": {"win": 66, "lost": 18, "players": {"YT_DanielMil": {"win": 1, "lost": 0, "battle_sets": {"Stomp_Trop Kick_XSpeed": {"win": 1, "lost": 0}}}, "pardisfat": {"win": 1, "lost": 0, "battle_sets": {"Stomp_Trop Kick_XSpeed": {"win": 1, "lost": 0}}}, "S2_\u82a5\u5ddd\u308a\u305c": {"win": 0, "lost": 1, "battle_sets": {"Stomp_Trop Kick_XSpeed": {"win": 0, "lost": 1}}}, "99\u00c6": {"win": 14, "lost": 3, "battle_sets": {"Stomp_Trop Kick_XSpeed": {"win": 13, "lost": 3}, "Triple Axel_Trop Kick_XSpeed": {"win": 1, "lost": 0}}}, "Galleta04": {"win": 1, "lost": 0, "battle_sets": {"Stomp_Trop Kick_XAttack": {"win": 1, "lost": 0}}}, "99\u30e0Renyiwei": {"win": 0, "lost": 1, "battle_sets": {"Stomp_Trop Kick_Purify": {"win": 0, "lost": 1}}}, "INF\u30fbAramis": {"win": 1, "lost": 0, "battle_sets": {"Stomp_Grassy Glide_XSpeed": {"win": 1, "lost": 0}}}, "KylukIFood": {"win": 3, "lost": 0, "battle_sets": {"Stomp_Trop Kick_Potion": {"win": 3, "lost": 0}}}, "Suntahj": {"win": 6, "lost": 0, "battle_sets": {"Stomp_Grassy Glide_XAttack": {"win": 6, "lost": 0}}}, "CPH>NARUTO": {"win": 2, "lost": 2, "battle_sets": {"Stomp_Trop Kick_XSpeed": {"win": 2, "lost": 1}, "Stomp_Grassy Glide_XSpeed": {"win": 0, "lost": 1}}}, "INF\u30fbAnemo": {"win": 1, "lost": 0, "battle_sets": {"Stomp_Trop Kick_XSpeed": {"win": 1, "lost": 0}}}, "\ub2e4\ubbf8_\u30d2\u30e1\u00b0": {"win": 0, "lost": 1, "battle_sets": {"Stomp_Trop Kick_XSpeed": {"win": 0, "lost": 1}}}, "Ansh_Blade": {"win": 0, "lost": 1, "battle_sets": {"Stomp_Trop Kick_XSpeed": {"win": 0, "lost": 1}}}, "RNT.BlizzarD": {"win": 1, "lost": 0, "battle_sets": {"Stomp_Trop Kick_XSpeed": {"win": 1, "lost": 0}}}, "Twist3xd": {"win": 5, "lost": 1, "battle_sets": {"Stomp_Trop Kick_XAttack": {"win": 5, "lost": 1}}}, "\u308d\u3093\u308d\u3093": {"win": 23, "lost": 7, "battle_sets": {"Stomp_Trop Kick_Purify": {"win": 11, "lost": 4}, "Triple Axel_Trop Kick_Purify": {"win": 12, "lost": 2}, "Stomp_Grassy Glide_Purify": {"win": 0, "lost": 1}}}, "S8ul\u30fbLegend": {"win": 4, "lost": 0, "battle_sets": {"Stomp_Trop Kick_Potion": {"win": 4, "lost": 0}}}, "RNT\u30fbNovaa": {"win": 2, "lost": 0, "battle_sets": {"Stomp_Trop Kick_XSpeed": {"win": 2, "lost": 0}}}, "DISapple": {"win": 1, "lost": 0, "battle_sets": {"Stomp_Trop Kick_XSpeed": {"win": 1, "lost": 0}}}, "\u3053\u3053\u3042\u3063\u305f": {"win": 0, "lost": 1, "battle_sets": {"Stomp_Trop Kick_XAttack": {"win": 0, "lost": 1}}}}, "battle_sets": {"Stomp_Trop Kick_XSpeed": {"win": 22, "lost": 7}, "Triple Axel_Trop Kick_XSpeed": {"win": 1, "lost": 0}, "Stomp_Trop Kick_XAttack": {"win": 6, "lost": 2}, "Stomp_Trop Kick_Purify": {"win": 11, "lost": 5}, "Stomp_Grassy Glide_XSpeed": {"win": 1, "lost": 1}, "Stomp_Trop Kick_Potion": {"win": 7, "lost": 0}, "Stomp_Grassy Glide_XAttack": {"win": 6, "lost": 0}, "Triple Axel_Trop Kick_Purify": {"win": 12, "lost": 2}, "Stomp_Grassy Glide_Purify": {"win": 0, "lost": 1}}}, "Dodrio": {"win": 168, "lost": 44, "players": {"TE\u30fbFreaK": {"win": 12, "lost": 4, "battle_sets": {"Tri Attack_Agility_Purify": {"win": 12, "lost": 4}}}, "YASHRANGERA": {"win": 4, "lost": 1, "battle_sets": {"Tri Attack_Agility_Purify": {"win": 4, "lost": 1}}}, "Teerawatb": {"win": 2, "lost": 2, "battle_sets": {"Tri Attack_Agility_Purify": {"win": 2, "lost": 2}}}, "TE\u30fbBarnW": {"win": 0, "lost": 1, "battle_sets": {"Tri Attack_Agility_Purify": {"win": 0, "lost": 1}}}, "\ucf54\ubbf8_\u3053\u307f": {"win": 1, "lost": 1, "battle_sets": {"Tri Attack_Agility_Purify": {"win": 1, "lost": 1}}}, "Stockings": {"win": 1, "lost": 0, "battle_sets": {"Tri Attack_Agility_Purify": {"win": 1, "lost": 0}}}, "\u30a2\u30ce\u30fc\u30ea\u30ab": {"win": 2, "lost": 0, "battle_sets": {"Tri Attack_Agility_Purify": {"win": 2, "lost": 0}}}, "S2_\u82a5\u5ddd\u308a\u305c": {"win": 8, "lost": 5, "battle_sets": {"Tri Attack_Agility_Purify": {"win": 7, "lost": 5}, "Tri Attack_Jump Kick_Purify": {"win": 1, "lost": 0}}}, "lRelentless": {"win": 4, "lost": 0, "battle_sets": {"Tri Attack_Agility_Purify": {"win": 4, "lost": 0}}}, "\u9006\u5f35\u308a\u30e4\u4e00\u30c9": {"win": 9, "lost": 5, "battle_sets": {"Tri Attack_Agility_Purify": {"win": 9, "lost": 5}}}, "Gow_YT\u4e36\u5584\u5fc3": {"win": 18, "lost": 2, "battle_sets": {"Tri Attack_Agility_XSpeed": {"win": 18, "lost": 2}}}, "Evek": {"win": 11, "lost": 1, "battle_sets": {"Tri Attack_Agility_Purify": {"win": 11, "lost": 1}}}, "-\u6708\u5149\u95c7-": {"win": 12, "lost": 3, "battle_sets": {"Tri Attack_Agility_Purify": {"win": 12, "lost": 3}}}, "Suna_7": {"win": 0, "lost": 1, "battle_sets": {"Tri Attack_Agility_Purify": {"win": 0, "lost": 1}}}, "ttvGhatIue": {"win": 16, "lost": 2, "battle_sets": {"Tri Attack_Agility_Purify": {"win": 16, "lost": 2}}}, "INF\u30fbAnemo": {"win": 9, "lost": 3, "battle_sets": {"Tri Attack_Agility_Purify": {"win": 9, "lost": 3}}}, "\u91ce\u3061\u3083\u3044": {"win": 21, "lost": 7, "battle_sets": {"Tri Attack_Agility_Purify": {"win": 21, "lost": 7}}}, "Metallic\u30c4": {"win": 3, "lost": 0, "battle_sets": {"Tri Attack_Agility_Purify": {"win": 3, "lost": 0}}}, "RB_\u3086\u3081\u306b\u3083": {"win": 13, "lost": 1, "battle_sets": {"Tri Attack_Agility_Purify": {"win": 13, "lost": 1}}}, "RNT.BlizzarD": {"win": 2, "lost": 0, "battle_sets": {"Tri Attack_Agility_Purify": {"win": 2, "lost": 0}}}, "H\u016bman": {"win": 8, "lost": 1, "battle_sets": {"Tri Attack_Agility_Purify": {"win": 8, "lost": 1}}}, "TheRedluvTTV": {"win": 3, "lost": 1, "battle_sets": {"Tri Attack_Agility_Purify": {"win": 3, "lost": 1}}}, "Edgy07": {"win": 1, "lost": 0, "battle_sets": {"Tri Attack_Agility_Purify": {"win": 1, "lost": 0}}}, "Sasuk\u00e9?": {"win": 0, "lost": 1, "battle_sets": {"Tri Attack_Agility_Ganrao": {"win": 0, "lost": 1}}}, "ELPREMIUMPR0": {"win": 1, "lost": 0, "battle_sets": {"Tri Attack_Agility_Purify": {"win": 1, "lost": 0}}}, "TtvPikaGod22": {"win": 2, "lost": 1, "battle_sets": {"Tri Attack_Agility_Purify": {"win": 2, "lost": 1}}}, "TMB\u30fbOsIrIs": {"win": 3, "lost": 0, "battle_sets": {"Tri Attack_Agility_Purify": {"win": 3, "lost": 0}}}, "DISapple": {"win": 2, "lost": 1, "battle_sets": {"Drill Peck_Agility_Purify": {"win": 0, "lost": 1}, "Tri Attack_Agility_Purify": {"win": 2, "lost": 0}}}}, "battle_sets": {"Tri Attack_Agility_Purify": {"win": 149, "lost": 40}, "Tri Attack_Jump Kick_Purify": {"win": 1, "lost": 0}, "Tri Attack_Agility_XSpeed": {"win": 18, "lost": 2}, "Tri Attack_Agility_Ganrao": {"win": 0, "lost": 1}, "Drill Peck_Agility_Purify": {"win": 0, "lost": 1}}}, "Talonflame": {"win": 11, "lost": 3, "players": {"TE\u30fbFreaK": {"win": 3, "lost": 1, "battle_sets": {"Flame Charge_Fly_Ganrao": {"win": 3, "lost": 1}}}, "Teerawatb": {"win": 1, "lost": 0, "battle_sets": {"Aerial Ace_Brave Bird_XAttack": {"win": 1, "lost": 0}}}, "Edgy777": {"win": 6, "lost": 1, "battle_sets": {"Flame Charge_Fly_Ganrao": {"win": 6, "lost": 1}}}, "\u3053\u3053\u3042\u3063\u305f": {"win": 1, "lost": 1, "battle_sets": {"Flame Charge_Fly_XAttack": {"win": 1, "lost": 1}}}}, "battle_sets": {"Flame Charge_Fly_Ganrao": {"win": 9, "lost": 2}, "Aerial Ace_Brave Bird_XAttack": {"win": 1, "lost": 0}, "Flame Charge_Fly_XAttack": {"win": 1, "lost": 1}}}, "Tyranitar": {"win": 36, "lost": 8, "players": {"TE\u30fbBora": {"win": 20, "lost": 2, "battle_sets": {"Dark Pulse_Ancient Power_XSpeed": {"win": 20, "lost": 2}}}, "Edgy777": {"win": 3, "lost": 1, "battle_sets": {"Dark Pulse_Ancient Power_XSpeed": {"win": 3, "lost": 1}}}, "lRelentless": {"win": 1, "lost": 1, "battle_sets": {"Dark Pulse_Ancient Power_XSpeed": {"win": 1, "lost": 1}}}, "INF\u30fbAnemo": {"win": 2, "lost": 0, "battle_sets": {"Dark Pulse_Ancient Power_XSpeed": {"win": 2, "lost": 0}}}, "Metallic\u30c4": {"win": 1, "lost": 0, "battle_sets": {"Dark Pulse_Ancient Power_XSpeed": {"win": 1, "lost": 0}}}, "TheRedluvTTV": {"win": 2, "lost": 0, "battle_sets": {"Dark Pulse_Ancient Power_Purify": {"win": 2, "lost": 0}}}, "IX\u30fbSherlock": {"win": 5, "lost": 2, "battle_sets": {"Dark Pulse_Ancient Power_XSpeed": {"win": 5, "lost": 2}}}, "Sasuk\u00e9?": {"win": 0, "lost": 1, "battle_sets": {"Dark Pulse_Ancient Power_Potion": {"win": 0, "lost": 1}}}, "DISapple": {"win": 2, "lost": 1, "battle_sets": {"Dark Pulse_Ancient Power_XSpeed": {"win": 2, "lost": 1}}}}, "battle_sets": {"Dark Pulse_Ancient Power_XSpeed": {"win": 34, "lost": 7}, "Dark Pulse_Ancient Power_Purify": {"win": 2, "lost": 0}, "Dark Pulse_Ancient Power_Potion": {"win": 0, "lost": 1}}}, "Mew": {"win": 321, "lost": 133, "players": {"NoobHuVai!": {"win": 11, "lost": 3, "battle_sets": {"Solar Beam_Light Screen_EjectButton": {"win": 5, "lost": 2}, "In Choice_In Choice_EjectButton": {"win": 1, "lost": 0}, "Surf_Agility_EjectButton": {"win": 4, "lost": 1}, "Solar Beam_In Choice_EjectButton": {"win": 1, "lost": 0}}}, "YASHRANGERA": {"win": 8, "lost": 1, "battle_sets": {"Solar Beam_Light Screen_EjectButton": {"win": 5, "lost": 0}, "Surf_Agility_EjectButton": {"win": 3, "lost": 1}}}, "SilentSheeps": {"win": 1, "lost": 1, "battle_sets": {"Solar Beam_Coaching_EjectButton": {"win": 1, "lost": 0}, "Solar Beam_In Choice_EjectButton": {"win": 0, "lost": 1}}}, "CeS\u68a6KiD": {"win": 4, "lost": 1, "battle_sets": {"Surf_Agility_EjectButton": {"win": 2, "lost": 1}, "Solar Beam_Light Screen_EjectButton": {"win": 1, "lost": 0}, "Electro Ball_Agility_EjectButton": {"win": 1, "lost": 0}}}, "OMO\u30e1Phoenix": {"win": 3, "lost": 0, "battle_sets": {"Solar Beam_Light Screen_XSpeed": {"win": 2, "lost": 0}, "Surf_Agility_XSpeed": {"win": 1, "lost": 0}}}, "\ucf54\ubbf8_\u3053\u307f": {"win": 9, "lost": 6, "battle_sets": {"Surf_Agility_EjectButton": {"win": 4, "lost": 5}, "Solar Beam_Agility_EjectButton": {"win": 2, "lost": 0}, "Surf_Light Screen_EjectButton": {"win": 1, "lost": 0}, "Solar Beam_Light Screen_EjectButton": {"win": 0, "lost": 1}, "Electro Ball_In Choice_EjectButton": {"win": 1, "lost": 0}, "Electro Ball_Agility_EjectButton": {"win": 1, "lost": 0}}}, "pardisfat": {"win": 8, "lost": 5, "battle_sets": {"Solar Beam_Light Screen_XAttack": {"win": 3, "lost": 3}, "Surf_Agility_XAttack": {"win": 3, "lost": 1}, "In Choice_In Choice_XAttack": {"win": 1, "lost": 0}, "Solar Beam_Agility_XAttack": {"win": 0, "lost": 1}, "Electro Ball_Agility_XAttack": {"win": 1, "lost": 0}}}, "Stockings": {"win": 9, "lost": 3, "battle_sets": {"Solar Beam_Light Screen_EjectButton": {"win": 5, "lost": 1}, "Surf_Agility_EjectButton": {"win": 2, "lost": 1}, "Electro Ball_Agility_EjectButton": {"win": 0, "lost": 1}, "Solar Beam_Agility_EjectButton": {"win": 2, "lost": 0}}}, "\u30a2\u30ce\u30fc\u30ea\u30ab": {"win": 9, "lost": 5, "battle_sets": {"Solar Beam_Light Screen_EjectButton": {"win": 2, "lost": 3}, "Solar Beam_Agility_EjectButton": {"win": 4, "lost": 0}, "Electro Ball_Agility_EjectButton": {"win": 2, "lost": 0}, "Surf_Light Screen_EjectButton": {"win": 0, "lost": 1}, "Surf_Agility_EjectButton": {"win": 1, "lost": 1}}}, "ObuyanTV\u30fbYT": {"win": 5, "lost": 3, "battle_sets": {"Surf_Agility_EjectButton": {"win": 1, "lost": 0}, "Solar Beam_Agility_EjectButton": {"win": 2, "lost": 0}, "Surf_In Choice_EjectButton": {"win": 0, "lost": 1}, "Solar Beam_Light Screen_EjectButton": {"win": 2, "lost": 1}, "Electro Ball_Agility_EjectButton": {"win": 0, "lost": 1}}}, "lRelentless": {"win": 1, "lost": 1, "battle_sets": {"Solar Beam_Agility_EjectButton": {"win": 1, "lost": 0}, "Surf_Agility_EjectButton": {"win": 0, "lost": 1}}}, "\u307f\u305f\u3089\u3057girl": {"win": 5, "lost": 2, "battle_sets": {"Surf_Agility_EjectButton": {"win": 2, "lost": 2}, "Solar Beam_Light Screen_EjectButton": {"win": 3, "lost": 0}}}, "mare__": {"win": 9, "lost": 3, "battle_sets": {"Solar Beam_Agility_EjectButton": {"win": 1, "lost": 2}, "Solar Beam_Light Screen_EjectButton": {"win": 4, "lost": 0}, "Surf_Agility_EjectButton": {"win": 3, "lost": 1}, "Surf_Light Screen_EjectButton": {"win": 1, "lost": 0}}}, "Galleta04": {"win": 1, "lost": 0, "battle_sets": {"Solar Beam_Light Screen_EjectButton": {"win": 1, "lost": 0}}}, "99\u30e0Renyiwei": {"win": 23, "lost": 7, "battle_sets": {"Surf_Agility_EjectButton": {"win": 7, "lost": 1}, "Solar Beam_Light Screen_EjectButton": {"win": 9, "lost": 5}, "Solar Beam_Agility_EjectButton": {"win": 5, "lost": 0}, "Electro Ball_Agility_EjectButton": {"win": 1, "lost": 1}, "In Choice_In Choice_EjectButton": {"win": 1, "lost": 0}}}, "INF\u30fbAramis": {"win": 11, "lost": 2, "battle_sets": {"Solar Beam_Light Screen_EjectButton": {"win": 0, "lost": 1}, "Surf_Agility_EjectButton": {"win": 4, "lost": 0}, "Electro Ball_Agility_EjectButton": {"win": 4, "lost": 1}, "Solar Beam_Agility_EjectButton": {"win": 2, "lost": 0}, "Electro Ball_Coaching_EjectButton": {"win": 1, "lost": 0}}}, "Suna_7": {"win": 13, "lost": 9, "battle_sets": {"Solar Beam_Light Screen_EjectButton": {"win": 3, "lost": 4}, "Surf_Agility_EjectButton": {"win": 10, "lost": 5}}}, "ttvGhatIue": {"win": 0, "lost": 1, "battle_sets": {"Solar Beam_Agility_EjectButton": {"win": 0, "lost": 1}}}, "RS_\u795e\u901f\u30de\u30f3": {"win": 20, "lost": 8, "battle_sets": {"Solar Beam_Light Screen_EjectButton": {"win": 4, "lost": 4}, "Electro Ball_Agility_EjectButton": {"win": 2, "lost": 0}, "Surf_Agility_EjectButton": {"win": 12, "lost": 3}, "Solar Beam_Coaching_EjectButton": {"win": 1, "lost": 0}, "Solar Beam_Agility_EjectButton": {"win": 1, "lost": 1}}}, "sTl": {"win": 12, "lost": 3, "battle_sets": {"Surf_Agility_EjectButton": {"win": 7, "lost": 2}, "Solar Beam_Agility_EjectButton": {"win": 1, "lost": 1}, "Electro Ball_Agility_EjectButton": {"win": 3, "lost": 0}, "Electro Ball_Coaching_EjectButton": {"win": 1, "lost": 0}}}, "Romfndq": {"win": 6, "lost": 2, "battle_sets": {"Electro Ball_Agility_EjectButton": {"win": 1, "lost": 1}, "Solar Beam_Agility_EjectButton": {"win": 2, "lost": 0}, "Solar Beam_Light Screen_EjectButton": {"win": 3, "lost": 1}}}, "\ub2e4\ubbf8_\u30d2\u30e1\u00b0": {"win": 6, "lost": 7, "battle_sets": {"Surf_Coaching_EjectButton": {"win": 0, "lost": 1}, "Solar Beam_Agility_EjectButton": {"win": 1, "lost": 2}, "Surf_Agility_EjectButton": {"win": 1, "lost": 1}, "Surf_Light Screen_EjectButton": {"win": 3, "lost": 0}, "Solar Beam_Light Screen_EjectButton": {"win": 0, "lost": 2}, "Solar Beam_In Choice_EjectButton": {"win": 1, "lost": 0}, "Electro Ball_Agility_EjectButton": {"win": 0, "lost": 1}}}, "Ansh_Blade": {"win": 7, "lost": 5, "battle_sets": {"Solar Beam_Light Screen_EjectButton": {"win": 4, "lost": 5}, "Surf_Agility_EjectButton": {"win": 3, "lost": 0}}}, "W\u00e4fu": {"win": 11, "lost": 3, "battle_sets": {"Solar Beam_Light Screen_EjectButton": {"win": 4, "lost": 1}, "Surf_Agility_EjectButton": {"win": 6, "lost": 1}, "Solar Beam_Agility_EjectButton": {"win": 1, "lost": 0}, "Surf_In Choice_EjectButton": {"win": 0, "lost": 1}}}, "ePe": {"win": 9, "lost": 5, "battle_sets": {"Surf_Agility_EjectButton": {"win": 3, "lost": 2}, "Solar Beam_Light Screen_EjectButton": {"win": 4, "lost": 2}, "Solar Beam_Agility_EjectButton": {"win": 2, "lost": 1}}}, "18V_piwai": {"win": 3, "lost": 1, "battle_sets": {"Electro Ball_Coaching_EjectButton": {"win": 1, "lost": 0}, "Surf_Agility_EjectButton": {"win": 0, "lost": 1}, "Solar Beam_Agility_EjectButton": {"win": 2, "lost": 0}}}, "Metallic\u30c4": {"win": 1, "lost": 0, "battle_sets": {"Surf_Agility_EjectButton": {"win": 1, "lost": 0}}}, "OMO\u30e1Zoe": {"win": 17, "lost": 7, "battle_sets": {"Solar Beam_Agility_XAttack": {"win": 3, "lost": 2}, "Surf_Agility_XAttack": {"win": 11, "lost": 4}, "Electro Ball_Agility_XAttack": {"win": 2, "lost": 1}, "Solar Beam_Light Screen_XAttack": {"win": 1, "lost": 0}}}, "TheRedluvTTV": {"win": 3, "lost": 2, "battle_sets": {"Solar Beam_Light Screen_XSpeed": {"win": 1, "lost": 0}, "Surf_Agility_XSpeed": {"win": 0, "lost": 1}, "Solar Beam_Agility_XSpeed": {"win": 1, "lost": 0}, "Electro Ball_Coaching_XSpeed": {"win": 1, "lost": 1}}}, "IX\u30fbSherlock": {"win": 7, "lost": 3, "battle_sets": {"Surf_Agility_XSpeed": {"win": 3, "lost": 1}, "Solar Beam_Light Screen_XSpeed": {"win": 3, "lost": 2}, "Surf_Coaching_XSpeed": {"win": 1, "lost": 0}}}, "NightmewFoxy": {"win": 19, "lost": 4, "battle_sets": {"Solar Beam_Light Screen_EjectButton": {"win": 5, "lost": 0}, "Surf_Agility_EjectButton": {"win": 2, "lost": 3}, "Solar Beam_Agility_EjectButton": {"win": 1, "lost": 0}, "In Choice_In Choice_EjectButton": {"win": 2, "lost": 0}, "Electro Ball_Coaching_EjectButton": {"win": 1, "lost": 0}, "Solar Beam_Light Screen_XAttack": {"win": 4, "lost": 1}, "In Choice_In Choice_XAttack": {"win": 1, "lost": 0}, "Solar Beam_Agility_XAttack": {"win": 1, "lost": 0}, "Surf_Agility_XAttack": {"win": 2, "lost": 0}}}, "Sasuk\u00e9?": {"win": 1, "lost": 1, "battle_sets": {"Solar Beam_Agility_EjectButton": {"win": 0, "lost": 1}, "Surf_Agility_EjectButton": {"win": 1, "lost": 0}}}, "ELPREMIUMPR0": {"win": 13, "lost": 1, "battle_sets": {"Surf_Agility_EjectButton": {"win": 3, "lost": 1}, "Solar Beam_Light Screen_EjectButton": {"win": 1, "lost": 0}, "Solar Beam_Coaching_EjectButton": {"win": 1, "lost": 0}, "In Choice_In Choice_EjectButton": {"win": 1, "lost": 0}, "Surf_Agility_XSpeed": {"win": 3, "lost": 0}, "Solar Beam_Light Screen_XSpeed": {"win": 4, "lost": 0}}}, "RoseTheHat": {"win": 23, "lost": 6, "battle_sets": {"Solar Beam_Light Screen_EjectButton": {"win": 13, "lost": 5}, "Electro Ball_Agility_EjectButton": {"win": 3, "lost": 1}, "Surf_Agility_EjectButton": {"win": 6, "lost": 0}, "In Choice_In Choice_EjectButton": {"win": 1, "lost": 0}}}, "LEOJI.": {"win": 2, "lost": 2, "battle_sets": {"Solar Beam_Light Screen_EjectButton": {"win": 0, "lost": 1}, "Solar Beam_Agility_EjectButton": {"win": 1, "lost": 1}, "Surf_Agility_EjectButton": {"win": 1, "lost": 0}}}, "YORU04": {"win": 6, "lost": 3, "battle_sets": {"Solar Beam_Agility_EjectButton": {"win": 3, "lost": 0}, "Surf_Agility_EjectButton": {"win": 2, "lost": 3}, "Solar Beam_In Choice_EjectButton": {"win": 1, "lost": 0}}}, "S8ul\u30fbLegend": {"win": 1, "lost": 0, "battle_sets": {"Solar Beam_Light Screen_XSpeed": {"win": 1, "lost": 0}}}, "99ASH99": {"win": 15, "lost": 6, "battle_sets": {"Solar Beam_Light Screen_EjectButton": {"win": 8, "lost": 3}, "Surf_Agility_EjectButton": {"win": 7, "lost": 3}}}, "Ray\u00fd": {"win": 1, "lost": 0, "battle_sets": {"Solar Beam_Light Screen_EjectButton": {"win": 1, "lost": 0}}}, "DISapple": {"win": 1, "lost": 2, "battle_sets": {"Solar Beam_Light Screen_EjectButton": {"win": 1, "lost": 1}, "Surf_Agility_EjectButton": {"win": 0, "lost": 1}}}, "SF\u00d7GeasSind": {"win": 7, "lost": 9, "battle_sets": {"Surf_Agility_XSpeed": {"win": 5, "lost": 5}, "Solar Beam_Light Screen_XSpeed": {"win": 1, "lost": 3}, "Solar Beam_Agility_XSpeed": {"win": 1, "lost": 0}, "Electro Ball_Agility_XSpeed": {"win": 0, "lost": 1}}}}, "battle_sets": {"Solar Beam_Light Screen_EjectButton": {"win": 88, "lost": 43}, "In Choice_In Choice_EjectButton": {"win": 6, "lost": 0}, "Surf_Agility_EjectButton": {"win": 98, "lost": 41}, "Solar Beam_In Choice_EjectButton": {"win": 3, "lost": 1}, "Solar Beam_Coaching_EjectButton": {"win": 3, "lost": 0}, "Electro Ball_Agility_EjectButton": {"win": 18, "lost": 7}, "Solar Beam_Light Screen_XSpeed": {"win": 12, "lost": 5}, "Surf_Agility_XSpeed": {"win": 12, "lost": 7}, "Solar Beam_Agility_EjectButton": {"win": 34, "lost": 10}, "Surf_Light Screen_EjectButton": {"win": 5, "lost": 1}, "Electro Ball_In Choice_EjectButton": {"win": 1, "lost": 0}, "Solar Beam_Light Screen_XAttack": {"win": 8, "lost": 4}, "Surf_Agility_XAttack": {"win": 16, "lost": 5}, "In Choice_In Choice_XAttack": {"win": 2, "lost": 0}, "Solar Beam_Agility_XAttack": {"win": 4, "lost": 3}, "Electro Ball_Agility_XAttack": {"win": 3, "lost": 1}, "Surf_In Choice_EjectButton": {"win": 0, "lost": 2}, "Electro Ball_Coaching_EjectButton": {"win": 4, "lost": 0}, "Surf_Coaching_EjectButton": {"win": 0, "lost": 1}, "Solar Beam_Agility_XSpeed": {"win": 2, "lost": 0}, "Electro Ball_Coaching_XSpeed": {"win": 1, "lost": 1}, "Surf_Coaching_XSpeed": {"win": 1, "lost": 0}, "Electro Ball_Agility_XSpeed": {"win": 0, "lost": 1}}}, "Blissey": {"win": 26, "lost": 6, "players": {"NoobHuVai!": {"win": 1, "lost": 0, "battle_sets": {"Egg Bomb_Soft-Boiled_XSpeed": {"win": 1, "lost": 0}}}, "SilentSheeps": {"win": 1, "lost": 0, "battle_sets": {"Egg Bomb_Soft-Boiled_XSpeed": {"win": 1, "lost": 0}}}, "CeS\u68a6KiD": {"win": 7, "lost": 0, "battle_sets": {"Egg Bomb_Soft-Boiled_EjectButton": {"win": 6, "lost": 0}, "Helping Hand_Safeguard_EjectButton": {"win": 1, "lost": 0}}}, "KylukIFood": {"win": 6, "lost": 2, "battle_sets": {"Egg Bomb_Soft-Boiled_XSpeed": {"win": 6, "lost": 2}}}, "RNT\u30fbXesoL": {"win": 4, "lost": 2, "battle_sets": {"Egg Bomb_Soft-Boiled_XSpeed": {"win": 1, "lost": 0}, "Egg Bomb_Safeguard_XSpeed": {"win": 3, "lost": 2}}}, "I'mSnow:D": {"win": 1, "lost": 0, "battle_sets": {"Egg Bomb_Soft-Boiled_XSpeed": {"win": 1, "lost": 0}}}, "\uc720\uadf8\ub140": {"win": 4, "lost": 1, "battle_sets": {"Egg Bomb_Soft-Boiled_XSpeed": {"win": 4, "lost": 1}}}, "RNT\u30fbVulcan": {"win": 1, "lost": 1, "battle_sets": {"Egg Bomb_Safeguard_XSpeed": {"win": 1, "lost": 0}, "Egg Bomb_Soft-Boiled_XSpeed": {"win": 0, "lost": 1}}}, "Schenti": {"win": 1, "lost": 0, "battle_sets": {"Egg Bomb_Soft-Boiled_XSpeed": {"win": 1, "lost": 0}}}}, "battle_sets": {"Egg Bomb_Soft-Boiled_XSpeed": {"win": 15, "lost": 4}, "Egg Bomb_Soft-Boiled_EjectButton": {"win": 6, "lost": 0}, "Helping Hand_Safeguard_EjectButton": {"win": 1, "lost": 0}, "Egg Bomb_Safeguard_XSpeed": {"win": 4, "lost": 2}}}, "Decidueye": {"win": 8, "lost": 4, "players": {"YASHRANGERA": {"win": 1, "lost": 1, "battle_sets": {"Spirit Shackle_Shadow Sneak_EjectButton": {"win": 1, "lost": 1}}}, "Teerawatb": {"win": 1, "lost": 0, "battle_sets": {"Spirit Shackle_Shadow Sneak_XSpeed": {"win": 1, "lost": 0}}}, "CeS\u68a6KiD": {"win": 1, "lost": 0, "battle_sets": {"Spirit Shackle_Shadow Sneak_XSpeed": {"win": 1, "lost": 0}}}, "S\u4e28MarKGod": {"win": 0, "lost": 1, "battle_sets": {"Spirit Shackle_Shadow Sneak_EjectButton": {"win": 0, "lost": 1}}}, "Ansh_Blade": {"win": 1, "lost": 1, "battle_sets": {"Spirit Shackle_Shadow Sneak_XSpeed": {"win": 1, "lost": 1}}}, "RNT.BlizzarD": {"win": 1, "lost": 1, "battle_sets": {"Spirit Shackle_Shadow Sneak_EjectButton": {"win": 1, "lost": 1}}}, "Edgy07": {"win": 1, "lost": 0, "battle_sets": {"Spirit Shackle_Shadow Sneak_XSpeed": {"win": 1, "lost": 0}}}, "DISapple": {"win": 2, "lost": 0, "battle_sets": {"Spirit Shackle_Shadow Sneak_EjectButton": {"win": 2, "lost": 0}}}}, "battle_sets": {"Spirit Shackle_Shadow Sneak_EjectButton": {"win": 4, "lost": 3}, "Spirit Shackle_Shadow Sneak_XSpeed": {"win": 4, "lost": 1}}}, "Charizard": {"win": 10, "lost": 3, "players": {"YASHRANGERA": {"win": 1, "lost": 1, "battle_sets": {"Flamethrower_Fire Blast_Purify": {"win": 1, "lost": 1}}}, "KellyJT_\u9670\u967d": {"win": 2, "lost": 1, "battle_sets": {"Flamethrower_Fire Blast_Purify": {"win": 2, "lost": 1}}}, "MW\u30fbTwoKiiL": {"win": 2, "lost": 0, "battle_sets": {"Flamethrower_Fire Blast_XAttack": {"win": 2, "lost": 0}}}, "KylukIFood": {"win": 2, "lost": 0, "battle_sets": {"Flamethrower_Fire Blast_XAttack": {"win": 2, "lost": 0}}}, "ttvGhatIue": {"win": 1, "lost": 0, "battle_sets": {"Flamethrower_Fire Blast_XSpeed": {"win": 1, "lost": 0}}}, "OG\u3072Ice": {"win": 1, "lost": 0, "battle_sets": {"Flamethrower_Flare Blitz_XSpeed": {"win": 1, "lost": 0}}}, "I'mSnow:D": {"win": 0, "lost": 1, "battle_sets": {"Flamethrower_Fire Blast_Purify": {"win": 0, "lost": 1}}}, "Ray\u00fd": {"win": 1, "lost": 0, "battle_sets": {"Flamethrower_Flare Blitz_Purify": {"win": 1, "lost": 0}}}}, "battle_sets": {"Flamethrower_Fire Blast_Purify": {"win": 3, "lost": 3}, "Flamethrower_Fire Blast_XAttack": {"win": 4, "lost": 0}, "Flamethrower_Fire Blast_XSpeed": {"win": 1, "lost": 0}, "Flamethrower_Flare Blitz_XSpeed": {"win": 1, "lost": 0}, "Flamethrower_Flare Blitz_Purify": {"win": 1, "lost": 0}}}, "Scizor": {"win": 34, "lost": 13, "players": {"YASHRANGERA": {"win": 2, "lost": 1, "battle_sets": {"Bullet Punch_Swords Dance_Purify": {"win": 2, "lost": 1}}}, "\u9006\u5f35\u308a\u30e4\u4e00\u30c9": {"win": 5, "lost": 3, "battle_sets": {"Bullet Punch_Double Hit_Purify": {"win": 3, "lost": 2}, "Bullet Punch_Swords Dance_Purify": {"win": 1, "lost": 0}, "Bullet Punch_Double Hit_Potion": {"win": 1, "lost": 1}}}, "KylukIFood": {"win": 2, "lost": 0, "battle_sets": {"Bullet Punch_Swords Dance_XSpeed": {"win": 2, "lost": 0}}}, "ttvGhatIue": {"win": 5, "lost": 0, "battle_sets": {"Bullet Punch_Swords Dance_XSpeed": {"win": 5, "lost": 0}}}, "kxm\u00e0": {"win": 2, "lost": 0, "battle_sets": {"Bullet Punch_Swords Dance_XSpeed": {"win": 2, "lost": 0}}}, "OG\u3072Ice": {"win": 3, "lost": 0, "battle_sets": {"Bullet Punch_Swords Dance_XSpeed": {"win": 1, "lost": 0}, "Dual Wingbeat_Double Hit_XSpeed": {"win": 2, "lost": 0}}}, "Ansh_Blade": {"win": 0, "lost": 1, "battle_sets": {"Bullet Punch_Double Hit_Purify": {"win": 0, "lost": 1}}}, "Metallic\u30c4": {"win": 1, "lost": 0, "battle_sets": {"Bullet Punch_Swords Dance_Purify": {"win": 1, "lost": 0}}}, "RB_\u3086\u3081\u306b\u3083": {"win": 1, "lost": 1, "battle_sets": {"Bullet Punch_Swords Dance_Purify": {"win": 1, "lost": 1}}}, "RNT.BlizzarD": {"win": 1, "lost": 2, "battle_sets": {"Dual Wingbeat_Double Hit_XSpeed": {"win": 1, "lost": 2}}}, "H\u016bman": {"win": 1, "lost": 0, "battle_sets": {"Bullet Punch_Swords Dance_Purify": {"win": 1, "lost": 0}}}, "Edgy07": {"win": 3, "lost": 1, "battle_sets": {"Bullet Punch_Double Hit_Purify": {"win": 2, "lost": 1}, "Dual Wingbeat_Double Hit_Purify": {"win": 1, "lost": 0}}}, "Sasuk\u00e9?": {"win": 2, "lost": 0, "battle_sets": {"Bullet Punch_Swords Dance_XAttack": {"win": 2, "lost": 0}}}, "TtvPikaGod22": {"win": 4, "lost": 1, "battle_sets": {"Bullet Punch_Swords Dance_Purify": {"win": 4, "lost": 1}}}, "RNT\u30fbNovaa": {"win": 2, "lost": 3, "battle_sets": {"Dual Wingbeat_Swords Dance_XSpeed": {"win": 1, "lost": 2}, "Bullet Punch_Swords Dance_XSpeed": {"win": 1, "lost": 1}}}}, "battle_sets": {"Bullet Punch_Swords Dance_Purify": {"win": 10, "lost": 3}, "Bullet Punch_Double Hit_Purify": {"win": 5, "lost": 4}, "Bullet Punch_Double Hit_Potion": {"win": 1, "lost": 1}, "Bullet Punch_Swords Dance_XSpeed": {"win": 11, "lost": 1}, "Dual Wingbeat_Double Hit_XSpeed": {"win": 3, "lost": 2}, "Dual Wingbeat_Double Hit_Purify": {"win": 1, "lost": 0}, "Bullet Punch_Swords Dance_XAttack": {"win": 2, "lost": 0}, "Dual Wingbeat_Swords Dance_XSpeed": {"win": 1, "lost": 2}}}, "Lucario": {"win": 30, "lost": 19, "players": {"YASHRANGERA": {"win": 1, "lost": 3, "battle_sets": {"Extreme Speed_Bone Rush_Purify": {"win": 1, "lost": 2}, "Power-Up Punch_Close Combat_XAttack": {"win": 0, "lost": 1}}}, "Edgy777": {"win": 1, "lost": 1, "battle_sets": {"Extreme Speed_Bone Rush_XAttack": {"win": 1, "lost": 0}, "Power-Up Punch_Bone Rush_XSpeed": {"win": 0, "lost": 1}}}, "\u30eb\u529b\u30ea\u30aa\u4e2d\u6bd2": {"win": 3, "lost": 0, "battle_sets": {"Power-Up Punch_Close Combat_Potion": {"win": 3, "lost": 0}}}, "KylukIFood": {"win": 3, "lost": 0, "battle_sets": {"Power-Up Punch_Close Combat_XSpeed": {"win": 3, "lost": 0}}}, "S\u4e28MarKGod": {"win": 9, "lost": 3, "battle_sets": {"Extreme Speed_Bone Rush_Purify": {"win": 7, "lost": 2}, "Power-Up Punch_Close Combat_EjectButton": {"win": 1, "lost": 1}, "Extreme Speed_Bone Rush_EjectButton": {"win": 1, "lost": 0}}}, "RS_\u795e\u901f\u30de\u30f3": {"win": 0, "lost": 1, "battle_sets": {"Power-Up Punch_Bone Rush_EjectButton": {"win": 0, "lost": 1}}}, "CPH>NARUTO": {"win": 5, "lost": 6, "battle_sets": {"Extreme Speed_Bone Rush_Purify": {"win": 4, "lost": 6}, "Extreme Speed_Bone Rush_XSpeed": {"win": 1, "lost": 0}}}, "Ansh_Blade": {"win": 0, "lost": 1, "battle_sets": {"Extreme Speed_Bone Rush_Purify": {"win": 0, "lost": 1}}}, "OMO\u30e1Zoe": {"win": 1, "lost": 1, "battle_sets": {"Extreme Speed_Bone Rush_Purify": {"win": 1, "lost": 1}}}, "RNT\u30fbNovaa": {"win": 0, "lost": 1, "battle_sets": {"Extreme Speed_Bone Rush_Purify": {"win": 0, "lost": 1}}}, "DISapple": {"win": 0, "lost": 1, "battle_sets": {"Extreme Speed_Bone Rush_Purify": {"win": 0, "lost": 1}}}, "\u3053\u3053\u3042\u3063\u305f": {"win": 7, "lost": 1, "battle_sets": {"Power-Up Punch_Close Combat_Potion": {"win": 7, "lost": 1}}}}, "battle_sets": {"Extreme Speed_Bone Rush_Purify": {"win": 13, "lost": 14}, "Power-Up Punch_Close Combat_XAttack": {"win": 0, "lost": 1}, "Extreme Speed_Bone Rush_XAttack": {"win": 1, "lost": 0}, "Power-Up Punch_Bone Rush_XSpeed": {"win": 0, "lost": 1}, "Power-Up Punch_Close Combat_Potion": {"win": 10, "lost": 1}, "Power-Up Punch_Close Combat_XSpeed": {"win": 3, "lost": 0}, "Power-Up Punch_Close Combat_EjectButton": {"win": 1, "lost": 1}, "Extreme Speed_Bone Rush_EjectButton": {"win": 1, "lost": 0}, "Power-Up Punch_Bone Rush_EjectButton": {"win": 0, "lost": 1}, "Extreme Speed_Bone Rush_XSpeed": {"win": 1, "lost": 0}}}, "Delphox": {"win": 11, "lost": 8, "players": {"YASHRANGERA": {"win": 1, "lost": 0, "battle_sets": {"Mystical Fire_Flame Charge_EjectButton": {"win": 1, "lost": 0}}}, "Teerawatb": {"win": 0, "lost": 1, "battle_sets": {"Mystical Fire_Flame Charge_EjectButton": {"win": 0, "lost": 1}}}, "Edgy777": {"win": 2, "lost": 0, "battle_sets": {"Mystical Fire_Flame Charge_Purify": {"win": 2, "lost": 0}}}, "TE\u30fbBarnW": {"win": 1, "lost": 0, "battle_sets": {"Mystical Fire_Flame Charge_EjectButton": {"win": 1, "lost": 0}}}, "lRelentless": {"win": 2, "lost": 2, "battle_sets": {"Mystical Fire_Flame Charge_XSpeed": {"win": 2, "lost": 2}}}, "KylukIFood": {"win": 1, "lost": 0, "battle_sets": {"Mystical Fire_Flame Charge_XSpeed": {"win": 1, "lost": 0}}}, "Metallic\u30c4": {"win": 3, "lost": 2, "battle_sets": {"Mystical Fire_Flame Charge_Purify": {"win": 3, "lost": 2}}}, "RNT.BlizzarD": {"win": 0, "lost": 1, "battle_sets": {"Mystical Fire_Flame Charge_EjectButton": {"win": 0, "lost": 1}}}, "Edgy07": {"win": 1, "lost": 1, "battle_sets": {"Mystical Fire_Flame Charge_EjectButton": {"win": 1, "lost": 1}}}, "SF\u00d7GeasSind": {"win": 0, "lost": 1, "battle_sets": {"Mystical Fire_Flame Charge_EjectButton": {"win": 0, "lost": 1}}}}, "battle_sets": {"Mystical Fire_Flame Charge_EjectButton": {"win": 3, "lost": 4}, "Mystical Fire_Flame Charge_Purify": {"win": 5, "lost": 2}, "Mystical Fire_Flame Charge_XSpeed": {"win": 3, "lost": 2}}}, "Absol": {"win": 49, "lost": 16, "players": {"Teerawatb": {"win": 0, "lost": 1, "battle_sets": {"Pursuit_Sucker Punch_EjectButton": {"win": 0, "lost": 1}}}, "Edgy777": {"win": 1, "lost": 0, "battle_sets": {"Pursuit_Sucker Punch_XAttack": {"win": 1, "lost": 0}}}, "TE\u30fbBarnW": {"win": 1, "lost": 0, "battle_sets": {"Pursuit_Sucker Punch_Purify": {"win": 1, "lost": 0}}}, "winnnnyyypps": {"win": 0, "lost": 1, "battle_sets": {"Night Slash_Sucker Punch_EjectButton": {"win": 0, "lost": 1}}}, "\ucf54\ubbf8_\u3053\u307f": {"win": 0, "lost": 1, "battle_sets": {"Pursuit_Sucker Punch_EjectButton": {"win": 0, "lost": 1}}}, "\u30a2\u30ce\u30fc\u30ea\u30ab": {"win": 1, "lost": 0, "battle_sets": {"Pursuit_Sucker Punch_EjectButton": {"win": 1, "lost": 0}}}, "\u30eb\u529b\u30ea\u30aa\u4e2d\u6bd2": {"win": 18, "lost": 6, "battle_sets": {"Pursuit_Sucker Punch_EjectButton": {"win": 17, "lost": 6}, "Night Slash_Psycho Cut_EjectButton": {"win": 1, "lost": 0}}}, "KylukIFood": {"win": 1, "lost": 0, "battle_sets": {"Pursuit_Sucker Punch_Ganrao": {"win": 1, "lost": 0}}}, "\u3072\u308d\u307d\u3059\u305f": {"win": 6, "lost": 3, "battle_sets": {"Pursuit_Sucker Punch_EjectButton": {"win": 6, "lost": 3}}}, "RS_\u795e\u901f\u30de\u30f3": {"win": 0, "lost": 1, "battle_sets": {"Pursuit_Sucker Punch_EjectButton": {"win": 0, "lost": 1}}}, "I'mSnow:D": {"win": 8, "lost": 1, "battle_sets": {"Pursuit_Sucker Punch_EjectButton": {"win": 7, "lost": 1}, "Night Slash_Psycho Cut_EjectButton": {"win": 1, "lost": 0}}}, "\ub2e4\ubbf8_\u30d2\u30e1\u00b0": {"win": 8, "lost": 2, "battle_sets": {"Pursuit_Sucker Punch_EjectButton": {"win": 8, "lost": 2}}}, "18V_piwai": {"win": 2, "lost": 0, "battle_sets": {"Night Slash_Psycho Cut_EjectButton": {"win": 2, "lost": 0}}}, "RNT.BlizzarD": {"win": 1, "lost": 0, "battle_sets": {"Pursuit_Sucker Punch_EjectButton": {"win": 1, "lost": 0}}}, "TtvPikaGod22": {"win": 1, "lost": 0, "battle_sets": {"Night Slash_Psycho Cut_EjectButton": {"win": 1, "lost": 0}}}, "DISapple": {"win": 1, "lost": 0, "battle_sets": {"Pursuit_Sucker Punch_EjectButton": {"win": 1, "lost": 0}}}}, "battle_sets": {"Pursuit_Sucker Punch_EjectButton": {"win": 41, "lost": 15}, "Pursuit_Sucker Punch_XAttack": {"win": 1, "lost": 0}, "Pursuit_Sucker Punch_Purify": {"win": 1, "lost": 0}, "Night Slash_Sucker Punch_EjectButton": {"win": 0, "lost": 1}, "Night Slash_Psycho Cut_EjectButton": {"win": 5, "lost": 0}, "Pursuit_Sucker Punch_Ganrao": {"win": 1, "lost": 0}}}, "Cinderace": {"win": 13, "lost": 3, "players": {"Teerawatb": {"win": 2, "lost": 1, "battle_sets": {"Blaze Kick_Flame Charge_EjectButton": {"win": 2, "lost": 1}}}, "lRelentless": {"win": 1, "lost": 0, "battle_sets": {"Blaze Kick_Feint_EjectButton": {"win": 1, "lost": 0}}}, "ttvGhatIue": {"win": 1, "lost": 0, "battle_sets": {"Blaze Kick_Flame Charge_Purify": {"win": 1, "lost": 0}}}, "INF\u30fbAnemo": {"win": 5, "lost": 1, "battle_sets": {"Blaze Kick_Flame Charge_Purify": {"win": 5, "lost": 1}}}, "RNT.BlizzarD": {"win": 1, "lost": 0, "battle_sets": {"Blaze Kick_Flame Charge_XAttack": {"win": 1, "lost": 0}}}, "IX\u30fbSherlock": {"win": 2, "lost": 1, "battle_sets": {"Blaze Kick_Flame Charge_EjectButton": {"win": 2, "lost": 0}, "Blaze Kick_Feint_EjectButton": {"win": 0, "lost": 1}}}, "Edgy07": {"win": 1, "lost": 0, "battle_sets": {"Blaze Kick_Flame Charge_XAttack": {"win": 1, "lost": 0}}}}, "battle_sets": {"Blaze Kick_Flame Charge_EjectButton": {"win": 4, "lost": 1}, "Blaze Kick_Feint_EjectButton": {"win": 1, "lost": 1}, "Blaze Kick_Flame Charge_Purify": {"win": 6, "lost": 1}, "Blaze Kick_Flame Charge_XAttack": {"win": 2, "lost": 0}}}, "Venusaur": {"win": 2, "lost": 0, "players": {"Teerawatb": {"win": 1, "lost": 0, "battle_sets": {"Giga Drain_Petal Dance_Purify": {"win": 1, "lost": 0}}}, "\u307f\u305f\u3089\u3057girl": {"win": 1, "lost": 0, "battle_sets": {"Sludge Bomb_Solar Beam_XSpeed": {"win": 1, "lost": 0}}}}, "battle_sets": {"Giga Drain_Petal Dance_Purify": {"win": 1, "lost": 0}, "Sludge Bomb_Solar Beam_XSpeed": {"win": 1, "lost": 0}}}, "Gengar": {"win": 6, "lost": 3, "players": {"Teerawatb": {"win": 2, "lost": 1, "battle_sets": {"Shadow Ball_Dream Eater_EjectButton": {"win": 2, "lost": 1}}}, "CeS\u68a6KiD": {"win": 2, "lost": 0, "battle_sets": {"Sludge Bomb_Hex_Purify": {"win": 2, "lost": 0}}}, "\u30a2\u30ce\u30fc\u30ea\u30ab": {"win": 0, "lost": 1, "battle_sets": {"Shadow Ball_Dream Eater_EjectButton": {"win": 0, "lost": 1}}}, "18V_piwai": {"win": 0, "lost": 1, "battle_sets": {"Sludge Bomb_Hex_Purify": {"win": 0, "lost": 1}}}, "Edgy07": {"win": 2, "lost": 0, "battle_sets": {"Shadow Ball_Dream Eater_EjectButton": {"win": 2, "lost": 0}}}}, "battle_sets": {"Shadow Ball_Dream Eater_EjectButton": {"win": 4, "lost": 2}, "Sludge Bomb_Hex_Purify": {"win": 2, "lost": 1}}}, "Greninja": {"win": 57, "lost": 27, "players": {"Teerawatb": {"win": 1, "lost": 0, "battle_sets": {"Surf_Smokescreen_XAttack": {"win": 1, "lost": 0}}}, "winnnnyyypps": {"win": 15, "lost": 5, "battle_sets": {"Surf_Smokescreen_XAttack": {"win": 15, "lost": 5}}}, "lRelentless": {"win": 1, "lost": 1, "battle_sets": {"Surf_Smokescreen_Purify": {"win": 1, "lost": 1}}}, "I'mSnow:D": {"win": 1, "lost": 3, "battle_sets": {"Surf_Smokescreen_XAttack": {"win": 1, "lost": 3}}}, "S4L-": {"win": 9, "lost": 5, "battle_sets": {"Surf_Smokescreen_XAttack": {"win": 9, "lost": 5}}}, "INF\u30fbAnemo": {"win": 3, "lost": 2, "battle_sets": {"Surf_Smokescreen_EjectButton": {"win": 3, "lost": 2}}}, "18V_piwai": {"win": 1, "lost": 0, "battle_sets": {"Surf_Smokescreen_XAttack": {"win": 1, "lost": 0}}}, "RNT.BlizzarD": {"win": 1, "lost": 1, "battle_sets": {"Surf_Smokescreen_XAttack": {"win": 1, "lost": 1}}}, "IX\u30fbSherlock": {"win": 0, "lost": 1, "battle_sets": {"Surf_Smokescreen_XAttack": {"win": 0, "lost": 1}}}, "Edgy07": {"win": 1, "lost": 1, "battle_sets": {"Surf_Smokescreen_XAttack": {"win": 1, "lost": 1}}}, "S8ul\u30fbLegend": {"win": 13, "lost": 2, "battle_sets": {"Surf_Smokescreen_XAttack": {"win": 13, "lost": 2}}}, "TTVTroubllex": {"win": 9, "lost": 4, "battle_sets": {"Surf_Smokescreen_XAttack": {"win": 9, "lost": 4}}}, "Ray\u00fd": {"win": 1, "lost": 0, "battle_sets": {"Surf_Smokescreen_Purify": {"win": 1, "lost": 0}}}, "DISapple": {"win": 1, "lost": 2, "battle_sets": {"Surf_Smokescreen_Purify": {"win": 1, "lost": 2}}}}, "battle_sets": {"Surf_Smokescreen_XAttack": {"win": 51, "lost": 22}, "Surf_Smokescreen_Purify": {"win": 3, "lost": 3}, "Surf_Smokescreen_EjectButton": {"win": 3, "lost": 2}}}, "Machamp": {"win": 5, "lost": 1, "players": {"Edgy777": {"win": 2, "lost": 0, "battle_sets": {"Cross Chop_Dynamic Punch_EjectButton": {"win": 2, "lost": 0}}}, "S\u4e28MarKGod": {"win": 2, "lost": 0, "battle_sets": {"Close Combat_Dynamic Punch_EjectButton": {"win": 2, "lost": 0}}}, "Twist3xd": {"win": 1, "lost": 0, "battle_sets": {"Cross Chop_Dynamic Punch_EjectButton": {"win": 1, "lost": 0}}}, "OMO\u30e1Zoe": {"win": 0, "lost": 1, "battle_sets": {"Cross Chop_Dynamic Punch_XSpeed": {"win": 0, "lost": 1}}}}, "battle_sets": {"Cross Chop_Dynamic Punch_EjectButton": {"win": 3, "lost": 0}, "Close Combat_Dynamic Punch_EjectButton": {"win": 2, "lost": 0}, "Cross Chop_Dynamic Punch_XSpeed": {"win": 0, "lost": 1}}}, "Buzzwole": {"win": 8, "lost": 3, "players": {"Edgy777": {"win": 1, "lost": 0, "battle_sets": {"Lunge_Leech Life_XSpeed": {"win": 1, "lost": 0}}}, "RNT\u30fbVulcan": {"win": 4, "lost": 2, "battle_sets": {"Smack Down_Leech Life_EjectButton": {"win": 4, "lost": 2}}}, "TheRedluvTTV": {"win": 2, "lost": 0, "battle_sets": {"Smack Down_Leech Life_XSpeed": {"win": 2, "lost": 0}}}, "99ASH99": {"win": 1, "lost": 0, "battle_sets": {"Smack Down_Leech Life_XSpeed": {"win": 1, "lost": 0}}}, "Ray\u00fd": {"win": 0, "lost": 1, "battle_sets": {"Smack Down_Leech Life_EjectButton": {"win": 0, "lost": 1}}}}, "battle_sets": {"Lunge_Leech Life_XSpeed": {"win": 1, "lost": 0}, "Smack Down_Leech Life_EjectButton": {"win": 4, "lost": 3}, "Smack Down_Leech Life_XSpeed": {"win": 3, "lost": 0}}}, "Azumarill": {"win": 77, "lost": 37, "players": {"Edgy777": {"win": 0, "lost": 1, "battle_sets": {"Water Pulse_Aqua Tail_XSpeed": {"win": 0, "lost": 1}}}, "TE\u30fbBarnW": {"win": 3, "lost": 0, "battle_sets": {"Water Pulse_Aqua Tail_XSpeed": {"win": 3, "lost": 0}}}, "\ucf54\ubbf8_\u3053\u307f": {"win": 1, "lost": 0, "battle_sets": {"Water Pulse_Aqua Tail_XSpeed": {"win": 1, "lost": 0}}}, "pardisfat": {"win": 1, "lost": 1, "battle_sets": {"Water Pulse_Aqua Tail_Potion": {"win": 1, "lost": 1}}}, "KellyJT_\u9670\u967d": {"win": 4, "lost": 0, "battle_sets": {"Water Pulse_Aqua Tail_EjectButton": {"win": 1, "lost": 0}, "Water Pulse_Aqua Tail_XAttack": {"win": 3, "lost": 0}}}, "\u30a2\u30ce\u30fc\u30ea\u30ab": {"win": 1, "lost": 2, "battle_sets": {"Water Pulse_Aqua Tail_Purify": {"win": 1, "lost": 2}}}, "S2_\u82a5\u5ddd\u308a\u305c": {"win": 3, "lost": 1, "battle_sets": {"Water Pulse_Aqua Tail_XAttack": {"win": 3, "lost": 1}}}, "\u307f\u305f\u3089\u3057girl": {"win": 5, "lost": 2, "battle_sets": {"Water Pulse_Aqua Tail_EjectButton": {"win": 2, "lost": 1}, "Water Pulse_Aqua Tail_Purify": {"win": 3, "lost": 1}}}, "MW\u30fbTwoKiiL": {"win": 1, "lost": 1, "battle_sets": {"Play Rough_Aqua Tail_XSpeed": {"win": 1, "lost": 1}}}, "mare__": {"win": 1, "lost": 0, "battle_sets": {"Water Pulse_Aqua Tail_XSpeed": {"win": 1, "lost": 0}}}, "Evek": {"win": 1, "lost": 0, "battle_sets": {"Water Pulse_Aqua Tail_Purify": {"win": 1, "lost": 0}}}, "Galleta04": {"win": 12, "lost": 3, "battle_sets": {"Water Pulse_Aqua Tail_XAttack": {"win": 12, "lost": 3}}}, "INF\u30fbAramis": {"win": 1, "lost": 0, "battle_sets": {"Water Pulse_Aqua Tail_XSpeed": {"win": 1, "lost": 0}}}, "KylukIFood": {"win": 3, "lost": 3, "battle_sets": {"Water Pulse_Aqua Tail_XSpeed": {"win": 3, "lost": 3}}}, "S\u4e28MarKGod": {"win": 2, "lost": 0, "battle_sets": {"Water Pulse_Aqua Tail_XSpeed": {"win": 2, "lost": 0}}}, "I'mSnow:D": {"win": 1, "lost": 0, "battle_sets": {"Water Pulse_Aqua Tail_XSpeed": {"win": 1, "lost": 0}}}, "Romfndq": {"win": 6, "lost": 9, "battle_sets": {"Water Pulse_Aqua Tail_XSpeed": {"win": 4, "lost": 7}, "Play Rough_Aqua Tail_XSpeed": {"win": 0, "lost": 1}, "Water Pulse_Aqua Tail_EjectButton": {"win": 2, "lost": 1}}}, "\u5b9f\u306f\u30d4\u30af\u30bd\u30eb": {"win": 2, "lost": 0, "battle_sets": {"Water Pulse_Aqua Tail_Purify": {"win": 2, "lost": 0}}}, "Ansh_Blade": {"win": 1, "lost": 3, "battle_sets": {"Water Pulse_Aqua Tail_XSpeed": {"win": 1, "lost": 3}}}, "OMO\u30e1Zoe": {"win": 0, "lost": 1, "battle_sets": {"Water Pulse_Aqua Tail_XAttack": {"win": 0, "lost": 1}}}, "KimChiCarry": {"win": 11, "lost": 3, "battle_sets": {"Water Pulse_Aqua Tail_XSpeed": {"win": 11, "lost": 3}}}, "Sasuk\u00e9?": {"win": 8, "lost": 4, "battle_sets": {"Water Pulse_Aqua Tail_XSpeed": {"win": 7, "lost": 4}, "Play Rough_Whirlpool_XSpeed": {"win": 1, "lost": 0}}}, "LEOJI.": {"win": 3, "lost": 0, "battle_sets": {"Water Pulse_Whirlpool_XSpeed": {"win": 1, "lost": 0}, "Water Pulse_Aqua Tail_XSpeed": {"win": 2, "lost": 0}}}, "RNT\u30fbNovaa": {"win": 5, "lost": 3, "battle_sets": {"Water Pulse_Aqua Tail_XSpeed": {"win": 4, "lost": 3}, "Play Rough_Aqua Tail_XSpeed": {"win": 1, "lost": 0}}}, "SF\u00d7GeasSind": {"win": 1, "lost": 0, "battle_sets": {"Water Pulse_Aqua Tail_Purify": {"win": 1, "lost": 0}}}}, "battle_sets": {"Water Pulse_Aqua Tail_XSpeed": {"win": 41, "lost": 24}, "Water Pulse_Aqua Tail_Potion": {"win": 1, "lost": 1}, "Water Pulse_Aqua Tail_EjectButton": {"win": 5, "lost": 2}, "Water Pulse_Aqua Tail_XAttack": {"win": 18, "lost": 5}, "Water Pulse_Aqua Tail_Purify": {"win": 8, "lost": 3}, "Play Rough_Aqua Tail_XSpeed": {"win": 2, "lost": 2}, "Play Rough_Whirlpool_XSpeed": {"win": 1, "lost": 0}, "Water Pulse_Whirlpool_XSpeed": {"win": 1, "lost": 0}}}, "Glaceon": {"win": 44, "lost": 17, "players": {"SilentSheeps": {"win": 1, "lost": 1, "battle_sets": {"Icy Wind_Freeze-Dry_XAttack": {"win": 1, "lost": 1}}}, "winnnnyyypps": {"win": 1, "lost": 1, "battle_sets": {"Icy Wind_Freeze-Dry_EjectButton": {"win": 1, "lost": 1}}}, "pardisfat": {"win": 1, "lost": 1, "battle_sets": {"Icy Wind_Freeze-Dry_EjectButton": {"win": 1, "lost": 1}}}, "lRelentless": {"win": 3, "lost": 0, "battle_sets": {"Icy Wind_Freeze-Dry_XSpeed": {"win": 3, "lost": 0}}}, "Suntahj": {"win": 15, "lost": 1, "battle_sets": {"Icy Wind_Freeze-Dry_XAttack": {"win": 15, "lost": 1}}}, "kxm\u00e0": {"win": 8, "lost": 2, "battle_sets": {"Icy Wind_Freeze-Dry_XSpeed": {"win": 8, "lost": 2}}}, "KimChiCarry": {"win": 0, "lost": 1, "battle_sets": {"Icicle Spear_Ice Shard_XSpeed": {"win": 0, "lost": 1}}}, "Edgy07": {"win": 1, "lost": 0, "battle_sets": {"Icy Wind_Freeze-Dry_XSpeed": {"win": 1, "lost": 0}}}, "\u3074\u3093\u3053YT": {"win": 1, "lost": 2, "battle_sets": {"Icy Wind_Freeze-Dry_Purify": {"win": 1, "lost": 2}}}, "TMB\u30fbOsIrIs": {"win": 1, "lost": 5, "battle_sets": {"Icy Wind_Freeze-Dry_XSpeed": {"win": 1, "lost": 5}}}, "Ray\u00fd": {"win": 11, "lost": 3, "battle_sets": {"Icy Wind_Freeze-Dry_XAttack": {"win": 11, "lost": 3}}}, "DISapple": {"win": 1, "lost": 0, "battle_sets": {"Icy Wind_Freeze-Dry_XSpeed": {"win": 1, "lost": 0}}}}, "battle_sets": {"Icy Wind_Freeze-Dry_XAttack": {"win": 27, "lost": 5}, "Icy Wind_Freeze-Dry_EjectButton": {"win": 2, "lost": 2}, "Icy Wind_Freeze-Dry_XSpeed": {"win": 14, "lost": 7}, "Icicle Spear_Ice Shard_XSpeed": {"win": 0, "lost": 1}, "Icy Wind_Freeze-Dry_Purify": {"win": 1, "lost": 2}}}, "Cramorant": {"win": 4, "lost": 4, "players": {"CeS\u68a6KiD": {"win": 1, "lost": 0, "battle_sets": {"Dive_Air Slash_EjectButton": {"win": 1, "lost": 0}}}, "OMO\u30e1Phoenix": {"win": 1, "lost": 0, "battle_sets": {"Dive_Air Slash_EjectButton": {"win": 1, "lost": 0}}}, "Galleta04": {"win": 1, "lost": 0, "battle_sets": {"Dive_Air Slash_EjectButton": {"win": 1, "lost": 0}}}, "ttvGhatIue": {"win": 0, "lost": 1, "battle_sets": {"Dive_Air Slash_EjectButton": {"win": 0, "lost": 1}}}, "YORU04": {"win": 0, "lost": 3, "battle_sets": {"Dive_Air Slash_EjectButton": {"win": 0, "lost": 3}}}, "Ray\u00fd": {"win": 1, "lost": 0, "battle_sets": {"Dive_Air Slash_EjectButton": {"win": 1, "lost": 0}}}}, "battle_sets": {"Dive_Air Slash_EjectButton": {"win": 4, "lost": 4}}}, "Clefable": {"win": 68, "lost": 22, "players": {"TE\u30fbBarnW": {"win": 13, "lost": 4, "battle_sets": {"Moonlight_Gravity_XSpeed": {"win": 13, "lost": 3}, "Moonlight_Follow Me_XSpeed": {"win": 0, "lost": 1}}}, "mare__": {"win": 1, "lost": 2, "battle_sets": {"Moonlight_Gravity_XSpeed": {"win": 1, "lost": 2}}}, "VER\u30fbDaniel\u025e": {"win": 3, "lost": 1, "battle_sets": {"Moonlight_Gravity_XSpeed": {"win": 3, "lost": 1}}}, "OG\u3072Ice": {"win": 10, "lost": 0, "battle_sets": {"Moonlight_Gravity_Gear": {"win": 10, "lost": 0}}}, "H\u016bman": {"win": 8, "lost": 1, "battle_sets": {"Moonlight_Gravity_XSpeed": {"win": 8, "lost": 1}}}, "RNT\u30fbVulcan": {"win": 1, "lost": 0, "battle_sets": {"Moonlight_Gravity_XSpeed": {"win": 1, "lost": 0}}}, "Reckzz": {"win": 16, "lost": 2, "battle_sets": {"Moonlight_Gravity_Potion": {"win": 16, "lost": 2}}}, "\u3074\u3093\u3053YT": {"win": 11, "lost": 8, "battle_sets": {"Moonlight_Gravity_Gear": {"win": 11, "lost": 8}}}, "Schenti": {"win": 5, "lost": 4, "battle_sets": {"Moonlight_Gravity_XSpeed": {"win": 5, "lost": 4}}}}, "battle_sets": {"Moonlight_Gravity_XSpeed": {"win": 31, "lost": 11}, "Moonlight_Follow Me_XSpeed": {"win": 0, "lost": 1}, "Moonlight_Gravity_Gear": {"win": 21, "lost": 8}, "Moonlight_Gravity_Potion": {"win": 16, "lost": 2}}}, "Mamoswine": {"win": 23, "lost": 10, "players": {"KellyJT_\u9670\u967d": {"win": 0, "lost": 1, "battle_sets": {"Icicle Crash_High Horsepower_EjectButton": {"win": 0, "lost": 1}}}, "Gow_Xiang.": {"win": 10, "lost": 3, "battle_sets": {"Icicle Crash_High Horsepower_EjectButton": {"win": 10, "lost": 3}}}, "VER\u30fbDaniel\u025e": {"win": 1, "lost": 0, "battle_sets": {"Icicle Crash_High Horsepower_Potion": {"win": 1, "lost": 0}}}, "RNT\u30fbXesoL": {"win": 1, "lost": 1, "battle_sets": {"Icicle Crash_High Horsepower_XSpeed": {"win": 1, "lost": 1}}}, "Ansh_Blade": {"win": 1, "lost": 0, "battle_sets": {"Icicle Crash_High Horsepower_EjectButton": {"win": 1, "lost": 0}}}, "Metallic\u30c4": {"win": 2, "lost": 3, "battle_sets": {"Icicle Crash_High Horsepower_EjectButton": {"win": 2, "lost": 3}}}, "RNT\u30fbVulcan": {"win": 1, "lost": 1, "battle_sets": {"Icicle Crash_High Horsepower_XSpeed": {"win": 1, "lost": 1}}}, "TheRedluvTTV": {"win": 5, "lost": 1, "battle_sets": {"Icicle Crash_High Horsepower_Potion": {"win": 5, "lost": 1}}}, "DISapple": {"win": 2, "lost": 0, "battle_sets": {"Icicle Crash_High Horsepower_XSpeed": {"win": 2, "lost": 0}}}}, "battle_sets": {"Icicle Crash_High Horsepower_EjectButton": {"win": 13, "lost": 7}, "Icicle Crash_High Horsepower_Potion": {"win": 6, "lost": 1}, "Icicle Crash_High Horsepower_XSpeed": {"win": 4, "lost": 2}}}, "Snorlax": {"win": 13, "lost": 6, "players": {"VER\u30fbDaniel\u025e": {"win": 1, "lost": 0, "battle_sets": {"Heavy Slam_Block_XSpeed": {"win": 1, "lost": 0}}}, "RNT\u30fbXesoL": {"win": 0, "lost": 1, "battle_sets": {"Heavy Slam_Block_XSpeed": {"win": 0, "lost": 1}}}, "I'mSnow:D": {"win": 1, "lost": 0, "battle_sets": {"Heavy Slam_Block_XSpeed": {"win": 1, "lost": 0}}}, "Ansh_Blade": {"win": 0, "lost": 1, "battle_sets": {"Heavy Slam_Block_XSpeed": {"win": 0, "lost": 1}}}, "DG\u30fbGoku": {"win": 3, "lost": 0, "battle_sets": {"Heavy Slam_Block_XSpeed": {"win": 3, "lost": 0}}}, "Twist3xd": {"win": 5, "lost": 2, "battle_sets": {"Heavy Slam_Block_XSpeed": {"win": 5, "lost": 2}}}, "99ASH99": {"win": 1, "lost": 2, "battle_sets": {"Heavy Slam_Block_XSpeed": {"win": 1, "lost": 2}}}, "Ray\u00fd": {"win": 1, "lost": 0, "battle_sets": {"Flail_Block_XSpeed": {"win": 1, "lost": 0}}}, "DISapple": {"win": 1, "lost": 0, "battle_sets": {"Heavy Slam_Block_EjectButton": {"win": 1, "lost": 0}}}}, "battle_sets": {"Heavy Slam_Block_XSpeed": {"win": 11, "lost": 6}, "Flail_Block_XSpeed": {"win": 1, "lost": 0}, "Heavy Slam_Block_EjectButton": {"win": 1, "lost": 0}}}, "Dragonite": {"win": 3, "lost": 0, "players": {"KylukIFood": {"win": 1, "lost": 0, "battle_sets": {"Dragon Dance_Hyper Beam_Purify": {"win": 1, "lost": 0}}}, "S\u4e28MarKGod": {"win": 2, "lost": 0, "battle_sets": {"Dragon Dance_Hyper Beam_Purify": {"win": 2, "lost": 0}}}}, "battle_sets": {"Dragon Dance_Hyper Beam_Purify": {"win": 3, "lost": 0}}}, "Greedent": {"win": 7, "lost": 0, "players": {"KylukIFood": {"win": 1, "lost": 0, "battle_sets": {"Belch_Covet_Tail": {"win": 1, "lost": 0}}}, "ttvGhatIue": {"win": 2, "lost": 0, "battle_sets": {"Bullet Seed_Stuff Cheeks_XAttack": {"win": 1, "lost": 0}, "Belch_Covet_EjectButton": {"win": 1, "lost": 0}}}, "RS_\u795e\u901f\u30de\u30f3": {"win": 4, "lost": 0, "battle_sets": {"Belch_Covet_Potion": {"win": 4, "lost": 0}}}}, "battle_sets": {"Belch_Covet_Tail": {"win": 1, "lost": 0}, "Bullet Seed_Stuff Cheeks_XAttack": {"win": 1, "lost": 0}, "Belch_Covet_EjectButton": {"win": 1, "lost": 0}, "Belch_Covet_Potion": {"win": 4, "lost": 0}}}, "Blastoise": {"win": 2, "lost": 0, "players": {"ttvGhatIue": {"win": 1, "lost": 0, "battle_sets": {"Water Spout_Rapid Spin_EjectButton": {"win": 1, "lost": 0}}}, "RNT\u30fbXesoL": {"win": 1, "lost": 0, "battle_sets": {"Water Spout_Rapid Spin_EjectButton": {"win": 1, "lost": 0}}}}, "battle_sets": {"Water Spout_Rapid Spin_EjectButton": {"win": 2, "lost": 0}}}, "Wigglytuff": {"win": 5, "lost": 2, "players": {"RNT\u30fbXesoL": {"win": 0, "lost": 1, "battle_sets": {"Dazzling Gleam_Sing_XSpeed": {"win": 0, "lost": 1}}}, "INF\u30fbDrakenN": {"win": 3, "lost": 0, "battle_sets": {"Dazzling Gleam_Sing_XSpeed": {"win": 3, "lost": 0}}}, "RNT\u30fbVulcan": {"win": 1, "lost": 1, "battle_sets": {"Dazzling Gleam_Sing_EjectButton": {"win": 1, "lost": 1}}}, "LEOJI.": {"win": 1, "lost": 0, "battle_sets": {"Dazzling Gleam_Sing_XSpeed": {"win": 1, "lost": 0}}}}, "battle_sets": {"Dazzling Gleam_Sing_XSpeed": {"win": 4, "lost": 1}, "Dazzling Gleam_Sing_EjectButton": {"win": 1, "lost": 1}}}, "Gardevoir": {"win": 2, "lost": 0, "players": {"OG\u3072Ice": {"win": 1, "lost": 0, "battle_sets": {"Psychic_Psyshock_XSpeed": {"win": 1, "lost": 0}}}, "Edgy07": {"win": 1, "lost": 0, "battle_sets": {"Moonblast_Future Sight_EjectButton": {"win": 1, "lost": 0}}}}, "battle_sets": {"Psychic_Psyshock_XSpeed": {"win": 1, "lost": 0}, "Moonblast_Future Sight_EjectButton": {"win": 1, "lost": 0}}}, "Zeraora": {"win": 2, "lost": 0, "players": {"INF\u30fbDrakenN": {"win": 1, "lost": 0, "battle_sets": {"Volt Switch_Discharge_XSpeed": {"win": 1, "lost": 0}}}, "Edgy07": {"win": 1, "lost": 0, "battle_sets": {"Volt Switch_Discharge_XAttack": {"win": 1, "lost": 0}}}}, "battle_sets": {"Volt Switch_Discharge_XSpeed": {"win": 1, "lost": 0}, "Volt Switch_Discharge_XAttack": {"win": 1, "lost": 0}}}, "Pikachu": {"win": 4, "lost": 1, "players": {"Metallic\u30c4": {"win": 4, "lost": 1, "battle_sets": {"Electro Ball_Volt Tackle_EjectButton": {"win": 4, "lost": 1}}}}, "battle_sets": {"Electro Ball_Volt Tackle_EjectButton": {"win": 4, "lost": 1}}}, "Espeon": {"win": 1, "lost": 3, "players": {"Metallic\u30c4": {"win": 1, "lost": 3, "battle_sets": {"Stored Power_Future Sight_XSpeed": {"win": 0, "lost": 1}, "Psyshock_Future Sight_XSpeed": {"win": 1, "lost": 2}}}}, "battle_sets": {"Stored Power_Future Sight_XSpeed": {"win": 0, "lost": 1}, "Psyshock_Future Sight_XSpeed": {"win": 1, "lost": 2}}}, "Slowbro": {"win": 1, "lost": 0, "players": {"TheRedluvTTV": {"win": 1, "lost": 0, "battle_sets": {"Surf_Telekinesis_EjectButton": {"win": 1, "lost": 0}}}}, "battle_sets": {"Surf_Telekinesis_EjectButton": {"win": 1, "lost": 0}}}, "Garchomp": {"win": 1, "lost": 0, "players": {"Edgy07": {"win": 1, "lost": 0, "battle_sets": {"Dragon Rush_Dragon Claw_EjectButton": {"win": 1, "lost": 0}}}}, "battle_sets": {"Dragon Rush_Dragon Claw_EjectButton": {"win": 1, "lost": 0}}}, "Sylveon": {"win": 4, "lost": 1, "players": {"Edgy07": {"win": 3, "lost": 1, "battle_sets": {"Hyper Voice_Calm Mind_XSpeed": {"win": 3, "lost": 1}}}, "Ray\u00fd": {"win": 1, "lost": 0, "battle_sets": {"Mystical Fire_Calm Mind_Potion": {"win": 1, "lost": 0}}}}, "battle_sets": {"Hyper Voice_Calm Mind_XSpeed": {"win": 3, "lost": 1}, "Mystical Fire_Calm Mind_Potion": {"win": 1, "lost": 0}}}}, "match_count": 1133}